{"version":2,"kind":"Notebook","sha256":"9c6e1b132694e66b50f44bcb8b4cde4997dbf51d21ababf1a8f71be810d3f54c","slug":"courseware.assignment-rcm-feedback","location":"/courseware/assignment-rcm-feedback.ipynb","dependencies":[],"frontmatter":{"title":"Assignment: Feedbacks in the Radiative-Convective Model","content_includes_title":false,"kernelspec":{"name":"python3","display_name":"Python 3 (ipykernel)","language":"python"},"authors":[{"id":"brian-rose","nameParsed":{"literal":"Brian E. J. Rose","given":"Brian E. J.","family":"Rose"},"name":"Brian E. J. Rose","orcid":"0000-0002-9961-3821","email":"brose@albany.edu","affiliations":["UAlbany"],"url":"https://brian-rose.github.io","github":"brian-rose","bluesky":"@brianejrose.bsky.social","linkedin":"https://www.linkedin.com/in/brian-rose-37bb55106/"}],"doi":"https://doi.org/10.5281/zenodo.4265097","open_access":true,"license":{"content":{"id":"CC-BY-4.0","url":"https://creativecommons.org/licenses/by/4.0/","name":"Creative Commons Attribution 4.0 International","free":true,"CC":true}},"github":"https://github.com/brian-rose/ClimateLaboratoryBook","affiliations":[{"id":"UAlbany","name":"University at Albany (SUNY)","department":"Atmospheric and Environmental Sciences","url":"https://www.albany.edu/daes"}],"abbreviations":{"TOA":"Top of Atmosphere","SW":"Shortwave","LW":"Longwave","UV":"Ultraviolet","IR":"Infrared","OLR":"Outgoing Longwave Radiation","ASR":"Absorbed Shortwave Radiation","CC":"Clausius-Clapeyron","LWP":"Liquid Water Path","CRE":"Cloud Radiative Effect","ECS":"Equilibrium Climate Sensitivity","TCR":"Transient Climate Response","WV":"Water Vapor","LR":"Lapse Rate","LCL":"Lifting Condensation Level","LGM":"Last Glacial Maximum","MSE":"Moist Static Energy","AHT":"Atmospheric Heat Transport","OHT":"Ocean Heat Transport","THT":"Total Heat Transport","1D":"One-dimensional","2D":"Two-dimensional","3D":"Three-dimensional","lat":"latitude","lon":"longitude","ppm":"parts per million","ppmv":"parts per million by volume","hPa":"hectoPascals","Ma":"Millions of years","LHS":"Left hand side","RHS":"Right hand side","EBM":"Energy Balance Model","GCM":"Global Circulation Model","OGCM":"Ocean Global Circulation Model","AGCM":"Atmospheric Global Circulation Model","AOGCM":"Atmosphere-Ocean Global Circulation Model","CGCM":"Coupled Global Circulation Model","RC":"Radiative-Convective","RCM":"Radiative-Convective Model","RCE":"Radiative-Convective Equilibrium","SCM":"Single-Column Model","ESM":"Earth System Model","SD":"Statistical-Dynamical","EMIC":"Earth System Model of Intermediate Complexity","IAM":"Integrated Asessment Model","SOM":"Slab Ocean Model","CESM":"Community Earth System Model","CAM":"Community Atmosphere Model","POP":"Parallel Ocean Program","CLM":"Community Land Model","CICE":"Community Ice CodE","RRTMG":"Rapid Radiative Transfer Model","ODE":"Ordinary Differential Equation","PDE":"Partial Differential Equation","FTCS":"Forward Time, Centered Space","URL":"Uniform Research Locator","CMIP":"Coupled Model Intercomparison Project","IPCC":"Intergovernmental Panel on Climate Change","AR5":"Fifth Assessment Report","AR6":"Sixth Assessment Report","WG1":"Working Group 1","NCAR":"National Center for Atmospheric Research","AMS":"American Meteorological Society","NCEP":"National Centers for Environmental Prediction"},"numbering":{"title":{"offset":1}},"edit_url":"https://github.com/brian-rose/ClimateLaboratoryBook/blob/main/courseware/assignment-rcm-feedback.ipynb","exports":[{"format":"ipynb","filename":"assignment-rcm-feedback.ipynb","url":"/ClimateLaboratoryBook/build/assignment-rcm-feedb-dedfd4a1cbb6feaa560d8fa8c136de46.ipynb"}]},"widgets":{},"mdast":{"type":"root","children":[{"type":"block","kind":"notebook-content","children":[{"type":"paragraph","position":{"start":{"line":3,"column":1},"end":{"line":3,"column":1}},"children":[{"type":"text","value":"This notebook is part of ","position":{"start":{"line":3,"column":1},"end":{"line":3,"column":1}},"key":"PcwNaRl9A5"},{"type":"link","url":"https://brian-rose.github.io/ClimateLaboratoryBook","position":{"start":{"line":3,"column":1},"end":{"line":3,"column":1}},"children":[{"type":"text","value":"The Climate Laboratory","position":{"start":{"line":3,"column":1},"end":{"line":3,"column":1}},"key":"en1OJ8aL5y"}],"urlSource":"https://brian-rose.github.io/ClimateLaboratoryBook","key":"QTQpRRCXEI"},{"type":"text","value":" by ","position":{"start":{"line":3,"column":1},"end":{"line":3,"column":1}},"key":"xfjyNQvC5j"},{"type":"link","url":"http://www.atmos.albany.edu/facstaff/brose/index.html","position":{"start":{"line":3,"column":1},"end":{"line":3,"column":1}},"children":[{"type":"text","value":"Brian E. J. Rose","position":{"start":{"line":3,"column":1},"end":{"line":3,"column":1}},"key":"c0Ug8CTT61"}],"urlSource":"http://www.atmos.albany.edu/facstaff/brose/index.html","key":"tLKue8pFPw"},{"type":"text","value":", University at Albany.","position":{"start":{"line":3,"column":1},"end":{"line":3,"column":1}},"key":"kLIik55UWE"}],"key":"tWPDgCumtY"}],"key":"YR4EwrSWrw"},{"type":"block","kind":"notebook-content","children":[{"type":"heading","depth":2,"position":{"start":{"line":1,"column":1},"end":{"line":1,"column":1}},"children":[{"type":"text","value":"Learning goals","position":{"start":{"line":1,"column":1},"end":{"line":1,"column":1}},"key":"NgBQ0riakG"}],"identifier":"learning-goals","label":"Learning goals","html_id":"learning-goals","implicit":true,"key":"GhhSb1QnrJ"},{"type":"paragraph","position":{"start":{"line":3,"column":1},"end":{"line":3,"column":1}},"children":[{"type":"text","value":"Students completing this assignment will gain the following skills and concepts:","position":{"start":{"line":3,"column":1},"end":{"line":3,"column":1}},"key":"zE51NxBRWl"}],"key":"zgRWtV1ZmI"},{"type":"list","ordered":false,"spread":false,"position":{"start":{"line":5,"column":1},"end":{"line":9,"column":1}},"children":[{"type":"listItem","spread":true,"position":{"start":{"line":5,"column":1},"end":{"line":5,"column":1}},"children":[{"type":"text","value":"Familiarity with setting up and running a single-column Radiative-Convective Model using climlab","position":{"start":{"line":5,"column":1},"end":{"line":5,"column":1}},"key":"Dp5nuVzocZ"}],"key":"mVV2T9MAEs"},{"type":"listItem","spread":true,"position":{"start":{"line":6,"column":1},"end":{"line":6,"column":1}},"children":[{"type":"text","value":"Familiarity with plotting and interpreting vertical air temperature data on meteorological Skew-T charts","position":{"start":{"line":6,"column":1},"end":{"line":6,"column":1}},"key":"qSlJgPtrgL"}],"key":"OxPc9guiB2"},{"type":"listItem","spread":true,"position":{"start":{"line":7,"column":1},"end":{"line":7,"column":1}},"children":[{"type":"text","value":"Use of climlab to perform controlled parameter-sensitivity experiments","position":{"start":{"line":7,"column":1},"end":{"line":7,"column":1}},"key":"b3UeQVrYgL"}],"key":"omzwr8RolM"},{"type":"listItem","spread":true,"position":{"start":{"line":8,"column":1},"end":{"line":8,"column":1}},"children":[{"type":"text","value":"Understanding of the lapse rate feedback concept","position":{"start":{"line":8,"column":1},"end":{"line":8,"column":1}},"key":"Tmpsb5S3Ow"}],"key":"i8gDU6Eug4"},{"type":"listItem","spread":true,"position":{"start":{"line":9,"column":1},"end":{"line":9,"column":1}},"children":[{"type":"text","value":"Calcu","key":"BLAc7LcJ1w"},{"type":"abbreviation","title":"latitude","children":[{"type":"text","value":"lat","key":"Vy62ODKI9f"}],"key":"QJ3RKwMX9Z"},{"type":"text","value":"ion of radiative forcing and climate feedback parameters","key":"DWACzMPzhU"}],"key":"JlrRzl74Ue"}],"key":"Gt7SiUkKVw"}],"key":"J9xZjSdKjF"},{"type":"block","kind":"notebook-content","children":[{"type":"heading","depth":2,"position":{"start":{"line":1,"column":1},"end":{"line":1,"column":1}},"children":[{"type":"text","value":"Question 1","position":{"start":{"line":1,"column":1},"end":{"line":1,"column":1}},"key":"NRISSUjJJt"}],"identifier":"question-1","label":"Question 1","html_id":"question-1","implicit":true,"key":"ANPTaXwvnc"},{"type":"paragraph","position":{"start":{"line":3,"column":1},"end":{"line":3,"column":1}},"children":[{"type":"text","value":"Here you look at the effects of doubling CO","position":{"start":{"line":3,"column":1},"end":{"line":3,"column":1}},"key":"IcF4ysJP2t"},{"type":"inlineMath","value":"_2","position":{"start":{"line":3,"column":1},"end":{"line":3,"column":1}},"html":"<span class=\"katex\"><span class=\"katex-mathml\"><math xmlns=\"http://www.w3.org/1998/Math/MathML\"><semantics><mrow><msub><mrow></mrow><mn>2</mn></msub></mrow><annotation encoding=\"application/x-tex\">_2</annotation></semantics></math></span><span class=\"katex-html\" aria-hidden=\"true\"><span class=\"base\"><span class=\"strut\" style=\"height:0.4511em;vertical-align:-0.15em;\"></span><span class=\"mord\"><span></span><span class=\"msupsub\"><span class=\"vlist-t vlist-t2\"><span class=\"vlist-r\"><span class=\"vlist\" style=\"height:0.3011em;\"><span style=\"top:-2.55em;margin-right:0.05em;\"><span class=\"pstrut\" style=\"height:2.7em;\"></span><span class=\"sizing reset-size6 size3 mtight\"><span class=\"mord mtight\">2</span></span></span></span><span class=\"vlist-s\">​</span></span><span class=\"vlist-r\"><span class=\"vlist\" style=\"height:0.15em;\"><span></span></span></span></span></span></span></span></span></span>","key":"Lys3Ul3aqY"},{"type":"text","value":" in the single-column Radiative-Convective model.","position":{"start":{"line":3,"column":1},"end":{"line":3,"column":1}},"key":"hikVPTegRS"}],"key":"WCCzrQbFN8"},{"type":"paragraph","position":{"start":{"line":5,"column":1},"end":{"line":5,"column":1}},"children":[{"type":"emphasis","position":{"start":{"line":5,"column":1},"end":{"line":5,"column":1}},"children":[{"type":"text","value":"This exercise just repeats what we did in the lecture notes. You want to ensure that you can reproduce the same results before starting the next question, because you will need these results below.","position":{"start":{"line":5,"column":1},"end":{"line":5,"column":1}},"key":"iAJXJZ8HRJ"}],"key":"dj9Du3mbNn"}],"key":"z0xgJNI7C2"},{"type":"paragraph","position":{"start":{"line":7,"column":1},"end":{"line":7,"column":1}},"children":[{"type":"text","value":"Following the ","position":{"start":{"line":7,"column":1},"end":{"line":7,"column":1}},"key":"tU92tjti4n"},{"type":"link","url":"https://brian-rose.github.io/ClimateLaboratoryBook/courseware/sensitivity-feedback.html","position":{"start":{"line":7,"column":1},"end":{"line":7,"column":1}},"children":[{"type":"text","value":"lecture notes on climate sensitivity","position":{"start":{"line":7,"column":1},"end":{"line":7,"column":1}},"key":"MQCy4WJMa8"}],"urlSource":"https://brian-rose.github.io/ClimateLaboratoryBook/courseware/sensitivity-feedback.html","key":"NmtAfcdXFI"},{"type":"text","value":", do the following:","position":{"start":{"line":7,"column":1},"end":{"line":7,"column":1}},"key":"l1IRJEF7xR"}],"key":"Kf44g3tHVy"},{"type":"list","ordered":false,"spread":false,"position":{"start":{"line":9,"column":1},"end":{"line":15,"column":1}},"children":[{"type":"listItem","spread":true,"position":{"start":{"line":9,"column":1},"end":{"line":9,"column":1}},"children":[{"type":"text","value":"set up a single-column radiative-convective model with specific humidity taken from the ","key":"I6tjtM7Wbd"},{"type":"abbreviation","title":"Community Earth System Model","children":[{"type":"text","value":"CESM","key":"SGN3IrWuCI"}],"key":"Fo9ysdQquM"},{"type":"text","value":" control simu","key":"m0KhIJGGr3"},{"type":"abbreviation","title":"latitude","children":[{"type":"text","value":"lat","key":"qQNwP0zIai"}],"key":"Usm4OqPN72"},{"type":"text","value":"ion","key":"kWnuc0q2jg"}],"key":"J3LFlfP6Gj"},{"type":"listItem","spread":true,"position":{"start":{"line":10,"column":1},"end":{"line":10,"column":1}},"children":[{"type":"text","value":"Run this control model out to equilibrium","position":{"start":{"line":10,"column":1},"end":{"line":10,"column":1}},"key":"dDOLh3m2NK"}],"key":"thYS5nIkRB"},{"type":"listItem","spread":true,"position":{"start":{"line":11,"column":1},"end":{"line":11,"column":1}},"children":[{"type":"text","value":"Using a c","key":"MwfflXLZyK"},{"type":"abbreviation","title":"longitude","children":[{"type":"text","value":"lon","key":"gi2B4xVXVJ"}],"key":"vxueNn2jMX"},{"type":"text","value":"e of the control model, double the atmospheric CO","key":"N5mtZl8VHl"},{"type":"inlineMath","value":"_2","position":{"start":{"line":11,"column":1},"end":{"line":11,"column":1}},"html":"<span class=\"katex\"><span class=\"katex-mathml\"><math xmlns=\"http://www.w3.org/1998/Math/MathML\"><semantics><mrow><msub><mrow></mrow><mn>2</mn></msub></mrow><annotation encoding=\"application/x-tex\">_2</annotation></semantics></math></span><span class=\"katex-html\" aria-hidden=\"true\"><span class=\"base\"><span class=\"strut\" style=\"height:0.4511em;vertical-align:-0.15em;\"></span><span class=\"mord\"><span></span><span class=\"msupsub\"><span class=\"vlist-t vlist-t2\"><span class=\"vlist-r\"><span class=\"vlist\" style=\"height:0.3011em;\"><span style=\"top:-2.55em;margin-right:0.05em;\"><span class=\"pstrut\" style=\"height:2.7em;\"></span><span class=\"sizing reset-size6 size3 mtight\"><span class=\"mord mtight\">2</span></span></span></span><span class=\"vlist-s\">​</span></span><span class=\"vlist-r\"><span class=\"vlist\" style=\"height:0.15em;\"><span></span></span></span></span></span></span></span></span></span>","key":"hx4vMKjdcc"},{"type":"text","value":" and calcu","key":"sL8mEf41r8"},{"type":"abbreviation","title":"latitude","children":[{"type":"text","value":"lat","key":"UU4oXFCaSW"}],"key":"XUviej9lgh"},{"type":"text","value":"e the ","key":"SRqSQkGt2I"},{"type":"emphasis","position":{"start":{"line":11,"column":1},"end":{"line":11,"column":1}},"children":[{"type":"text","value":"stratosphere-adjusted radiative forcing","position":{"start":{"line":11,"column":1},"end":{"line":11,"column":1}},"key":"OB4nsFAe23"}],"key":"AfD9w3TBxJ"},{"type":"text","value":" ","position":{"start":{"line":11,"column":1},"end":{"line":11,"column":1}},"key":"FiOFxMygD2"},{"type":"inlineMath","value":"\\Delta R","position":{"start":{"line":11,"column":1},"end":{"line":11,"column":1}},"html":"<span class=\"katex\"><span class=\"katex-mathml\"><math xmlns=\"http://www.w3.org/1998/Math/MathML\"><semantics><mrow><mi mathvariant=\"normal\">Δ</mi><mi>R</mi></mrow><annotation encoding=\"application/x-tex\">\\Delta R</annotation></semantics></math></span><span class=\"katex-html\" aria-hidden=\"true\"><span class=\"base\"><span class=\"strut\" style=\"height:0.6833em;\"></span><span class=\"mord\">Δ</span><span class=\"mord mathnormal\" style=\"margin-right:0.00773em;\">R</span></span></span></span>","key":"LOQBglNirj"},{"type":"text","value":".","position":{"start":{"line":11,"column":1},"end":{"line":11,"column":1}},"key":"a8s991zmdF"}],"key":"QgzYJz6urm"},{"type":"listItem","spread":true,"position":{"start":{"line":12,"column":1},"end":{"line":12,"column":1}},"children":[{"type":"text","value":"Using another model c","key":"vERsA5eNaQ"},{"type":"abbreviation","title":"longitude","children":[{"type":"text","value":"lon","key":"HHEijAWfnQ"}],"key":"BZvwiFPgu4"},{"type":"text","value":"e with doubled CO","key":"oKuSas3yHs"},{"type":"inlineMath","value":"_2","position":{"start":{"line":12,"column":1},"end":{"line":12,"column":1}},"html":"<span class=\"katex\"><span class=\"katex-mathml\"><math xmlns=\"http://www.w3.org/1998/Math/MathML\"><semantics><mrow><msub><mrow></mrow><mn>2</mn></msub></mrow><annotation encoding=\"application/x-tex\">_2</annotation></semantics></math></span><span class=\"katex-html\" aria-hidden=\"true\"><span class=\"base\"><span class=\"strut\" style=\"height:0.4511em;vertical-align:-0.15em;\"></span><span class=\"mord\"><span></span><span class=\"msupsub\"><span class=\"vlist-t vlist-t2\"><span class=\"vlist-r\"><span class=\"vlist\" style=\"height:0.3011em;\"><span style=\"top:-2.55em;margin-right:0.05em;\"><span class=\"pstrut\" style=\"height:2.7em;\"></span><span class=\"sizing reset-size6 size3 mtight\"><span class=\"mord mtight\">2</span></span></span></span><span class=\"vlist-s\">​</span></span><span class=\"vlist-r\"><span class=\"vlist\" style=\"height:0.15em;\"><span></span></span></span></span></span></span></span></span></span>","key":"n9YHY3qD4L"},{"type":"text","value":", timestep the model out to equilibrium. ","position":{"start":{"line":12,"column":1},"end":{"line":12,"column":1}},"key":"yIcK2enaf0"},{"type":"emphasis","position":{"start":{"line":12,"column":1},"end":{"line":12,"column":1}},"children":[{"type":"text","value":"For this calcu","key":"uk2Hq00oeM"},{"type":"abbreviation","title":"latitude","children":[{"type":"text","value":"lat","key":"ouf0WxuGcm"}],"key":"Vg3GvUJrOO"},{"type":"text","value":"ion, do not modify the specific humidity as we are assuming that there is no change in the water vapor distribution as the climate warms.","key":"uRe4NqpxNr"}],"key":"rVrqB4OJ7E"}],"key":"wMC7U2kdQl"},{"type":"listItem","spread":true,"position":{"start":{"line":13,"column":1},"end":{"line":13,"column":1}},"children":[{"type":"text","value":"Calcu","key":"lq4XQXfQxn"},{"type":"abbreviation","title":"latitude","children":[{"type":"text","value":"lat","key":"XBZnkshCGi"}],"key":"esBBmd7FNi"},{"type":"text","value":"e the no-feedback Equilibrium Climate Sensitivity (","key":"sS4P9TbASO"},{"type":"abbreviation","title":"Equilibrium Climate Sensitivity","children":[{"type":"text","value":"ECS","key":"KNVE7SZwLl"}],"key":"zWMm7rUH1w"},{"type":"text","value":"). ","key":"OabB06YhCT"},{"type":"emphasis","position":{"start":{"line":13,"column":1},"end":{"line":13,"column":1}},"children":[{"type":"text","value":"Recall that this is a number in Kelvin.","position":{"start":{"line":13,"column":1},"end":{"line":13,"column":1}},"key":"iMEjjMDi79"}],"key":"PBSD3YLmzZ"}],"key":"EDA8eJDDn6"},{"type":"listItem","spread":true,"position":{"start":{"line":14,"column":1},"end":{"line":15,"column":1}},"children":[{"type":"text","value":"Also calcu","key":"pASxnyfcQQ"},{"type":"abbreviation","title":"latitude","children":[{"type":"text","value":"lat","key":"CHOWSdDKVc"}],"key":"DZDMreIgD6"},{"type":"text","value":"e the no-feedback climate response parameter ","key":"yCroV7ScHc"},{"type":"inlineMath","value":"\\lambda_0","position":{"start":{"line":14,"column":1},"end":{"line":14,"column":1}},"html":"<span class=\"katex\"><span class=\"katex-mathml\"><math xmlns=\"http://www.w3.org/1998/Math/MathML\"><semantics><mrow><msub><mi>λ</mi><mn>0</mn></msub></mrow><annotation encoding=\"application/x-tex\">\\lambda_0</annotation></semantics></math></span><span class=\"katex-html\" aria-hidden=\"true\"><span class=\"base\"><span class=\"strut\" style=\"height:0.8444em;vertical-align:-0.15em;\"></span><span class=\"mord\"><span class=\"mord mathnormal\">λ</span><span class=\"msupsub\"><span class=\"vlist-t vlist-t2\"><span class=\"vlist-r\"><span class=\"vlist\" style=\"height:0.3011em;\"><span style=\"top:-2.55em;margin-left:0em;margin-right:0.05em;\"><span class=\"pstrut\" style=\"height:2.7em;\"></span><span class=\"sizing reset-size6 size3 mtight\"><span class=\"mord mtight\">0</span></span></span></span><span class=\"vlist-s\">​</span></span><span class=\"vlist-r\"><span class=\"vlist\" style=\"height:0.15em;\"><span></span></span></span></span></span></span></span></span></span>","key":"lxzxeTD3Nj"},{"type":"text","value":" in W m","position":{"start":{"line":14,"column":1},"end":{"line":14,"column":1}},"key":"NUczOcJ2rb"},{"type":"inlineMath","value":"^{-2}","position":{"start":{"line":14,"column":1},"end":{"line":14,"column":1}},"html":"<span class=\"katex\"><span class=\"katex-mathml\"><math xmlns=\"http://www.w3.org/1998/Math/MathML\"><semantics><mrow><msup><mrow></mrow><mrow><mo>−</mo><mn>2</mn></mrow></msup></mrow><annotation encoding=\"application/x-tex\">^{-2}</annotation></semantics></math></span><span class=\"katex-html\" aria-hidden=\"true\"><span class=\"base\"><span class=\"strut\" style=\"height:0.8141em;\"></span><span class=\"mord\"><span></span><span class=\"msupsub\"><span class=\"vlist-t\"><span class=\"vlist-r\"><span class=\"vlist\" style=\"height:0.8141em;\"><span style=\"top:-3.063em;margin-right:0.05em;\"><span class=\"pstrut\" style=\"height:2.7em;\"></span><span class=\"sizing reset-size6 size3 mtight\"><span class=\"mord mtight\"><span class=\"mord mtight\">−</span><span class=\"mord mtight\">2</span></span></span></span></span></span></span></span></span></span></span></span>","key":"YUZwzV1DI6"},{"type":"text","value":" K","position":{"start":{"line":14,"column":1},"end":{"line":14,"column":1}},"key":"wRAOD1IQIO"},{"type":"inlineMath","value":"^{-1}","position":{"start":{"line":14,"column":1},"end":{"line":14,"column":1}},"html":"<span class=\"katex\"><span class=\"katex-mathml\"><math xmlns=\"http://www.w3.org/1998/Math/MathML\"><semantics><mrow><msup><mrow></mrow><mrow><mo>−</mo><mn>1</mn></mrow></msup></mrow><annotation encoding=\"application/x-tex\">^{-1}</annotation></semantics></math></span><span class=\"katex-html\" aria-hidden=\"true\"><span class=\"base\"><span class=\"strut\" style=\"height:0.8141em;\"></span><span class=\"mord\"><span></span><span class=\"msupsub\"><span class=\"vlist-t\"><span class=\"vlist-r\"><span class=\"vlist\" style=\"height:0.8141em;\"><span style=\"top:-3.063em;margin-right:0.05em;\"><span class=\"pstrut\" style=\"height:2.7em;\"></span><span class=\"sizing reset-size6 size3 mtight\"><span class=\"mord mtight\"><span class=\"mord mtight\">−</span><span class=\"mord mtight\">1</span></span></span></span></span></span></span></span></span></span></span></span>","key":"f9s2uRSWOQ"},{"type":"text","value":".","position":{"start":{"line":14,"column":1},"end":{"line":14,"column":1}},"key":"gqWPU33H5a"}],"key":"G72yMPBx8y"}],"key":"ra0dzvhKNM"},{"type":"paragraph","position":{"start":{"line":16,"column":1},"end":{"line":16,"column":1}},"children":[{"type":"text","value":"Verify and show that you get the same results as we did in the lecture notes.","position":{"start":{"line":16,"column":1},"end":{"line":16,"column":1}},"key":"Ig8HnmbNne"}],"key":"U2KHkrjLeI"}],"key":"u4dPqb7SyZ"},{"type":"block","kind":"notebook-code","children":[{"type":"code","lang":"python","executable":true,"value":"","key":"txVDj5hvQJ"},{"type":"output","id":"WiXizC6GpnSWyOHRWktE6","data":[],"key":"UnfkzcYENh"}],"key":"lDLyIECYAT"},{"type":"block","kind":"notebook-content","children":[{"type":"heading","depth":2,"position":{"start":{"line":1,"column":1},"end":{"line":1,"column":1}},"children":[{"type":"text","value":"Question 2: combined lapse rate and water vapor feedback in the ","key":"t17KSVT2Qy"},{"type":"abbreviation","title":"Radiative-Convective Model","children":[{"type":"text","value":"RCM","key":"eAMF4s0NIz"}],"key":"fjnmebkBko"}],"identifier":"question-2-combined-lapse-rate-and-water-vapor-feedback-in-the-rcm","label":"Question 2: combined lapse rate and water vapor feedback in the RCM","html_id":"question-2-combined-lapse-rate-and-water-vapor-feedback-in-the-rcm","implicit":true,"key":"hCO9vw6xob"},{"type":"heading","depth":3,"position":{"start":{"line":3,"column":1},"end":{"line":3,"column":1}},"children":[{"type":"text","value":"Instructions","position":{"start":{"line":3,"column":1},"end":{"line":3,"column":1}},"key":"rM3jtx8rdV"}],"identifier":"instructions","label":"Instructions","html_id":"instructions","implicit":true,"key":"Gzy5YGGyZX"},{"type":"paragraph","position":{"start":{"line":5,"column":1},"end":{"line":5,"column":1}},"children":[{"type":"text","value":"A typical, expected feature of global warming is that the ","position":{"start":{"line":5,"column":1},"end":{"line":5,"column":1}},"key":"nUPEus7zPh"},{"type":"strong","position":{"start":{"line":5,"column":1},"end":{"line":5,"column":1}},"children":[{"type":"text","value":"upper troposphere warms more than the surface","position":{"start":{"line":5,"column":1},"end":{"line":5,"column":1}},"key":"DlKZUA2gPI"}],"key":"crj3ENTw1l"},{"type":"text","value":". (Later we will see that this does occur in the ","key":"LFzq6LqqYp"},{"type":"abbreviation","title":"Community Earth System Model","children":[{"type":"text","value":"CESM","key":"LdzfCvNs8i"}],"key":"y8CiEBygnt"},{"type":"text","value":" simu","key":"gUwgsOaVHm"},{"type":"abbreviation","title":"latitude","children":[{"type":"text","value":"lat","key":"lrW2IoWxOI"}],"key":"yNJB5Og7BO"},{"type":"text","value":"ions).","key":"z3ftk2c37S"}],"key":"jnmv5KUO9T"},{"type":"paragraph","position":{"start":{"line":7,"column":1},"end":{"line":7,"column":1}},"children":[{"type":"text","value":"This feature is ","position":{"start":{"line":7,"column":1},"end":{"line":7,"column":1}},"key":"quQ3jUaGwz"},{"type":"strong","position":{"start":{"line":7,"column":1},"end":{"line":7,"column":1}},"children":[{"type":"text","value":"not represented in our standard radiative-convective model","position":{"start":{"line":7,"column":1},"end":{"line":7,"column":1}},"key":"EgYsXiYtDZ"}],"key":"Ekt4QcAsnU"},{"type":"text","value":", which is forced to a single prescribed lapse rate due to our convective adjustment.","position":{"start":{"line":7,"column":1},"end":{"line":7,"column":1}},"key":"UBviOqlDo2"}],"key":"lNCdohwjXq"},{"type":"paragraph","position":{"start":{"line":9,"column":1},"end":{"line":9,"column":1}},"children":[{"type":"text","value":"Here you will suppose that other physical processes modify this lapse rate as the climate warms.","position":{"start":{"line":9,"column":1},"end":{"line":9,"column":1}},"key":"I3donFUbSx"}],"key":"If3ovU8IcE"},{"type":"paragraph","position":{"start":{"line":11,"column":1},"end":{"line":11,"column":1}},"children":[{"type":"strong","position":{"start":{"line":11,"column":1},"end":{"line":11,"column":1}},"children":[{"type":"text","value":"Repeat the ","key":"RpzoQY6nUI"},{"type":"abbreviation","title":"Radiative-Convective Model","children":[{"type":"text","value":"RCM","key":"SRsvABzf8a"}],"key":"OyDg9AgCPO"},{"type":"text","value":" global warming calcu","key":"Vke6A1dKZ5"},{"type":"abbreviation","title":"latitude","children":[{"type":"text","value":"lat","key":"isuV03sMZa"}],"key":"HcpZXLsAWY"},{"type":"text","value":"ion, but implement two different feedbacks:","key":"dXWlIoeJwG"}],"key":"WE2UQMqTEt"}],"key":"e6lKubXKJi"},{"type":"list","ordered":false,"spread":false,"position":{"start":{"line":13,"column":1},"end":{"line":15,"column":1}},"children":[{"type":"listItem","spread":true,"position":{"start":{"line":13,"column":1},"end":{"line":13,"column":1}},"children":[{"type":"text","value":"a water vapor feedback using ","position":{"start":{"line":13,"column":1},"end":{"line":13,"column":1}},"key":"I0LTvm8m54"},{"type":"strong","position":{"start":{"line":13,"column":1},"end":{"line":13,"column":1}},"children":[{"type":"text","value":"fixed re","key":"TPqgiL3rTY"},{"type":"abbreviation","title":"latitude","children":[{"type":"text","value":"lat","key":"JsQr6Jvuxr"}],"key":"YQ1WKIRHNO"},{"type":"text","value":"ive humidity","key":"gs51pZKksq"}],"key":"YG2V6P8SoY"}],"key":"qfAEEEKYgV"},{"type":"listItem","spread":true,"position":{"start":{"line":14,"column":1},"end":{"line":15,"column":1}},"children":[{"type":"text","value":"a ","position":{"start":{"line":14,"column":1},"end":{"line":14,"column":1}},"key":"JthFmAvvk9"},{"type":"strong","position":{"start":{"line":14,"column":1},"end":{"line":14,"column":1}},"children":[{"type":"text","value":"lapse rate feedback","position":{"start":{"line":14,"column":1},"end":{"line":14,"column":1}},"key":"bPFbZt8utR"}],"key":"jsAOX8KLLx"},{"type":"text","value":" using this formula:","position":{"start":{"line":14,"column":1},"end":{"line":14,"column":1}},"key":"qTpM6fFZkp"}],"key":"SknlfVbEJh"}],"key":"yg0euW1E2w"},{"type":"math","value":"\\Gamma = \\Gamma_{ref} - (0.3 \\text{ km}) \\Delta T_s","position":{"start":{"line":16,"column":1},"end":{"line":16,"column":1}},"html":"<span class=\"katex-display\"><span class=\"katex\"><span class=\"katex-mathml\"><math xmlns=\"http://www.w3.org/1998/Math/MathML\" display=\"block\"><semantics><mrow><mi mathvariant=\"normal\">Γ</mi><mo>=</mo><msub><mi mathvariant=\"normal\">Γ</mi><mrow><mi>r</mi><mi>e</mi><mi>f</mi></mrow></msub><mo>−</mo><mo stretchy=\"false\">(</mo><mn>0.3</mn><mtext> km</mtext><mo stretchy=\"false\">)</mo><mi mathvariant=\"normal\">Δ</mi><msub><mi>T</mi><mi>s</mi></msub></mrow><annotation encoding=\"application/x-tex\">\\Gamma = \\Gamma_{ref} - (0.3 \\text{ km}) \\Delta T_s</annotation></semantics></math></span><span class=\"katex-html\" aria-hidden=\"true\"><span class=\"base\"><span class=\"strut\" style=\"height:0.6833em;\"></span><span class=\"mord\">Γ</span><span class=\"mspace\" style=\"margin-right:0.2778em;\"></span><span class=\"mrel\">=</span><span class=\"mspace\" style=\"margin-right:0.2778em;\"></span></span><span class=\"base\"><span class=\"strut\" style=\"height:0.9694em;vertical-align:-0.2861em;\"></span><span class=\"mord\"><span class=\"mord\">Γ</span><span class=\"msupsub\"><span class=\"vlist-t vlist-t2\"><span class=\"vlist-r\"><span class=\"vlist\" style=\"height:0.3361em;\"><span style=\"top:-2.55em;margin-left:0em;margin-right:0.05em;\"><span class=\"pstrut\" style=\"height:2.7em;\"></span><span class=\"sizing reset-size6 size3 mtight\"><span class=\"mord mtight\"><span class=\"mord mathnormal mtight\">re</span><span class=\"mord mathnormal mtight\" style=\"margin-right:0.10764em;\">f</span></span></span></span></span><span class=\"vlist-s\">​</span></span><span class=\"vlist-r\"><span class=\"vlist\" style=\"height:0.2861em;\"><span></span></span></span></span></span></span><span class=\"mspace\" style=\"margin-right:0.2222em;\"></span><span class=\"mbin\">−</span><span class=\"mspace\" style=\"margin-right:0.2222em;\"></span></span><span class=\"base\"><span class=\"strut\" style=\"height:1em;vertical-align:-0.25em;\"></span><span class=\"mopen\">(</span><span class=\"mord\">0.3</span><span class=\"mord text\"><span class=\"mord\"> km</span></span><span class=\"mclose\">)</span><span class=\"mord\">Δ</span><span class=\"mord\"><span class=\"mord mathnormal\" style=\"margin-right:0.13889em;\">T</span><span class=\"msupsub\"><span class=\"vlist-t vlist-t2\"><span class=\"vlist-r\"><span class=\"vlist\" style=\"height:0.1514em;\"><span style=\"top:-2.55em;margin-left:-0.1389em;margin-right:0.05em;\"><span class=\"pstrut\" style=\"height:2.7em;\"></span><span class=\"sizing reset-size6 size3 mtight\"><span class=\"mord mathnormal mtight\">s</span></span></span></span><span class=\"vlist-s\">​</span></span><span class=\"vlist-r\"><span class=\"vlist\" style=\"height:0.15em;\"><span></span></span></span></span></span></span></span></span></span></span>","enumerator":"1","key":"hLL2DGQNO1"},{"type":"paragraph","position":{"start":{"line":18,"column":1},"end":{"line":18,"column":1}},"children":[{"type":"text","value":"where ","position":{"start":{"line":18,"column":1},"end":{"line":18,"column":1}},"key":"abgUlEYA6G"},{"type":"inlineMath","value":"\\Gamma_{ref}","position":{"start":{"line":18,"column":1},"end":{"line":18,"column":1}},"html":"<span class=\"katex\"><span class=\"katex-mathml\"><math xmlns=\"http://www.w3.org/1998/Math/MathML\"><semantics><mrow><msub><mi mathvariant=\"normal\">Γ</mi><mrow><mi>r</mi><mi>e</mi><mi>f</mi></mrow></msub></mrow><annotation encoding=\"application/x-tex\">\\Gamma_{ref}</annotation></semantics></math></span><span class=\"katex-html\" aria-hidden=\"true\"><span class=\"base\"><span class=\"strut\" style=\"height:0.9694em;vertical-align:-0.2861em;\"></span><span class=\"mord\"><span class=\"mord\">Γ</span><span class=\"msupsub\"><span class=\"vlist-t vlist-t2\"><span class=\"vlist-r\"><span class=\"vlist\" style=\"height:0.3361em;\"><span style=\"top:-2.55em;margin-left:0em;margin-right:0.05em;\"><span class=\"pstrut\" style=\"height:2.7em;\"></span><span class=\"sizing reset-size6 size3 mtight\"><span class=\"mord mtight\"><span class=\"mord mathnormal mtight\">re</span><span class=\"mord mathnormal mtight\" style=\"margin-right:0.10764em;\">f</span></span></span></span></span><span class=\"vlist-s\">​</span></span><span class=\"vlist-r\"><span class=\"vlist\" style=\"height:0.2861em;\"><span></span></span></span></span></span></span></span></span></span>","key":"P1kUeZtE5Q"},{"type":"text","value":" is the critical lapse rate you used in your control model, probably 6.5 K / km, and ","position":{"start":{"line":18,"column":1},"end":{"line":18,"column":1}},"key":"KgvH64hRfA"},{"type":"inlineMath","value":"\\Delta T_s","position":{"start":{"line":18,"column":1},"end":{"line":18,"column":1}},"html":"<span class=\"katex\"><span class=\"katex-mathml\"><math xmlns=\"http://www.w3.org/1998/Math/MathML\"><semantics><mrow><mi mathvariant=\"normal\">Δ</mi><msub><mi>T</mi><mi>s</mi></msub></mrow><annotation encoding=\"application/x-tex\">\\Delta T_s</annotation></semantics></math></span><span class=\"katex-html\" aria-hidden=\"true\"><span class=\"base\"><span class=\"strut\" style=\"height:0.8333em;vertical-align:-0.15em;\"></span><span class=\"mord\">Δ</span><span class=\"mord\"><span class=\"mord mathnormal\" style=\"margin-right:0.13889em;\">T</span><span class=\"msupsub\"><span class=\"vlist-t vlist-t2\"><span class=\"vlist-r\"><span class=\"vlist\" style=\"height:0.1514em;\"><span style=\"top:-2.55em;margin-left:-0.1389em;margin-right:0.05em;\"><span class=\"pstrut\" style=\"height:2.7em;\"></span><span class=\"sizing reset-size6 size3 mtight\"><span class=\"mord mathnormal mtight\">s</span></span></span></span><span class=\"vlist-s\">​</span></span><span class=\"vlist-r\"><span class=\"vlist\" style=\"height:0.15em;\"><span></span></span></span></span></span></span></span></span></span>","key":"jZ8ORuWpr6"},{"type":"text","value":" is the ","position":{"start":{"line":18,"column":1},"end":{"line":18,"column":1}},"key":"RYFUWrIJDj"},{"type":"strong","position":{"start":{"line":18,"column":1},"end":{"line":18,"column":1}},"children":[{"type":"text","value":"current value of the surface warming re","key":"FwJtLNeizk"},{"type":"abbreviation","title":"latitude","children":[{"type":"text","value":"lat","key":"WK4m15h86y"}],"key":"Ww9lWBgP6o"},{"type":"text","value":"ive to the control","key":"fbhzWfF7Fz"}],"key":"sMPSxv4KvR"},{"type":"text","value":" in units of K.","position":{"start":{"line":18,"column":1},"end":{"line":18,"column":1}},"key":"pW280ik9uz"}],"key":"AyF8asZMs5"},{"type":"paragraph","position":{"start":{"line":20,"column":1},"end":{"line":20,"column":1}},"children":[{"type":"text","value":"So, for example if the model has warmed by 1 K at the surface, then our parameterization says that the critical lapse rate should be 6.5 - 0.3 = 6.2 K / km.","position":{"start":{"line":20,"column":1},"end":{"line":20,"column":1}},"key":"skguiBLXGQ"}],"key":"Ig6aaoUUm5"},{"type":"paragraph","position":{"start":{"line":22,"column":1},"end":{"line":22,"column":1}},"children":[{"type":"text","value":"Follow the example in the lecture notes where we implemented the fixed re","key":"IcrCVP5jYp"},{"type":"abbreviation","title":"latitude","children":[{"type":"text","value":"lat","key":"VE7JpOHTaj"}],"key":"efdKeFtR3u"},{"type":"text","value":"ive humidity. Remember that we needed to adjust the ","key":"bHKKySAKKH"},{"type":"inlineCode","value":"specific_humidity","position":{"start":{"line":22,"column":1},"end":{"line":22,"column":1}},"key":"sUK7wE24HC"},{"type":"text","value":" field of our radiation process at every timestep. Here we still need to do that, but in addition, we also need to change the attribute","position":{"start":{"line":22,"column":1},"end":{"line":22,"column":1}},"key":"HmlQu0tBb5"}],"key":"sCZh1ST4QX"},{"type":"code","lang":"","value":"adj_lapse_rate","position":{"start":{"line":24,"column":1},"end":{"line":26,"column":1}},"key":"siy0GjUw8g"},{"type":"paragraph","position":{"start":{"line":28,"column":1},"end":{"line":28,"column":1}},"children":[{"type":"text","value":"of the convection process at each timestep.","position":{"start":{"line":28,"column":1},"end":{"line":28,"column":1}},"key":"EPYMSgIhtS"}],"key":"DVt3qNkKeE"},{"type":"paragraph","position":{"start":{"line":30,"column":1},"end":{"line":30,"column":1}},"children":[{"type":"text","value":"For example, if you have a model called ","position":{"start":{"line":30,"column":1},"end":{"line":30,"column":1}},"key":"ATdfhFPfs0"},{"type":"inlineCode","value":"mymodel","position":{"start":{"line":30,"column":1},"end":{"line":30,"column":1}},"key":"LODomCLSvg"},{"type":"text","value":" that contains a ","position":{"start":{"line":30,"column":1},"end":{"line":30,"column":1}},"key":"PThq40L7qb"},{"type":"inlineCode","value":"ConvectiveAdjustment","position":{"start":{"line":30,"column":1},"end":{"line":30,"column":1}},"key":"zRod8djkTB"},{"type":"text","value":" process called ","position":{"start":{"line":30,"column":1},"end":{"line":30,"column":1}},"key":"eJKg7GFQXj"},{"type":"inlineCode","value":"Convection","position":{"start":{"line":30,"column":1},"end":{"line":30,"column":1}},"key":"gh7m5gdqYA"},{"type":"text","value":", here is some code that you would need at every timestep:","position":{"start":{"line":30,"column":1},"end":{"line":30,"column":1}},"key":"tbKpTq6P6t"}],"key":"DNHvqhFgp2"},{"type":"code","lang":"","value":"mymodel.subprocess['Convection'].adj_lapse_rate = newvalue","position":{"start":{"line":31,"column":1},"end":{"line":33,"column":1}},"key":"UAqoQFyMWZ"},{"type":"paragraph","position":{"start":{"line":34,"column":1},"end":{"line":34,"column":1}},"children":[{"type":"text","value":"where ","position":{"start":{"line":34,"column":1},"end":{"line":34,"column":1}},"key":"vr1euQm8g3"},{"type":"inlineCode","value":"newvalue","position":{"start":{"line":34,"column":1},"end":{"line":34,"column":1}},"key":"WTKLrGaWLP"},{"type":"text","value":" is a number in K / km.","position":{"start":{"line":34,"column":1},"end":{"line":34,"column":1}},"key":"s3mgh8D5wT"}],"key":"LitiGnYTfH"},{"type":"paragraph","position":{"start":{"line":36,"column":1},"end":{"line":36,"column":1}},"children":[{"type":"text","value":"You will need to write a loop where, at every timestep, you calcu","key":"Bx9ytRGuQG"},{"type":"abbreviation","title":"latitude","children":[{"type":"text","value":"lat","key":"PvKcTiG0AI"}],"key":"M959s9snct"},{"type":"text","value":"e the appropriate value of ","key":"TaXfU6WGn6"},{"type":"inlineCode","value":"newvalue","position":{"start":{"line":36,"column":1},"end":{"line":36,"column":1}},"key":"E00r4HTMP7"},{"type":"text","value":" and set the lapse rate parameter as shown above.","position":{"start":{"line":36,"column":1},"end":{"line":36,"column":1}},"key":"MzoQpomsGJ"}],"key":"eERT5Byv1n"},{"type":"heading","depth":3,"position":{"start":{"line":38,"column":1},"end":{"line":38,"column":1}},"children":[{"type":"text","value":"Specific questions:","position":{"start":{"line":38,"column":1},"end":{"line":38,"column":1}},"key":"OjyAAJUEHO"}],"identifier":"specific-questions","label":"Specific questions:","html_id":"specific-questions","implicit":true,"key":"RG8WzEm2wE"},{"type":"list","ordered":true,"start":1,"spread":false,"position":{"start":{"line":40,"column":1},"end":{"line":49,"column":1}},"children":[{"type":"listItem","spread":true,"position":{"start":{"line":40,"column":1},"end":{"line":43,"column":1}},"children":[{"type":"abbreviation","title":"Millions of years","children":[{"type":"text","value":"Ma","key":"tg1R3xMhc2"}],"key":"oxRyn4lJMB"},{"type":"text","value":"ke a nice skew-T plot that shows three temperature profiles:","key":"aI6mF8YkRZ"},{"type":"list","ordered":false,"spread":false,"position":{"start":{"line":41,"column":1},"end":{"line":43,"column":1}},"children":[{"type":"listItem","spread":true,"position":{"start":{"line":41,"column":1},"end":{"line":41,"column":1}},"children":[{"type":"abbreviation","title":"Radiative-Convective Model","children":[{"type":"text","value":"RCM","key":"pylqnliYGE"}],"key":"gIBUNl3Sjr"},{"type":"text","value":" control","key":"tjT3sQ8IR4"}],"key":"IGeGLT9Zdu"},{"type":"listItem","spread":true,"position":{"start":{"line":42,"column":1},"end":{"line":42,"column":1}},"children":[{"type":"abbreviation","title":"Radiative-Convective Model","children":[{"type":"text","value":"RCM","key":"rNNGvC8V4q"}],"key":"CRBBYLAole"},{"type":"text","value":", equilibrium after doubling CO","key":"azojlHdm27"},{"type":"inlineMath","value":"_2","position":{"start":{"line":42,"column":1},"end":{"line":42,"column":1}},"html":"<span class=\"katex\"><span class=\"katex-mathml\"><math xmlns=\"http://www.w3.org/1998/Math/MathML\"><semantics><mrow><msub><mrow></mrow><mn>2</mn></msub></mrow><annotation encoding=\"application/x-tex\">_2</annotation></semantics></math></span><span class=\"katex-html\" aria-hidden=\"true\"><span class=\"base\"><span class=\"strut\" style=\"height:0.4511em;vertical-align:-0.15em;\"></span><span class=\"mord\"><span></span><span class=\"msupsub\"><span class=\"vlist-t vlist-t2\"><span class=\"vlist-r\"><span class=\"vlist\" style=\"height:0.3011em;\"><span style=\"top:-2.55em;margin-right:0.05em;\"><span class=\"pstrut\" style=\"height:2.7em;\"></span><span class=\"sizing reset-size6 size3 mtight\"><span class=\"mord mtight\">2</span></span></span></span><span class=\"vlist-s\">​</span></span><span class=\"vlist-r\"><span class=\"vlist\" style=\"height:0.15em;\"><span></span></span></span></span></span></span></span></span></span>","key":"Zu2U7E5J5g"},{"type":"text","value":" without feedback","position":{"start":{"line":42,"column":1},"end":{"line":42,"column":1}},"key":"a8d9gUhUTu"}],"key":"fgy2tdfnyT"},{"type":"listItem","spread":true,"position":{"start":{"line":43,"column":1},"end":{"line":43,"column":1}},"children":[{"type":"abbreviation","title":"Radiative-Convective Model","children":[{"type":"text","value":"RCM","key":"U5Wpv5AiRl"}],"key":"SaSkaoGrrs"},{"type":"text","value":", equilibrium after doubling CO","key":"pUxeMxc92v"},{"type":"inlineMath","value":"_2","position":{"start":{"line":43,"column":1},"end":{"line":43,"column":1}},"html":"<span class=\"katex\"><span class=\"katex-mathml\"><math xmlns=\"http://www.w3.org/1998/Math/MathML\"><semantics><mrow><msub><mrow></mrow><mn>2</mn></msub></mrow><annotation encoding=\"application/x-tex\">_2</annotation></semantics></math></span><span class=\"katex-html\" aria-hidden=\"true\"><span class=\"base\"><span class=\"strut\" style=\"height:0.4511em;vertical-align:-0.15em;\"></span><span class=\"mord\"><span></span><span class=\"msupsub\"><span class=\"vlist-t vlist-t2\"><span class=\"vlist-r\"><span class=\"vlist\" style=\"height:0.3011em;\"><span style=\"top:-2.55em;margin-right:0.05em;\"><span class=\"pstrut\" style=\"height:2.7em;\"></span><span class=\"sizing reset-size6 size3 mtight\"><span class=\"mord mtight\">2</span></span></span></span><span class=\"vlist-s\">​</span></span><span class=\"vlist-r\"><span class=\"vlist\" style=\"height:0.15em;\"><span></span></span></span></span></span></span></span></span></span>","key":"G0LbdCZAiz"},{"type":"text","value":" with combined water vapor and lapse rate feedback","position":{"start":{"line":43,"column":1},"end":{"line":43,"column":1}},"key":"onTLxJIjdd"}],"key":"mncwBO4cP5"}],"key":"P5EK8AETUf"}],"key":"ohucBPmTZl"},{"type":"listItem","spread":true,"position":{"start":{"line":44,"column":1},"end":{"line":44,"column":1}},"children":[{"type":"text","value":"Based on your plot, where in the column do you find the greatest warming?","position":{"start":{"line":44,"column":1},"end":{"line":44,"column":1}},"key":"EPS5j5bO9H"}],"key":"XE0vLUXIxT"},{"type":"listItem","spread":true,"position":{"start":{"line":45,"column":1},"end":{"line":45,"column":1}},"children":[{"type":"text","value":"Calcu","key":"gAyZckIAvQ"},{"type":"abbreviation","title":"latitude","children":[{"type":"text","value":"lat","key":"vuIEOqt5PW"}],"key":"nv5Nh3YPeb"},{"type":"text","value":"e the ","key":"DfV1GLoZAF"},{"type":"abbreviation","title":"Equilibrium Climate Sensitivity","children":[{"type":"text","value":"ECS","key":"e7ywk3lfay"}],"key":"GwQHGJo2eU"},{"type":"text","value":" of the new version of the model with combined water vapor and lapse rate feedback","key":"Bu424DiqxX"}],"key":"wHSx7IcdEk"},{"type":"listItem","spread":true,"position":{"start":{"line":46,"column":1},"end":{"line":46,"column":1}},"children":[{"type":"text","value":"Is this sensitivity larger or smaller than the “no feedback” ","key":"FU1C6pCtjv"},{"type":"abbreviation","title":"Equilibrium Climate Sensitivity","children":[{"type":"text","value":"ECS","key":"L8UgJXiQ3B"}],"key":"b69yY0etey"},{"type":"text","value":"? Is it larger or smaller than the ","key":"PQehvRDTeQ"},{"type":"abbreviation","title":"Equilibrium Climate Sensitivity","children":[{"type":"text","value":"ECS","key":"eecRmwhnKa"}],"key":"f65NVT7ydY"},{"type":"text","value":" with water vapor feedback a","key":"q8yEHbiVRg"},{"type":"abbreviation","title":"longitude","children":[{"type":"text","value":"lon","key":"kosaxLdXPF"}],"key":"X3Fn4vVO34"},{"type":"text","value":"e (which we calcu","key":"ETTmCRM7eo"},{"type":"abbreviation","title":"latitude","children":[{"type":"text","value":"lat","key":"SnNZdrxAf3"}],"key":"DkdG8nCMj7"},{"type":"text","value":"ed in the lecture notes)?","key":"PWRLPcHZCv"}],"key":"JmULEeyK8D"},{"type":"listItem","spread":true,"position":{"start":{"line":47,"column":1},"end":{"line":47,"column":1}},"children":[{"type":"text","value":"Calcu","key":"BzKtPdjzOP"},{"type":"abbreviation","title":"latitude","children":[{"type":"text","value":"lat","key":"YC4Feq33Ov"}],"key":"Kysgs56N2c"},{"type":"text","value":"e the combined feedback parameter for (water vapor plus lapse rate).","key":"fsL2ZbYmyb"}],"key":"KSlKCouokf"},{"type":"listItem","spread":true,"position":{"start":{"line":48,"column":1},"end":{"line":48,"column":1}},"children":[{"type":"text","value":"Compare this result to the ","key":"cG8PASV2IC"},{"type":"abbreviation","title":"Intergovernmental Panel on Climate Change","children":[{"type":"text","value":"IPCC","key":"zaW2yDTJCq"}],"key":"bzFYQuBRas"},{"type":"text","value":" figure with feedback results from comprehensive models in our lecture notes (labeled “","key":"FVK0xbBdKs"},{"type":"abbreviation","title":"Water Vapor","children":[{"type":"text","value":"WV","key":"pSs6D5g2ww"}],"key":"ZexvUzxHrq"},{"type":"text","value":"+","key":"HJDi28temd"},{"type":"abbreviation","title":"Lapse Rate","children":[{"type":"text","value":"LR","key":"YvGgDm9Z2z"}],"key":"YFWxEaEpKm"},{"type":"text","value":"”). Do you find a similar number?","key":"USZryoSugR"}],"key":"lm8NmBxKNN"},{"type":"listItem","spread":true,"position":{"start":{"line":49,"column":1},"end":{"line":49,"column":1}},"children":[{"type":"text","value":"Would you describe the ","position":{"start":{"line":49,"column":1},"end":{"line":49,"column":1}},"key":"OJvnzR1gpx"},{"type":"strong","position":{"start":{"line":49,"column":1},"end":{"line":49,"column":1}},"children":[{"type":"text","value":"lapse rate feedback","position":{"start":{"line":49,"column":1},"end":{"line":49,"column":1}},"key":"ZcD9VMCbDJ"}],"key":"FdhLpM04tR"},{"type":"text","value":" as positive or negative?","position":{"start":{"line":49,"column":1},"end":{"line":49,"column":1}},"key":"kUL7bS4Isc"}],"key":"EQ9WeJcdAu"}],"key":"eQW7EhUZl9"}],"key":"mEbGdvgaGe"},{"type":"block","kind":"notebook-code","children":[{"type":"code","lang":"python","executable":true,"value":"","key":"Q1ChBKPjoN"},{"type":"output","id":"sLkYa76GtAtJ8D4RuixGI","data":[],"key":"twx9EYpMIa"}],"key":"AYzi5bBikd"},{"type":"block","kind":"notebook-content","children":[{"type":"thematicBreak","position":{"start":{"line":1,"column":1},"end":{"line":1,"column":1}},"key":"t7GOBw1AtX"},{"type":"heading","depth":2,"position":{"start":{"line":3,"column":1},"end":{"line":3,"column":1}},"children":[{"type":"text","value":"Credits","position":{"start":{"line":3,"column":1},"end":{"line":3,"column":1}},"key":"cGOgBJYDmg"}],"identifier":"credits","label":"Credits","html_id":"credits","implicit":true,"key":"CrKExCw5YT"},{"type":"paragraph","position":{"start":{"line":5,"column":1},"end":{"line":5,"column":1}},"children":[{"type":"text","value":"This notebook is part of ","position":{"start":{"line":5,"column":1},"end":{"line":5,"column":1}},"key":"pMnw8BfNZh"},{"type":"link","url":"https://brian-rose.github.io/ClimateLaboratoryBook","position":{"start":{"line":5,"column":1},"end":{"line":5,"column":1}},"children":[{"type":"text","value":"The Climate Laboratory","position":{"start":{"line":5,"column":1},"end":{"line":5,"column":1}},"key":"etvFkWe2ak"}],"urlSource":"https://brian-rose.github.io/ClimateLaboratoryBook","key":"gTdIv75fyj"},{"type":"text","value":", an open-source textbook developed and maintained by ","position":{"start":{"line":5,"column":1},"end":{"line":5,"column":1}},"key":"r7rb9UmKVQ"},{"type":"link","url":"http://www.atmos.albany.edu/facstaff/brose/index.html","position":{"start":{"line":5,"column":1},"end":{"line":5,"column":1}},"children":[{"type":"text","value":"Brian E. J. Rose","position":{"start":{"line":5,"column":1},"end":{"line":5,"column":1}},"key":"HiTbSJiNAC"}],"urlSource":"http://www.atmos.albany.edu/facstaff/brose/index.html","key":"zN9V9f53dL"},{"type":"text","value":", University at Albany.","position":{"start":{"line":5,"column":1},"end":{"line":5,"column":1}},"key":"lmAPCoJska"}],"key":"zQSEPHczkm"},{"type":"paragraph","position":{"start":{"line":7,"column":1},"end":{"line":8,"column":1}},"children":[{"type":"text","value":"It is licensed for free and open consumption under the\n","position":{"start":{"line":7,"column":1},"end":{"line":7,"column":1}},"key":"bLtwFTi0Uk"},{"type":"link","url":"https://creativecommons.org/licenses/by/4.0/","position":{"start":{"line":7,"column":1},"end":{"line":7,"column":1}},"children":[{"type":"text","value":"Creative Commons Attribution 4.0 International (CC BY 4.0)","position":{"start":{"line":7,"column":1},"end":{"line":7,"column":1}},"key":"hl0TziCSMV"}],"urlSource":"https://creativecommons.org/licenses/by/4.0/","key":"ts7jk61o9a"},{"type":"text","value":" license.","position":{"start":{"line":7,"column":1},"end":{"line":7,"column":1}},"key":"s23pXtfwbd"}],"key":"RoMiG18lB1"},{"type":"paragraph","position":{"start":{"line":10,"column":1},"end":{"line":10,"column":1}},"children":[{"type":"text","value":"Development of these notes and the ","position":{"start":{"line":10,"column":1},"end":{"line":10,"column":1}},"key":"yqilpea6dM"},{"type":"link","url":"https://github.com/climlab/climlab","position":{"start":{"line":10,"column":1},"end":{"line":10,"column":1}},"children":[{"type":"text","value":"climlab software","position":{"start":{"line":10,"column":1},"end":{"line":10,"column":1}},"key":"twiBEO52eo"}],"urlSource":"https://github.com/climlab/climlab","error":true,"key":"Xn4Rb5wJX5"},{"type":"text","value":" is partially supported by the National Science Foundation under award AGS-1455071 to Brian Rose. Any opinions, findings, conclusions or recommendations expressed here are mine and do not necessarily reflect the views of the National Science Foundation.","position":{"start":{"line":10,"column":1},"end":{"line":10,"column":1}},"key":"GklakPQPFz"}],"key":"XmVr6kznaX"},{"type":"thematicBreak","position":{"start":{"line":11,"column":1},"end":{"line":11,"column":1}},"key":"QnpjjeZUPc"}],"key":"UPoOHRWVZH"}],"key":"sD4791mU77"},"references":{"cite":{"order":[],"data":{}}},"footer":{"navigation":{"prev":{"title":"Assignment: Clouds in the Leaky Greenhouse Model","url":"/courseware/assignment-simple-clouds","group":"The Climate Laboratory"},"next":{"title":"Assignment: Climate change in the CESM simulations","url":"/courseware/assignment-cesm-climate-change","group":"The Climate Laboratory"}}},"domain":"http://localhost:3000"}