{"version":2,"kind":"Notebook","sha256":"dc81897eeb03502ee269764b446d53f0d1e2e2866c4774fc28744e00b79cd947","slug":"courseware.assignment-cesm-climate-change","location":"/courseware/assignment-cesm-climate-change.ipynb","dependencies":[],"frontmatter":{"title":"Assignment: Climate change in the CESM simulations","content_includes_title":false,"kernelspec":{"name":"python3","display_name":"Python 3","language":"python"},"authors":[{"id":"brian-rose","nameParsed":{"literal":"Brian E. J. Rose","given":"Brian E. J.","family":"Rose"},"name":"Brian E. J. Rose","orcid":"0000-0002-9961-3821","email":"brose@albany.edu","affiliations":["UAlbany"],"url":"https://brian-rose.github.io","github":"brian-rose","bluesky":"@brianejrose.bsky.social","linkedin":"https://www.linkedin.com/in/brian-rose-37bb55106/"}],"doi":"https://doi.org/10.5281/zenodo.4265097","open_access":true,"license":{"content":{"id":"CC-BY-4.0","url":"https://creativecommons.org/licenses/by/4.0/","name":"Creative Commons Attribution 4.0 International","free":true,"CC":true}},"github":"https://github.com/brian-rose/ClimateLaboratoryBook","affiliations":[{"id":"UAlbany","name":"University at Albany (SUNY)","department":"Atmospheric and Environmental Sciences","url":"https://www.albany.edu/daes"}],"abbreviations":{"TOA":"Top of Atmosphere","SW":"Shortwave","LW":"Longwave","UV":"Ultraviolet","IR":"Infrared","OLR":"Outgoing Longwave Radiation","ASR":"Absorbed Shortwave Radiation","CC":"Clausius-Clapeyron","LWP":"Liquid Water Path","CRE":"Cloud Radiative Effect","ECS":"Equilibrium Climate Sensitivity","TCR":"Transient Climate Response","WV":"Water Vapor","LR":"Lapse Rate","LCL":"Lifting Condensation Level","LGM":"Last Glacial Maximum","MSE":"Moist Static Energy","AHT":"Atmospheric Heat Transport","OHT":"Ocean Heat Transport","THT":"Total Heat Transport","1D":"One-dimensional","2D":"Two-dimensional","3D":"Three-dimensional","lat":"latitude","lon":"longitude","ppm":"parts per million","ppmv":"parts per million by volume","hPa":"hectoPascals","Ma":"Millions of years","LHS":"Left hand side","RHS":"Right hand side","EBM":"Energy Balance Model","GCM":"Global Circulation Model","OGCM":"Ocean Global Circulation Model","AGCM":"Atmospheric Global Circulation Model","AOGCM":"Atmosphere-Ocean Global Circulation Model","CGCM":"Coupled Global Circulation Model","RC":"Radiative-Convective","RCM":"Radiative-Convective Model","RCE":"Radiative-Convective Equilibrium","SCM":"Single-Column Model","ESM":"Earth System Model","SD":"Statistical-Dynamical","EMIC":"Earth System Model of Intermediate Complexity","IAM":"Integrated Asessment Model","SOM":"Slab Ocean Model","CESM":"Community Earth System Model","CAM":"Community Atmosphere Model","POP":"Parallel Ocean Program","CLM":"Community Land Model","CICE":"Community Ice CodE","RRTMG":"Rapid Radiative Transfer Model","ODE":"Ordinary Differential Equation","PDE":"Partial Differential Equation","FTCS":"Forward Time, Centered Space","URL":"Uniform Research Locator","CMIP":"Coupled Model Intercomparison Project","IPCC":"Intergovernmental Panel on Climate Change","AR5":"Fifth Assessment Report","AR6":"Sixth Assessment Report","WG1":"Working Group 1","NCAR":"National Center for Atmospheric Research","AMS":"American Meteorological Society","NCEP":"National Centers for Environmental Prediction"},"numbering":{"title":{"offset":1}},"edit_url":"https://github.com/brian-rose/ClimateLaboratoryBook/blob/main/courseware/assignment-cesm-climate-change.ipynb","exports":[{"format":"ipynb","filename":"assignment-cesm-climate-change.ipynb","url":"/ClimateLaboratoryBook/build/assignment-cesm-clim-81f482a9682d3f71a4748e1d09f82964.ipynb"}]},"widgets":{},"mdast":{"type":"root","children":[{"type":"block","kind":"notebook-content","children":[{"type":"paragraph","position":{"start":{"line":3,"column":1},"end":{"line":3,"column":1}},"children":[{"type":"text","value":"This notebook is part of ","position":{"start":{"line":3,"column":1},"end":{"line":3,"column":1}},"key":"F5T35F8mWM"},{"type":"link","url":"https://brian-rose.github.io/ClimateLaboratoryBook","position":{"start":{"line":3,"column":1},"end":{"line":3,"column":1}},"children":[{"type":"text","value":"The Climate Laboratory","position":{"start":{"line":3,"column":1},"end":{"line":3,"column":1}},"key":"QRqouwWgVg"}],"urlSource":"https://brian-rose.github.io/ClimateLaboratoryBook","key":"AfzqiCUaiy"},{"type":"text","value":" by ","position":{"start":{"line":3,"column":1},"end":{"line":3,"column":1}},"key":"DnYDdCIyO5"},{"type":"link","url":"http://www.atmos.albany.edu/facstaff/brose/index.html","position":{"start":{"line":3,"column":1},"end":{"line":3,"column":1}},"children":[{"type":"text","value":"Brian E. J. Rose","position":{"start":{"line":3,"column":1},"end":{"line":3,"column":1}},"key":"EX7sgWwXho"}],"urlSource":"http://www.atmos.albany.edu/facstaff/brose/index.html","key":"SIa4PqrYfp"},{"type":"text","value":", University at Albany.","position":{"start":{"line":3,"column":1},"end":{"line":3,"column":1}},"key":"cIRR0v81wz"}],"key":"rAj2BfW2sS"}],"key":"Wkf788Fbpa"},{"type":"block","kind":"notebook-content","children":[{"type":"heading","depth":2,"position":{"start":{"line":1,"column":1},"end":{"line":1,"column":1}},"children":[{"type":"text","value":"Part 1","position":{"start":{"line":1,"column":1},"end":{"line":1,"column":1}},"key":"dwwvtBIPlE"}],"identifier":"part-1","label":"Part 1","html_id":"part-1","implicit":true,"key":"SbfIcvRrfz"},{"type":"paragraph","position":{"start":{"line":3,"column":1},"end":{"line":3,"column":1}},"children":[{"type":"text","value":"Following the examples in the ","position":{"start":{"line":3,"column":1},"end":{"line":3,"column":1}},"key":"uvYw3R5n5j"},{"type":"link","url":"https://brian-rose.github.io/ClimateLaboratoryBook/courseware/transient-cesm.html","position":{"start":{"line":3,"column":1},"end":{"line":3,"column":1}},"children":[{"type":"text","value":"lecture notes","position":{"start":{"line":3,"column":1},"end":{"line":3,"column":1}},"key":"PAvwoB5Uck"}],"urlSource":"https://brian-rose.github.io/ClimateLaboratoryBook/courseware/transient-cesm.html","key":"CL3ajBGWAu"},{"type":"text","value":", open the four ","key":"XcsQDTCvnf"},{"type":"abbreviation","title":"Community Earth System Model","children":[{"type":"text","value":"CESM","key":"ykPqRJPP20"}],"key":"l4ZL1mIPX4"},{"type":"text","value":" simu","key":"HHH3n0q2ub"},{"type":"abbreviation","title":"latitude","children":[{"type":"text","value":"lat","key":"wLSsQ95h9z"}],"key":"v7JVyK5Xcn"},{"type":"text","value":"ions (fully coupled and slab ocean versions).","key":"sJVwG0pwRv"}],"key":"E3LNkJQtnP"},{"type":"paragraph","position":{"start":{"line":5,"column":1},"end":{"line":5,"column":1}},"children":[{"type":"text","value":"Calcu","key":"OCEXp2N1ni"},{"type":"abbreviation","title":"latitude","children":[{"type":"text","value":"lat","key":"cCY3F6k9Bt"}],"key":"QxelZWrGtP"},{"type":"text","value":"e timeseries of ","key":"v6e0bSCopa"},{"type":"strong","position":{"start":{"line":5,"column":1},"end":{"line":5,"column":1}},"children":[{"type":"text","value":"global mean ","key":"Q0wbB5mGB5"},{"type":"abbreviation","title":"Absorbed Shortwave Radiation","children":[{"type":"text","value":"ASR","key":"n9vUWIwKWI"}],"key":"g2cG0gdARK"},{"type":"text","value":" and ","key":"GH8U4g7UEO"},{"type":"abbreviation","title":"Outgoing Longwave Radiation","children":[{"type":"text","value":"OLR","key":"YCdve3s2hl"}],"key":"o8eGwQsvd4"}],"key":"MxGuJ3Cc34"},{"type":"text","value":" and store each of these as a new variable. ","position":{"start":{"line":5,"column":1},"end":{"line":5,"column":1}},"key":"z5MDLUDQOg"},{"type":"emphasis","position":{"start":{"line":5,"column":1},"end":{"line":5,"column":1}},"children":[{"type":"text","value":"Recall that ","key":"x5v0uBNB1g"},{"type":"abbreviation","title":"Absorbed Shortwave Radiation","children":[{"type":"text","value":"ASR","key":"sJAHR3aNWp"}],"key":"S6hgTBLAQc"},{"type":"text","value":" is called ","key":"dgEu6OwFXE"},{"type":"inlineCode","value":"FSNT","position":{"start":{"line":5,"column":1},"end":{"line":5,"column":1}},"key":"L49bDmpXT9"},{"type":"text","value":" in the ","key":"CVkQ1QrixX"},{"type":"abbreviation","title":"Community Earth System Model","children":[{"type":"text","value":"CESM","key":"ouTTwc1EwW"}],"key":"ZUSF3Ldp54"},{"type":"text","value":" output, and ","key":"TJRSdi3jFB"},{"type":"abbreviation","title":"Outgoing Longwave Radiation","children":[{"type":"text","value":"OLR","key":"M3fEPVxmh3"}],"key":"gAPfQQUbE3"},{"type":"text","value":" is called ","key":"bHTp3k2QQ5"},{"type":"inlineCode","value":"FLNT","position":{"start":{"line":5,"column":1},"end":{"line":5,"column":1}},"key":"XhIO7i2GBM"},{"type":"text","value":".","position":{"start":{"line":5,"column":1},"end":{"line":5,"column":1}},"key":"kcj2p7KOey"}],"key":"libApYb1eL"}],"key":"zJZzz6QtNY"},{"type":"paragraph","position":{"start":{"line":7,"column":1},"end":{"line":7,"column":1}},"children":[{"type":"text","value":"Plot a timeseries of ","position":{"start":{"line":7,"column":1},"end":{"line":7,"column":1}},"key":"D6AciObGvC"},{"type":"strong","position":{"start":{"line":7,"column":1},"end":{"line":7,"column":1}},"children":[{"type":"text","value":"(","key":"ma9qUeRN9T"},{"type":"abbreviation","title":"Absorbed Shortwave Radiation","children":[{"type":"text","value":"ASR","key":"jRQ5lU5R0s"}],"key":"GOqYEceTmh"},{"type":"text","value":" - ","key":"QmMPBll10a"},{"type":"abbreviation","title":"Outgoing Longwave Radiation","children":[{"type":"text","value":"OLR","key":"tRhn9speFa"}],"key":"mbIINiUQEp"},{"type":"text","value":"), the net downward energy flux at the top of the model","key":"uhZ7du4ys6"}],"key":"dgTgo5FrEE"},{"type":"text","value":", a","key":"FMehZivUex"},{"type":"abbreviation","title":"longitude","children":[{"type":"text","value":"lon","key":"a9NFjiOSNV"}],"key":"JdCaHcSJd9"},{"type":"text","value":"g with a ","key":"zI9Hw9zLXg"},{"type":"strong","position":{"start":{"line":7,"column":1},"end":{"line":7,"column":1}},"children":[{"type":"text","value":"12 month rolling mean","position":{"start":{"line":7,"column":1},"end":{"line":7,"column":1}},"key":"Jzn088YJ6x"}],"key":"s1Ame8eoEA"},{"type":"text","value":", analogous to the plot of global mean surface air temperature in the lecture notes.","position":{"start":{"line":7,"column":1},"end":{"line":7,"column":1}},"key":"E5oqKIIvXY"}],"key":"i24M1Ip3VO"},{"type":"paragraph","position":{"start":{"line":9,"column":1},"end":{"line":9,"column":1}},"children":[{"type":"emphasis","position":{"start":{"line":9,"column":1},"end":{"line":9,"column":1}},"children":[{"type":"text","value":"Note that the rolling mean is important here because, just like with surface air temperature, there is a large seasonal cycle which makes it harder to see evidence of the climate change signal we wish to focus on.","position":{"start":{"line":9,"column":1},"end":{"line":9,"column":1}},"key":"Wi6LcR3aHy"}],"key":"FLzhXCtML6"}],"key":"rKcKgEy356"}],"key":"FDAF3xJLeJ"},{"type":"block","kind":"notebook-code","children":[{"type":"code","lang":"python","executable":true,"value":"","key":"BlvjQNrAgD"},{"type":"output","id":"4W6foT9q3hMH12CpLZM7Y","data":[],"key":"BvzilqHpYy"}],"key":"ZlatUXWJIf"},{"type":"block","kind":"notebook-content","children":[{"type":"heading","depth":2,"position":{"start":{"line":1,"column":1},"end":{"line":1,"column":1}},"children":[{"type":"text","value":"Part 2","position":{"start":{"line":1,"column":1},"end":{"line":1,"column":1}},"key":"Y4CC6Xdzy4"}],"identifier":"part-2","label":"Part 2","html_id":"part-2","implicit":true,"key":"xIDs4dWWNF"},{"type":"paragraph","position":{"start":{"line":3,"column":1},"end":{"line":3,"column":1}},"children":[{"type":"text","value":"Calcu","key":"KVhiN4hCMT"},{"type":"abbreviation","title":"latitude","children":[{"type":"text","value":"lat","key":"IPK8ruKUWY"}],"key":"Sx2YwmbPSO"},{"type":"text","value":"e and show the ","key":"ANVYCDfIMG"},{"type":"strong","position":{"start":{"line":3,"column":1},"end":{"line":3,"column":1}},"children":[{"type":"text","value":"time-average ","key":"eEnazsh6pZ"},{"type":"abbreviation","title":"Absorbed Shortwave Radiation","children":[{"type":"text","value":"ASR","key":"NBKrCLEkj3"}],"key":"a8zCOsshiO"}],"key":"qLYLuf5OVs"},{"type":"text","value":" and ","position":{"start":{"line":3,"column":1},"end":{"line":3,"column":1}},"key":"aiuRw6xinI"},{"type":"strong","position":{"start":{"line":3,"column":1},"end":{"line":3,"column":1}},"children":[{"type":"text","value":"time-average ","key":"cifbUzeCJR"},{"type":"abbreviation","title":"Outgoing Longwave Radiation","children":[{"type":"text","value":"OLR","key":"ah8VR9pTA5"}],"key":"SOAGPcZkYZ"}],"key":"OLhc2L2d0b"},{"type":"text","value":" over the final 10 or 20 years of each simu","key":"cVaRx77KRn"},{"type":"abbreviation","title":"latitude","children":[{"type":"text","value":"lat","key":"SBsVEOTklH"}],"key":"kU01WBX2Jw"},{"type":"text","value":"ion. Following the lecture notes, use the 20-year slice for the fully coupled simu","key":"bQkzFL2Fgs"},{"type":"abbreviation","title":"latitude","children":[{"type":"text","value":"lat","key":"koA2VhARmX"}],"key":"v1zt1FV87J"},{"type":"text","value":"ions, and the 10-year slice for the slab ocean simu","key":"F8arQ4VanS"},{"type":"abbreviation","title":"latitude","children":[{"type":"text","value":"lat","key":"ZeHd94PrWD"}],"key":"XiuVZudH3Y"},{"type":"text","value":"ions.","key":"D9CrSn3iMH"}],"key":"Af4aNIEKh7"}],"key":"tDNPatYKaQ"},{"type":"block","kind":"notebook-code","children":[{"type":"code","lang":"python","executable":true,"value":"","key":"EfTw2egQHE"},{"type":"output","id":"PFrLd0JAm1p6E_UGuHtp6","data":[],"key":"s6saJRyG0k"}],"key":"Ly7sYoVBt8"},{"type":"block","kind":"notebook-content","children":[{"type":"heading","depth":2,"position":{"start":{"line":1,"column":1},"end":{"line":1,"column":1}},"children":[{"type":"text","value":"Part 3","position":{"start":{"line":1,"column":1},"end":{"line":1,"column":1}},"key":"YQRmNiBLHY"}],"identifier":"part-3","label":"Part 3","html_id":"part-3","implicit":true,"key":"KuHAAeeoEn"},{"type":"paragraph","position":{"start":{"line":3,"column":1},"end":{"line":3,"column":1}},"children":[{"type":"text","value":"Based on your plots and numerical results from Parts 1 and 2, answer these questions:","position":{"start":{"line":3,"column":1},"end":{"line":3,"column":1}},"key":"liRhhydWt5"}],"key":"nSaU3nv0lm"},{"type":"list","ordered":true,"start":1,"spread":false,"position":{"start":{"line":5,"column":1},"end":{"line":8,"column":1}},"children":[{"type":"listItem","spread":true,"position":{"start":{"line":5,"column":1},"end":{"line":5,"column":1}},"children":[{"type":"text","value":"Are the two control simu","key":"IXuPshWK5A"},{"type":"abbreviation","title":"latitude","children":[{"type":"text","value":"lat","key":"dzNnfSTBm3"}],"key":"trAJgy0Hdh"},{"type":"text","value":"ions (fully coupled and slab ocean) near energy balance?","key":"EV2NG3QWxU"}],"key":"nkwWQrMLwj"},{"type":"listItem","spread":true,"position":{"start":{"line":6,"column":1},"end":{"line":6,"column":1}},"children":[{"type":"text","value":"In the fully coupled CO2 ramp simu","key":"c2Ii8Wxk3i"},{"type":"abbreviation","title":"latitude","children":[{"type":"text","value":"lat","key":"W25SWQz7Oa"}],"key":"na8Zw7iBik"},{"type":"text","value":"ion, does the energy imbalance (","key":"RbZZctHHL9"},{"type":"abbreviation","title":"Absorbed Shortwave Radiation","children":[{"type":"text","value":"ASR","key":"wIieMZQxWY"}],"key":"ynz54kOUEU"},{"type":"text","value":"-","key":"I939LAAN1g"},{"type":"abbreviation","title":"Outgoing Longwave Radiation","children":[{"type":"text","value":"OLR","key":"hlfKSbqcPv"}],"key":"NuwsGNugRC"},{"type":"text","value":") increase or decrease with time? What is the imbalance at the end of the 80 year simu","key":"JvRDluNwWr"},{"type":"abbreviation","title":"latitude","children":[{"type":"text","value":"lat","key":"eIiKnV40UG"}],"key":"iP5deZEqSl"},{"type":"text","value":"ion?","key":"js2rcrItDD"}],"key":"IPriqlgYdd"},{"type":"listItem","spread":true,"position":{"start":{"line":7,"column":1},"end":{"line":7,"column":1}},"children":[{"type":"text","value":"Answer the same questions for the slab ocean abrupt 2xCO2 simu","key":"Lu6Q9sxAOo"},{"type":"abbreviation","title":"latitude","children":[{"type":"text","value":"lat","key":"Jbe22fAU0N"}],"key":"Bk5QgxRVAd"},{"type":"text","value":"ion.","key":"GbEMSM6sEu"}],"key":"pkqpjEhS6A"},{"type":"listItem","spread":true,"position":{"start":{"line":8,"column":1},"end":{"line":8,"column":1}},"children":[{"type":"text","value":"Explain in words why the timeseries of ","key":"sEBw4wQbAa"},{"type":"abbreviation","title":"Absorbed Shortwave Radiation","children":[{"type":"text","value":"ASR","key":"c6DhxY3Tze"}],"key":"gSuieJBl7e"},{"type":"text","value":"-","key":"eUPLvZnrk1"},{"type":"abbreviation","title":"Outgoing Longwave Radiation","children":[{"type":"text","value":"OLR","key":"u6Y0uTViV4"}],"key":"PH94zKyADY"},{"type":"text","value":" look very different in the fully coupled simu","key":"svWkaF0F9S"},{"type":"abbreviation","title":"latitude","children":[{"type":"text","value":"lat","key":"ysL98qRY2o"}],"key":"bh2qoEOPP1"},{"type":"text","value":"ion (1%/year CO2 ramp) versus the slab ocean simu","key":"hyygslqurT"},{"type":"abbreviation","title":"latitude","children":[{"type":"text","value":"lat","key":"IIxjqVqZM6"}],"key":"qZpgePe1ER"},{"type":"text","value":"ion (abrupt 2xCO2). ","key":"UIov8eXNvb"},{"type":"emphasis","position":{"start":{"line":8,"column":1},"end":{"line":8,"column":1}},"children":[{"type":"text","value":"Think about both the different radiative forcings and the different ocean heat capacities.","position":{"start":{"line":8,"column":1},"end":{"line":8,"column":1}},"key":"HCyVmSN8R6"}],"key":"MrkQQzt4RG"}],"key":"uqngbswAwI"}],"key":"DxML1FgTVL"}],"key":"hJkBDF1ZN3"},{"type":"block","kind":"notebook-code","children":[{"type":"code","lang":"python","executable":true,"value":"","key":"dLXYYjLxee"},{"type":"output","id":"hlG3fPzJUwbZZ-VU9NEJX","data":[],"key":"FYOyQ45ADE"}],"key":"hyIY920GrP"},{"type":"block","kind":"notebook-content","children":[{"type":"heading","depth":2,"position":{"start":{"line":1,"column":1},"end":{"line":1,"column":1}},"children":[{"type":"text","value":"Part 4","position":{"start":{"line":1,"column":1},"end":{"line":1,"column":1}},"key":"bTyZmNqo5R"}],"identifier":"part-4","label":"Part 4","html_id":"part-4","implicit":true,"key":"ZKCvBQCy8T"},{"type":"paragraph","position":{"start":{"line":3,"column":1},"end":{"line":3,"column":1}},"children":[{"type":"text","value":"Does the global average ","key":"LIAPTK9ZP5"},{"type":"abbreviation","title":"Absorbed Shortwave Radiation","children":[{"type":"text","value":"ASR","key":"MHp8BIeClj"}],"key":"pxYYEsNxcf"},{"type":"text","value":" ","key":"RarJGr9CSy"},{"type":"strong","position":{"start":{"line":3,"column":1},"end":{"line":3,"column":1}},"children":[{"type":"text","value":"increase","position":{"start":{"line":3,"column":1},"end":{"line":3,"column":1}},"key":"fcgRP2n4x5"}],"key":"yhBYG6p4Z0"},{"type":"text","value":" or ","position":{"start":{"line":3,"column":1},"end":{"line":3,"column":1}},"key":"mfWRsErIXR"},{"type":"strong","position":{"start":{"line":3,"column":1},"end":{"line":3,"column":1}},"children":[{"type":"text","value":"decrease","position":{"start":{"line":3,"column":1},"end":{"line":3,"column":1}},"key":"Fdg983lCVI"}],"key":"oeg8XeYEWR"},{"type":"text","value":" because of CO2-driven warming in the ","key":"qDsAKdMolX"},{"type":"abbreviation","title":"Community Earth System Model","children":[{"type":"text","value":"CESM","key":"FutcFd9Ka7"}],"key":"CdDGqkfpes"},{"type":"text","value":"?","key":"P4WmO4XlsT"}],"key":"JaSNsRqiAL"},{"type":"paragraph","position":{"start":{"line":5,"column":1},"end":{"line":5,"column":1}},"children":[{"type":"text","value":"Would you describe this as a ","position":{"start":{"line":5,"column":1},"end":{"line":5,"column":1}},"key":"p4UT20JfTv"},{"type":"strong","position":{"start":{"line":5,"column":1},"end":{"line":5,"column":1}},"children":[{"type":"text","value":"positive","position":{"start":{"line":5,"column":1},"end":{"line":5,"column":1}},"key":"GlAxwH6gJo"}],"key":"Ui35DXhPYp"},{"type":"text","value":" or ","position":{"start":{"line":5,"column":1},"end":{"line":5,"column":1}},"key":"Yj4RIWuldH"},{"type":"strong","position":{"start":{"line":5,"column":1},"end":{"line":5,"column":1}},"children":[{"type":"text","value":"negative","position":{"start":{"line":5,"column":1},"end":{"line":5,"column":1}},"key":"s0yngdLNWo"}],"key":"FjRyDZ6LdI"},{"type":"text","value":" feedback?","position":{"start":{"line":5,"column":1},"end":{"line":5,"column":1}},"key":"zzDBqCilzL"}],"key":"ObwT4enLMO"}],"key":"P0YeTERSQ1"},{"type":"block","kind":"notebook-code","children":[{"type":"code","lang":"python","executable":true,"value":"","key":"IXfL0WMFuY"},{"type":"output","id":"WJzOJkr3Px4gFZ1uOsqTB","data":[],"key":"m0eViOBAHQ"}],"key":"NrqB5fMtzk"},{"type":"block","kind":"notebook-content","children":[{"type":"heading","depth":2,"position":{"start":{"line":1,"column":1},"end":{"line":1,"column":1}},"children":[{"type":"text","value":"Part 5","position":{"start":{"line":1,"column":1},"end":{"line":1,"column":1}},"key":"Ho5pjoFP7c"}],"identifier":"part-5","label":"Part 5","html_id":"part-5","implicit":true,"key":"lemkz6dZ8w"},{"type":"paragraph","position":{"start":{"line":3,"column":1},"end":{"line":3,"column":1}},"children":[{"type":"text","value":"In the previous question you looked at the global average change in ","key":"mfa4Pke61v"},{"type":"abbreviation","title":"Absorbed Shortwave Radiation","children":[{"type":"text","value":"ASR","key":"WGSKNPIlbK"}],"key":"WQ3n49GFKx"},{"type":"text","value":". Now I want you to look at how different parts of the world contribute to this change.","key":"rumeLHTaAV"}],"key":"zf8c4g5Bjj"},{"type":"paragraph","position":{"start":{"line":5,"column":1},"end":{"line":5,"column":1}},"children":[{"type":"strong","position":{"start":{"line":5,"column":1},"end":{"line":5,"column":1}},"children":[{"type":"abbreviation","title":"Millions of years","children":[{"type":"text","value":"Ma","key":"V01Gvedknm"}],"key":"MYOReQssOl"},{"type":"text","value":"ke a map","key":"RY39n5nhfj"}],"key":"kLT8rrN0se"},{"type":"text","value":" of the ","position":{"start":{"line":5,"column":1},"end":{"line":5,"column":1}},"key":"t7bZRvJSRD"},{"type":"strong","position":{"start":{"line":5,"column":1},"end":{"line":5,"column":1}},"children":[{"type":"text","value":"change in ","key":"vcfX3kzSUw"},{"type":"abbreviation","title":"Absorbed Shortwave Radiation","children":[{"type":"text","value":"ASR","key":"EXOYR4avr0"}],"key":"B4d9KGblu4"}],"key":"k4cuBnU1pd"},{"type":"text","value":" due to the CO2 forcing. Use the average over the last 20 years of the coupled CO2 ramp simu","key":"IkHwCHBvft"},{"type":"abbreviation","title":"latitude","children":[{"type":"text","value":"lat","key":"lc1QqK7IkI"}],"key":"LyZaUgfWrw"},{"type":"text","value":"ion, comparing against the average over the last 20 years of the control simu","key":"mhhmXDXsEt"},{"type":"abbreviation","title":"latitude","children":[{"type":"text","value":"lat","key":"ZQ51op0f6n"}],"key":"JTq5qmcaRp"},{"type":"text","value":"ion.","key":"MTWt6TTBuG"}],"key":"IjSGSXFQPz"}],"key":"DusKlR9J4R"},{"type":"block","kind":"notebook-code","children":[{"type":"code","lang":"python","executable":true,"value":"","key":"Zra3Qp5wLl"},{"type":"output","id":"z3FGzQRmLx-UCSb-56srL","data":[],"key":"HdLXKmle4A"}],"key":"zsEsM4xLbe"},{"type":"block","kind":"notebook-content","children":[{"type":"heading","depth":2,"position":{"start":{"line":1,"column":1},"end":{"line":1,"column":1}},"children":[{"type":"text","value":"Part 6","position":{"start":{"line":1,"column":1},"end":{"line":1,"column":1}},"key":"y2o5iEZ8NR"}],"identifier":"part-6","label":"Part 6","html_id":"part-6","implicit":true,"key":"f2aY0OOqBs"},{"type":"paragraph","position":{"start":{"line":3,"column":1},"end":{"line":3,"column":1}},"children":[{"type":"text","value":"Repeat part 5, but this time instead of the change in ","key":"MdFLAdD7QZ"},{"type":"abbreviation","title":"Absorbed Shortwave Radiation","children":[{"type":"text","value":"ASR","key":"qsRt6MzFxW"}],"key":"jmCsqDEJo9"},{"type":"text","value":", look at the just change in the ","key":"tsfgBFGwsT"},{"type":"strong","position":{"start":{"line":3,"column":1},"end":{"line":3,"column":1}},"children":[{"type":"text","value":"clear-sky","position":{"start":{"line":3,"column":1},"end":{"line":3,"column":1}},"key":"u3CEGM73Un"}],"key":"Ka2zc8TT5A"},{"type":"text","value":" component of ","key":"qV2ZvhkB6N"},{"type":"abbreviation","title":"Absorbed Shortwave Radiation","children":[{"type":"text","value":"ASR","key":"mT9NS5x5yU"}],"key":"TZuAKfAQ3W"},{"type":"text","value":". You can find this in the output field called ","key":"Al0X4WaOqb"},{"type":"inlineCode","value":"FSNTC","position":{"start":{"line":3,"column":1},"end":{"line":3,"column":1}},"key":"v36JKunaI6"},{"type":"text","value":".","position":{"start":{"line":3,"column":1},"end":{"line":3,"column":1}},"key":"uhd3qQve43"}],"key":"zg2YCgHqMg"},{"type":"paragraph","position":{"start":{"line":5,"column":1},"end":{"line":5,"column":1}},"children":[{"type":"emphasis","position":{"start":{"line":5,"column":1},"end":{"line":5,"column":1}},"children":[{"type":"text","value":"The ","position":{"start":{"line":5,"column":1},"end":{"line":5,"column":1}},"key":"hpkBhFfMQx"},{"type":"inlineCode","value":"FSNTC","position":{"start":{"line":5,"column":1},"end":{"line":5,"column":1}},"key":"QzwIhh65Eo"},{"type":"text","value":" field shows shortwave absorption in the absence of clouds, so the ","position":{"start":{"line":5,"column":1},"end":{"line":5,"column":1}},"key":"AubAO5TtcD"},{"type":"strong","position":{"start":{"line":5,"column":1},"end":{"line":5,"column":1}},"children":[{"type":"text","value":"change","position":{"start":{"line":5,"column":1},"end":{"line":5,"column":1}},"key":"KqF59ImVCN"}],"key":"y8CJicEXyv"},{"type":"text","value":" in ","position":{"start":{"line":5,"column":1},"end":{"line":5,"column":1}},"key":"sVCGl18Jvj"},{"type":"inlineCode","value":"FSNTC","position":{"start":{"line":5,"column":1},"end":{"line":5,"column":1}},"key":"zDUbP5tOTQ"},{"type":"text","value":" shows how absorption and reflection of shortwave are affected by processes other than clouds.","position":{"start":{"line":5,"column":1},"end":{"line":5,"column":1}},"key":"MQQXhTAz2C"}],"key":"Cc5DNPPWxB"}],"key":"PJfyZuyqBM"}],"key":"WEUCR0mHMB"},{"type":"block","kind":"notebook-code","children":[{"type":"code","lang":"python","executable":true,"value":"","key":"DGUzozJKk9"},{"type":"output","id":"zX6VGBpwuz-_fCZHWZwhy","data":[],"key":"GoS9V2oOxw"}],"key":"ugDopAy874"},{"type":"block","kind":"notebook-content","children":[{"type":"heading","depth":2,"position":{"start":{"line":1,"column":1},"end":{"line":1,"column":1}},"children":[{"type":"text","value":"Part 7","position":{"start":{"line":1,"column":1},"end":{"line":1,"column":1}},"key":"BEzMF4kUGp"}],"identifier":"part-7","label":"Part 7","html_id":"part-7","implicit":true,"key":"SONqG5V05v"},{"type":"paragraph","position":{"start":{"line":3,"column":1},"end":{"line":3,"column":1}},"children":[{"type":"text","value":"Discussion:","position":{"start":{"line":3,"column":1},"end":{"line":3,"column":1}},"key":"svf0fNHlDp"}],"key":"LW7xbNn8Th"},{"type":"list","ordered":false,"spread":false,"position":{"start":{"line":5,"column":1},"end":{"line":7,"column":1}},"children":[{"type":"listItem","spread":true,"position":{"start":{"line":5,"column":1},"end":{"line":5,"column":1}},"children":[{"type":"text","value":"Do your two maps (change in ","key":"dPMW9q25pr"},{"type":"abbreviation","title":"Absorbed Shortwave Radiation","children":[{"type":"text","value":"ASR","key":"UApBZWGoRa"}],"key":"cF9TdwJpen"},{"type":"text","value":", change in clear-sky ","key":"SDRtSojBwM"},{"type":"abbreviation","title":"Absorbed Shortwave Radiation","children":[{"type":"text","value":"ASR","key":"yYbnJ1GVMz"}],"key":"Fg00iaoXXe"},{"type":"text","value":") look the same?","key":"SMjb2hT5z5"}],"key":"RyvU4qbZz2"},{"type":"listItem","spread":true,"position":{"start":{"line":6,"column":1},"end":{"line":6,"column":1}},"children":[{"type":"text","value":"Offer some ideas about why the clear-sky map looks the way it does.","position":{"start":{"line":6,"column":1},"end":{"line":6,"column":1}},"key":"vrmRbfQgSl"}],"key":"c4jsNXT6zj"},{"type":"listItem","spread":true,"position":{"start":{"line":7,"column":1},"end":{"line":7,"column":1}},"children":[{"type":"text","value":"Comment on anything interesting, unusual or surprising you found in the maps.","position":{"start":{"line":7,"column":1},"end":{"line":7,"column":1}},"key":"X7Sg5DbtaD"}],"key":"AeL6ptRUBD"}],"key":"H4odX8A5he"}],"key":"rYoCc9QIkS"},{"type":"block","kind":"notebook-code","children":[{"type":"code","lang":"python","executable":true,"value":"","key":"xHuJ5mI9Os"},{"type":"output","id":"4kXNiayaXe1F6qak3xbN2","data":[],"key":"xqjlxK3MIv"}],"key":"X8XjCHbxiy"},{"type":"block","kind":"notebook-content","children":[{"type":"thematicBreak","position":{"start":{"line":1,"column":1},"end":{"line":1,"column":1}},"key":"tq5FRXpYHE"},{"type":"heading","depth":2,"position":{"start":{"line":3,"column":1},"end":{"line":3,"column":1}},"children":[{"type":"text","value":"Credits","position":{"start":{"line":3,"column":1},"end":{"line":3,"column":1}},"key":"qhdVcj62iU"}],"identifier":"credits","label":"Credits","html_id":"credits","implicit":true,"key":"Sdc0JwwIJ4"},{"type":"paragraph","position":{"start":{"line":5,"column":1},"end":{"line":5,"column":1}},"children":[{"type":"text","value":"This notebook is part of ","position":{"start":{"line":5,"column":1},"end":{"line":5,"column":1}},"key":"WEWjLPFoB8"},{"type":"link","url":"https://brian-rose.github.io/ClimateLaboratoryBook","position":{"start":{"line":5,"column":1},"end":{"line":5,"column":1}},"children":[{"type":"text","value":"The Climate Laboratory","position":{"start":{"line":5,"column":1},"end":{"line":5,"column":1}},"key":"KtTdOP0eXt"}],"urlSource":"https://brian-rose.github.io/ClimateLaboratoryBook","key":"XKyZgbPKrL"},{"type":"text","value":", an open-source textbook developed and maintained by ","position":{"start":{"line":5,"column":1},"end":{"line":5,"column":1}},"key":"izLpEQ0mlK"},{"type":"link","url":"http://www.atmos.albany.edu/facstaff/brose/index.html","position":{"start":{"line":5,"column":1},"end":{"line":5,"column":1}},"children":[{"type":"text","value":"Brian E. J. Rose","position":{"start":{"line":5,"column":1},"end":{"line":5,"column":1}},"key":"trSNRwPSNq"}],"urlSource":"http://www.atmos.albany.edu/facstaff/brose/index.html","key":"M9qtFZxB85"},{"type":"text","value":", University at Albany.","position":{"start":{"line":5,"column":1},"end":{"line":5,"column":1}},"key":"pvXeTsi9CU"}],"key":"zijcfVb0NL"},{"type":"paragraph","position":{"start":{"line":7,"column":1},"end":{"line":8,"column":1}},"children":[{"type":"text","value":"It is licensed for free and open consumption under the\n","position":{"start":{"line":7,"column":1},"end":{"line":7,"column":1}},"key":"lOVB2LCFME"},{"type":"link","url":"https://creativecommons.org/licenses/by/4.0/","position":{"start":{"line":7,"column":1},"end":{"line":7,"column":1}},"children":[{"type":"text","value":"Creative Commons Attribution 4.0 International (CC BY 4.0)","position":{"start":{"line":7,"column":1},"end":{"line":7,"column":1}},"key":"Jgh4uUqs1R"}],"urlSource":"https://creativecommons.org/licenses/by/4.0/","key":"x2uirRnBLr"},{"type":"text","value":" license.","position":{"start":{"line":7,"column":1},"end":{"line":7,"column":1}},"key":"NVt2A5YVer"}],"key":"WGH4O3JTXG"},{"type":"paragraph","position":{"start":{"line":10,"column":1},"end":{"line":10,"column":1}},"children":[{"type":"text","value":"Development of these notes and the ","position":{"start":{"line":10,"column":1},"end":{"line":10,"column":1}},"key":"UIfyXbWjI9"},{"type":"link","url":"https://github.com/climlab/climlab","position":{"start":{"line":10,"column":1},"end":{"line":10,"column":1}},"children":[{"type":"text","value":"climlab software","position":{"start":{"line":10,"column":1},"end":{"line":10,"column":1}},"key":"GhC2K0bE7I"}],"urlSource":"https://github.com/climlab/climlab","error":true,"key":"GSP9jbXnBs"},{"type":"text","value":" is partially supported by the National Science Foundation under award AGS-1455071 to Brian Rose. Any opinions, findings, conclusions or recommendations expressed here are mine and do not necessarily reflect the views of the National Science Foundation.","position":{"start":{"line":10,"column":1},"end":{"line":10,"column":1}},"key":"cDoixgjYdQ"}],"key":"PBkbO8D1dL"},{"type":"thematicBreak","position":{"start":{"line":11,"column":1},"end":{"line":11,"column":1}},"key":"ne1OqIL1Ww"}],"key":"opba7xUAhS"}],"key":"qs1cixHurn"},"references":{"cite":{"order":[],"data":{}}},"footer":{"navigation":{"prev":{"title":"Assignment: Feedbacks in the Radiative-Convective Model","url":"/courseware/assignment-rcm-feedback","group":"The Climate Laboratory"},"next":{"title":"Assignment: Insolation and orbital parameters","url":"/courseware/assignment-insolation-orbit","group":"The Climate Laboratory"}}},"domain":"http://localhost:3000"}