{"version":2,"kind":"Notebook","sha256":"dc81897eeb03502ee269764b446d53f0d1e2e2866c4774fc28744e00b79cd947","slug":"courseware.assignment-cesm-climate-change","location":"/courseware/assignment-cesm-climate-change.ipynb","dependencies":[],"frontmatter":{"title":"Assignment: Climate change in the CESM simulations","content_includes_title":false,"kernelspec":{"name":"python3","display_name":"Python 3","language":"python"},"authors":[{"id":"brian-rose","nameParsed":{"literal":"Brian E. J. Rose","given":"Brian E. J.","family":"Rose"},"name":"Brian E. J. Rose","orcid":"0000-0002-9961-3821","email":"brose@albany.edu","affiliations":["UAlbany"],"url":"https://brian-rose.github.io","github":"brian-rose","bluesky":"@brianejrose.bsky.social","linkedin":"https://www.linkedin.com/in/brian-rose-37bb55106/"}],"doi":"https://doi.org/10.5281/zenodo.4265097","open_access":true,"license":{"content":{"id":"CC-BY-4.0","url":"https://creativecommons.org/licenses/by/4.0/","name":"Creative Commons Attribution 4.0 International","free":true,"CC":true}},"github":"https://github.com/brian-rose/ClimateLaboratoryBook","affiliations":[{"id":"UAlbany","name":"University at Albany (SUNY)","department":"Atmospheric and Environmental Sciences","url":"https://www.albany.edu/daes"}],"abbreviations":{"TOA":"Top of Atmosphere","SW":"Shortwave","LW":"Longwave","UV":"Ultraviolet","IR":"Infrared","OLR":"Outgoing Longwave Radiation","ASR":"Absorbed Shortwave Radiation","CC":"Clausius-Clapeyron","LWP":"Liquid Water Path","CRE":"Cloud Radiative Effect","ECS":"Equilibrium Climate Sensitivity","TCR":"Transient Climate Response","WV":"Water Vapor","LR":"Lapse Rate","LCL":"Lifting Condensation Level","LGM":"Last Glacial Maximum","MSE":"Moist Static Energy","AHT":"Atmospheric Heat Transport","OHT":"Ocean Heat Transport","THT":"Total Heat Transport","1D":"One-dimensional","2D":"Two-dimensional","3D":"Three-dimensional","lat":"latitude","lon":"longitude","ppm":"parts per million","ppmv":"parts per million by volume","hPa":"hectoPascals","Ma":"Millions of years","LHS":"Left hand side","RHS":"Right hand side","EBM":"Energy Balance Model","GCM":"Global Circulation Model","OGCM":"Ocean Global Circulation Model","AGCM":"Atmospheric Global Circulation Model","AOGCM":"Atmosphere-Ocean Global Circulation Model","CGCM":"Coupled Global Circulation Model","RC":"Radiative-Convective","RCM":"Radiative-Convective Model","RCE":"Radiative-Convective Equilibrium","SCM":"Single-Column Model","ESM":"Earth System Model","SD":"Statistical-Dynamical","EMIC":"Earth System Model of Intermediate Complexity","IAM":"Integrated Asessment Model","SOM":"Slab Ocean Model","CESM":"Community Earth System Model","CAM":"Community Atmosphere Model","POP":"Parallel Ocean Program","CLM":"Community Land Model","CICE":"Community Ice CodE","RRTMG":"Rapid Radiative Transfer Model","ODE":"Ordinary Differential Equation","PDE":"Partial Differential Equation","FTCS":"Forward Time, Centered Space","URL":"Uniform Research Locator","CMIP":"Coupled Model Intercomparison Project","IPCC":"Intergovernmental Panel on Climate Change","AR5":"Fifth Assessment Report","AR6":"Sixth Assessment Report","WG1":"Working Group 1","NCAR":"National Center for Atmospheric Research","AMS":"American Meteorological Society","NCEP":"National Centers for Environmental Prediction"},"numbering":{"title":{"offset":1}},"edit_url":"https://github.com/brian-rose/ClimateLaboratoryBook/blob/main/courseware/assignment-cesm-climate-change.ipynb","exports":[{"format":"ipynb","filename":"assignment-cesm-climate-change.ipynb","url":"/ClimateLaboratoryBook/build/assignment-cesm-clim-b8fe3fa6ba551c0190014f996d6d147a.ipynb"}]},"widgets":{},"mdast":{"type":"root","children":[{"type":"block","kind":"notebook-content","children":[{"type":"paragraph","position":{"start":{"line":3,"column":1},"end":{"line":3,"column":1}},"children":[{"type":"text","value":"This notebook is part of ","position":{"start":{"line":3,"column":1},"end":{"line":3,"column":1}},"key":"kRuWM6Ax8Q"},{"type":"link","url":"https://brian-rose.github.io/ClimateLaboratoryBook","position":{"start":{"line":3,"column":1},"end":{"line":3,"column":1}},"children":[{"type":"text","value":"The Climate Laboratory","position":{"start":{"line":3,"column":1},"end":{"line":3,"column":1}},"key":"rsZAdP3VtZ"}],"urlSource":"https://brian-rose.github.io/ClimateLaboratoryBook","key":"sMJg0ucmtP"},{"type":"text","value":" by ","position":{"start":{"line":3,"column":1},"end":{"line":3,"column":1}},"key":"P4cLqh8I5F"},{"type":"link","url":"http://www.atmos.albany.edu/facstaff/brose/index.html","position":{"start":{"line":3,"column":1},"end":{"line":3,"column":1}},"children":[{"type":"text","value":"Brian E. J. Rose","position":{"start":{"line":3,"column":1},"end":{"line":3,"column":1}},"key":"mg0VRINgcg"}],"urlSource":"http://www.atmos.albany.edu/facstaff/brose/index.html","key":"UkBPK1AaIL"},{"type":"text","value":", University at Albany.","position":{"start":{"line":3,"column":1},"end":{"line":3,"column":1}},"key":"jm5jtLew5U"}],"key":"A0gwOOtxuM"}],"key":"byJm5CZYXk"},{"type":"block","kind":"notebook-content","children":[{"type":"heading","depth":2,"position":{"start":{"line":1,"column":1},"end":{"line":1,"column":1}},"children":[{"type":"text","value":"Part 1","position":{"start":{"line":1,"column":1},"end":{"line":1,"column":1}},"key":"h9DbM7MOe0"}],"identifier":"part-1","label":"Part 1","html_id":"part-1","implicit":true,"key":"NgdwBLqQ5W"},{"type":"paragraph","position":{"start":{"line":3,"column":1},"end":{"line":3,"column":1}},"children":[{"type":"text","value":"Following the examples in the ","position":{"start":{"line":3,"column":1},"end":{"line":3,"column":1}},"key":"N7ValzoOGW"},{"type":"link","url":"https://brian-rose.github.io/ClimateLaboratoryBook/courseware/transient-cesm.html","position":{"start":{"line":3,"column":1},"end":{"line":3,"column":1}},"children":[{"type":"text","value":"lecture notes","position":{"start":{"line":3,"column":1},"end":{"line":3,"column":1}},"key":"ZNGZ8qOkeB"}],"urlSource":"https://brian-rose.github.io/ClimateLaboratoryBook/courseware/transient-cesm.html","key":"yvagvhLQgH"},{"type":"text","value":", open the four ","key":"OKd8jIRjTA"},{"type":"abbreviation","title":"Community Earth System Model","children":[{"type":"text","value":"CESM","key":"XTE0yVlLMM"}],"key":"XEoXX9hKSA"},{"type":"text","value":" simu","key":"fTFQwRgUWj"},{"type":"abbreviation","title":"latitude","children":[{"type":"text","value":"lat","key":"gGWminM5d3"}],"key":"ZYoplJpR0a"},{"type":"text","value":"ions (fully coupled and slab ocean versions).","key":"U1ZqJG3odT"}],"key":"FAEUZ0RKTb"},{"type":"paragraph","position":{"start":{"line":5,"column":1},"end":{"line":5,"column":1}},"children":[{"type":"text","value":"Calcu","key":"KF1Jls8NBB"},{"type":"abbreviation","title":"latitude","children":[{"type":"text","value":"lat","key":"r5e18AahTy"}],"key":"bjoXBP6q7Q"},{"type":"text","value":"e timeseries of ","key":"NFYHMBRqm4"},{"type":"strong","position":{"start":{"line":5,"column":1},"end":{"line":5,"column":1}},"children":[{"type":"text","value":"global mean ","key":"kDu8FmXAB9"},{"type":"abbreviation","title":"Absorbed Shortwave Radiation","children":[{"type":"text","value":"ASR","key":"EZS4xOKuPD"}],"key":"piRWUg5Yjm"},{"type":"text","value":" and ","key":"SSKbuON878"},{"type":"abbreviation","title":"Outgoing Longwave Radiation","children":[{"type":"text","value":"OLR","key":"rHipoCNoU2"}],"key":"FUE37U3lIS"}],"key":"VZECtsME2A"},{"type":"text","value":" and store each of these as a new variable. ","position":{"start":{"line":5,"column":1},"end":{"line":5,"column":1}},"key":"Elb9RlZaoQ"},{"type":"emphasis","position":{"start":{"line":5,"column":1},"end":{"line":5,"column":1}},"children":[{"type":"text","value":"Recall that ","key":"N4QTWOebkX"},{"type":"abbreviation","title":"Absorbed Shortwave Radiation","children":[{"type":"text","value":"ASR","key":"bpzNs682oz"}],"key":"HqibjVo04f"},{"type":"text","value":" is called ","key":"znQw8XB0D7"},{"type":"inlineCode","value":"FSNT","position":{"start":{"line":5,"column":1},"end":{"line":5,"column":1}},"key":"ETDGpKkWjC"},{"type":"text","value":" in the ","key":"ZwW8tawoHZ"},{"type":"abbreviation","title":"Community Earth System Model","children":[{"type":"text","value":"CESM","key":"jhNwojitTb"}],"key":"VJzIn3wkJC"},{"type":"text","value":" output, and ","key":"roCuLkDi4q"},{"type":"abbreviation","title":"Outgoing Longwave Radiation","children":[{"type":"text","value":"OLR","key":"QFThECpHQo"}],"key":"XVUpjzorfX"},{"type":"text","value":" is called ","key":"d0di68tpPN"},{"type":"inlineCode","value":"FLNT","position":{"start":{"line":5,"column":1},"end":{"line":5,"column":1}},"key":"fWHcte3NP6"},{"type":"text","value":".","position":{"start":{"line":5,"column":1},"end":{"line":5,"column":1}},"key":"QjAeyulpAK"}],"key":"ZKJCFLrAZj"}],"key":"vbkB55yuGZ"},{"type":"paragraph","position":{"start":{"line":7,"column":1},"end":{"line":7,"column":1}},"children":[{"type":"text","value":"Plot a timeseries of ","position":{"start":{"line":7,"column":1},"end":{"line":7,"column":1}},"key":"n9xSSg34n1"},{"type":"strong","position":{"start":{"line":7,"column":1},"end":{"line":7,"column":1}},"children":[{"type":"text","value":"(","key":"widuBCiioL"},{"type":"abbreviation","title":"Absorbed Shortwave Radiation","children":[{"type":"text","value":"ASR","key":"A8tderOy1h"}],"key":"umSGJcyf5d"},{"type":"text","value":" - ","key":"v0xfdHAwf0"},{"type":"abbreviation","title":"Outgoing Longwave Radiation","children":[{"type":"text","value":"OLR","key":"yjsJzYlhPm"}],"key":"iO9Vl6XUIv"},{"type":"text","value":"), the net downward energy flux at the top of the model","key":"UilnYsGZwU"}],"key":"HF76lOjyGT"},{"type":"text","value":", a","key":"FfZt2Lv1sy"},{"type":"abbreviation","title":"longitude","children":[{"type":"text","value":"lon","key":"GiUWpvFA0d"}],"key":"diMozOWOqj"},{"type":"text","value":"g with a ","key":"X1PlOevRMv"},{"type":"strong","position":{"start":{"line":7,"column":1},"end":{"line":7,"column":1}},"children":[{"type":"text","value":"12 month rolling mean","position":{"start":{"line":7,"column":1},"end":{"line":7,"column":1}},"key":"pbHPd7ZuDs"}],"key":"pWtFXkMAsG"},{"type":"text","value":", analogous to the plot of global mean surface air temperature in the lecture notes.","position":{"start":{"line":7,"column":1},"end":{"line":7,"column":1}},"key":"RQPvjCVz4Q"}],"key":"RVWpqWH2nb"},{"type":"paragraph","position":{"start":{"line":9,"column":1},"end":{"line":9,"column":1}},"children":[{"type":"emphasis","position":{"start":{"line":9,"column":1},"end":{"line":9,"column":1}},"children":[{"type":"text","value":"Note that the rolling mean is important here because, just like with surface air temperature, there is a large seasonal cycle which makes it harder to see evidence of the climate change signal we wish to focus on.","position":{"start":{"line":9,"column":1},"end":{"line":9,"column":1}},"key":"AxYJu4U1iI"}],"key":"hqSYkbpMJm"}],"key":"ANnaRcdC4B"}],"key":"ZA5uLVdDmt"},{"type":"block","kind":"notebook-code","children":[{"type":"code","lang":"python","executable":true,"value":"","key":"cm5cH5Niml"},{"type":"output","id":"1ksEJeRsDtAnxJrVQ2eTs","data":[],"key":"rQPuFTkJjR"}],"key":"Dn1yYxhZzG"},{"type":"block","kind":"notebook-content","children":[{"type":"heading","depth":2,"position":{"start":{"line":1,"column":1},"end":{"line":1,"column":1}},"children":[{"type":"text","value":"Part 2","position":{"start":{"line":1,"column":1},"end":{"line":1,"column":1}},"key":"CAQIqonuOd"}],"identifier":"part-2","label":"Part 2","html_id":"part-2","implicit":true,"key":"B1X9qrgvyB"},{"type":"paragraph","position":{"start":{"line":3,"column":1},"end":{"line":3,"column":1}},"children":[{"type":"text","value":"Calcu","key":"tsTF90t7HP"},{"type":"abbreviation","title":"latitude","children":[{"type":"text","value":"lat","key":"Sgt81FLOYT"}],"key":"nV0WBN5eCI"},{"type":"text","value":"e and show the ","key":"hEksDDC6OF"},{"type":"strong","position":{"start":{"line":3,"column":1},"end":{"line":3,"column":1}},"children":[{"type":"text","value":"time-average ","key":"Roj5DdeYSC"},{"type":"abbreviation","title":"Absorbed Shortwave Radiation","children":[{"type":"text","value":"ASR","key":"MIQbHjRw5P"}],"key":"sJjhPP3ZZX"}],"key":"atNJIRzDR2"},{"type":"text","value":" and ","position":{"start":{"line":3,"column":1},"end":{"line":3,"column":1}},"key":"C4QQBW4WQQ"},{"type":"strong","position":{"start":{"line":3,"column":1},"end":{"line":3,"column":1}},"children":[{"type":"text","value":"time-average ","key":"FiLxiaNY31"},{"type":"abbreviation","title":"Outgoing Longwave Radiation","children":[{"type":"text","value":"OLR","key":"A89prPEjFV"}],"key":"ogR4eCZgu1"}],"key":"TH2ffr6rIh"},{"type":"text","value":" over the final 10 or 20 years of each simu","key":"tF4YLJLgts"},{"type":"abbreviation","title":"latitude","children":[{"type":"text","value":"lat","key":"PnF3UiQxw2"}],"key":"Eph1ZMUO2I"},{"type":"text","value":"ion. Following the lecture notes, use the 20-year slice for the fully coupled simu","key":"pypNIJNADn"},{"type":"abbreviation","title":"latitude","children":[{"type":"text","value":"lat","key":"mOqGZJZQfa"}],"key":"QwrJBt4bXc"},{"type":"text","value":"ions, and the 10-year slice for the slab ocean simu","key":"XmSV5hFHMK"},{"type":"abbreviation","title":"latitude","children":[{"type":"text","value":"lat","key":"SBbh8dVNvQ"}],"key":"FnZWes0FJL"},{"type":"text","value":"ions.","key":"oejBOQTRNd"}],"key":"EaBTc47SDL"}],"key":"Zjr8PLa51g"},{"type":"block","kind":"notebook-code","children":[{"type":"code","lang":"python","executable":true,"value":"","key":"ONn9nZVDAv"},{"type":"output","id":"zFmN6MT3TCiXTdsIDEYse","data":[],"key":"YQltHvfXmZ"}],"key":"DLCvcrE7Eq"},{"type":"block","kind":"notebook-content","children":[{"type":"heading","depth":2,"position":{"start":{"line":1,"column":1},"end":{"line":1,"column":1}},"children":[{"type":"text","value":"Part 3","position":{"start":{"line":1,"column":1},"end":{"line":1,"column":1}},"key":"NSwfh1otwi"}],"identifier":"part-3","label":"Part 3","html_id":"part-3","implicit":true,"key":"IXqCsDK0S2"},{"type":"paragraph","position":{"start":{"line":3,"column":1},"end":{"line":3,"column":1}},"children":[{"type":"text","value":"Based on your plots and numerical results from Parts 1 and 2, answer these questions:","position":{"start":{"line":3,"column":1},"end":{"line":3,"column":1}},"key":"aXZ3suNADU"}],"key":"tIUkADCIUm"},{"type":"list","ordered":true,"start":1,"spread":false,"position":{"start":{"line":5,"column":1},"end":{"line":8,"column":1}},"children":[{"type":"listItem","spread":true,"position":{"start":{"line":5,"column":1},"end":{"line":5,"column":1}},"children":[{"type":"text","value":"Are the two control simu","key":"EQtLjkD1Xt"},{"type":"abbreviation","title":"latitude","children":[{"type":"text","value":"lat","key":"Fx8LdTVS2D"}],"key":"nt5JGnjQoQ"},{"type":"text","value":"ions (fully coupled and slab ocean) near energy balance?","key":"iFao5Rleig"}],"key":"rWLqhAbCdT"},{"type":"listItem","spread":true,"position":{"start":{"line":6,"column":1},"end":{"line":6,"column":1}},"children":[{"type":"text","value":"In the fully coupled CO2 ramp simu","key":"E4TJR8DYwS"},{"type":"abbreviation","title":"latitude","children":[{"type":"text","value":"lat","key":"QDfiXONJUi"}],"key":"cAegd8wkSr"},{"type":"text","value":"ion, does the energy imbalance (","key":"JyHD6Z2hsx"},{"type":"abbreviation","title":"Absorbed Shortwave Radiation","children":[{"type":"text","value":"ASR","key":"vz0j2Vl5VQ"}],"key":"TwRRRBPvO0"},{"type":"text","value":"-","key":"foFKgwOBW4"},{"type":"abbreviation","title":"Outgoing Longwave Radiation","children":[{"type":"text","value":"OLR","key":"rZoNEXdzKz"}],"key":"hry6vefaMX"},{"type":"text","value":") increase or decrease with time? What is the imbalance at the end of the 80 year simu","key":"HcVfGzlhp9"},{"type":"abbreviation","title":"latitude","children":[{"type":"text","value":"lat","key":"JNWf7vccAq"}],"key":"XOaiBLvTRO"},{"type":"text","value":"ion?","key":"CfonO6YlRp"}],"key":"zpAlKZQUMu"},{"type":"listItem","spread":true,"position":{"start":{"line":7,"column":1},"end":{"line":7,"column":1}},"children":[{"type":"text","value":"Answer the same questions for the slab ocean abrupt 2xCO2 simu","key":"yq93vDEgs2"},{"type":"abbreviation","title":"latitude","children":[{"type":"text","value":"lat","key":"sVlR4wvwc7"}],"key":"uC2sK9lbIu"},{"type":"text","value":"ion.","key":"mcLR3CBMJR"}],"key":"FBsPKfQdXP"},{"type":"listItem","spread":true,"position":{"start":{"line":8,"column":1},"end":{"line":8,"column":1}},"children":[{"type":"text","value":"Explain in words why the timeseries of ","key":"RZSj7Xw3Ud"},{"type":"abbreviation","title":"Absorbed Shortwave Radiation","children":[{"type":"text","value":"ASR","key":"pb9xKVgJe4"}],"key":"PpgoDD34cJ"},{"type":"text","value":"-","key":"cbSUyFm3n8"},{"type":"abbreviation","title":"Outgoing Longwave Radiation","children":[{"type":"text","value":"OLR","key":"cJ5fYhnrxf"}],"key":"tlofuPPX67"},{"type":"text","value":" look very different in the fully coupled simu","key":"rtdqFCxSg7"},{"type":"abbreviation","title":"latitude","children":[{"type":"text","value":"lat","key":"wvrdhxPwQ8"}],"key":"nU6zeFTe5Q"},{"type":"text","value":"ion (1%/year CO2 ramp) versus the slab ocean simu","key":"lvTxmiGbET"},{"type":"abbreviation","title":"latitude","children":[{"type":"text","value":"lat","key":"Ue9Kb0v3vl"}],"key":"gLljn8SlUE"},{"type":"text","value":"ion (abrupt 2xCO2). ","key":"wt4V7aWCnD"},{"type":"emphasis","position":{"start":{"line":8,"column":1},"end":{"line":8,"column":1}},"children":[{"type":"text","value":"Think about both the different radiative forcings and the different ocean heat capacities.","position":{"start":{"line":8,"column":1},"end":{"line":8,"column":1}},"key":"QxI5IK3Eb9"}],"key":"yJy5cuE2Yd"}],"key":"bJuyoBfrxl"}],"key":"ubsC9t3C5J"}],"key":"S3YYeeHflk"},{"type":"block","kind":"notebook-code","children":[{"type":"code","lang":"python","executable":true,"value":"","key":"DFA9rc2tg8"},{"type":"output","id":"Dq4uwT-xdXDl0cc1A4NmK","data":[],"key":"wVspM8KvgJ"}],"key":"XaUVpENCIF"},{"type":"block","kind":"notebook-content","children":[{"type":"heading","depth":2,"position":{"start":{"line":1,"column":1},"end":{"line":1,"column":1}},"children":[{"type":"text","value":"Part 4","position":{"start":{"line":1,"column":1},"end":{"line":1,"column":1}},"key":"t4Ih1d6nS5"}],"identifier":"part-4","label":"Part 4","html_id":"part-4","implicit":true,"key":"eloXNew5Ux"},{"type":"paragraph","position":{"start":{"line":3,"column":1},"end":{"line":3,"column":1}},"children":[{"type":"text","value":"Does the global average ","key":"zb4rBOQgm2"},{"type":"abbreviation","title":"Absorbed Shortwave Radiation","children":[{"type":"text","value":"ASR","key":"q9U4iN4Dma"}],"key":"xFcZjAklrj"},{"type":"text","value":" ","key":"neTKeMt9mG"},{"type":"strong","position":{"start":{"line":3,"column":1},"end":{"line":3,"column":1}},"children":[{"type":"text","value":"increase","position":{"start":{"line":3,"column":1},"end":{"line":3,"column":1}},"key":"wnxrIAugLw"}],"key":"V5SKopF5sQ"},{"type":"text","value":" or ","position":{"start":{"line":3,"column":1},"end":{"line":3,"column":1}},"key":"VUDD04tmsu"},{"type":"strong","position":{"start":{"line":3,"column":1},"end":{"line":3,"column":1}},"children":[{"type":"text","value":"decrease","position":{"start":{"line":3,"column":1},"end":{"line":3,"column":1}},"key":"w69pNh8eIi"}],"key":"SjKEHl4M1R"},{"type":"text","value":" because of CO2-driven warming in the ","key":"MbwbvpeXsf"},{"type":"abbreviation","title":"Community Earth System Model","children":[{"type":"text","value":"CESM","key":"Okiyx9hVKw"}],"key":"AWHjgrEs7w"},{"type":"text","value":"?","key":"noTz8aGc7q"}],"key":"b6OBQGkXDA"},{"type":"paragraph","position":{"start":{"line":5,"column":1},"end":{"line":5,"column":1}},"children":[{"type":"text","value":"Would you describe this as a ","position":{"start":{"line":5,"column":1},"end":{"line":5,"column":1}},"key":"ckJq5HKm3k"},{"type":"strong","position":{"start":{"line":5,"column":1},"end":{"line":5,"column":1}},"children":[{"type":"text","value":"positive","position":{"start":{"line":5,"column":1},"end":{"line":5,"column":1}},"key":"t4QShEn2d7"}],"key":"lU3o3pKmVM"},{"type":"text","value":" or ","position":{"start":{"line":5,"column":1},"end":{"line":5,"column":1}},"key":"E0vfNj5M7D"},{"type":"strong","position":{"start":{"line":5,"column":1},"end":{"line":5,"column":1}},"children":[{"type":"text","value":"negative","position":{"start":{"line":5,"column":1},"end":{"line":5,"column":1}},"key":"jPPq1u62cO"}],"key":"JSYRgaX4c4"},{"type":"text","value":" feedback?","position":{"start":{"line":5,"column":1},"end":{"line":5,"column":1}},"key":"vd4BXR4EMq"}],"key":"nM0YY7XZwY"}],"key":"LsMWZotsHj"},{"type":"block","kind":"notebook-code","children":[{"type":"code","lang":"python","executable":true,"value":"","key":"u5Yz3MEZPk"},{"type":"output","id":"TIUxs_t_OucoI5JCeG_SQ","data":[],"key":"ABoR7S60rF"}],"key":"e8f1NG6Kri"},{"type":"block","kind":"notebook-content","children":[{"type":"heading","depth":2,"position":{"start":{"line":1,"column":1},"end":{"line":1,"column":1}},"children":[{"type":"text","value":"Part 5","position":{"start":{"line":1,"column":1},"end":{"line":1,"column":1}},"key":"c2iFx68RvF"}],"identifier":"part-5","label":"Part 5","html_id":"part-5","implicit":true,"key":"pXDZ8JLHIb"},{"type":"paragraph","position":{"start":{"line":3,"column":1},"end":{"line":3,"column":1}},"children":[{"type":"text","value":"In the previous question you looked at the global average change in ","key":"ghpZg5T0dJ"},{"type":"abbreviation","title":"Absorbed Shortwave Radiation","children":[{"type":"text","value":"ASR","key":"zQ4iv7bhuk"}],"key":"EPva2bxZJT"},{"type":"text","value":". Now I want you to look at how different parts of the world contribute to this change.","key":"Jozndnd4fV"}],"key":"ajIx0gq28c"},{"type":"paragraph","position":{"start":{"line":5,"column":1},"end":{"line":5,"column":1}},"children":[{"type":"strong","position":{"start":{"line":5,"column":1},"end":{"line":5,"column":1}},"children":[{"type":"abbreviation","title":"Millions of years","children":[{"type":"text","value":"Ma","key":"ESvgbgrhcg"}],"key":"BoNCgvtjpe"},{"type":"text","value":"ke a map","key":"oW1TwnYvPd"}],"key":"TevAuQtbs9"},{"type":"text","value":" of the ","position":{"start":{"line":5,"column":1},"end":{"line":5,"column":1}},"key":"C8cATplCWB"},{"type":"strong","position":{"start":{"line":5,"column":1},"end":{"line":5,"column":1}},"children":[{"type":"text","value":"change in ","key":"qCd2XjGfFP"},{"type":"abbreviation","title":"Absorbed Shortwave Radiation","children":[{"type":"text","value":"ASR","key":"CschlllmJU"}],"key":"bdkXu1inj5"}],"key":"hgRmeQHqcq"},{"type":"text","value":" due to the CO2 forcing. Use the average over the last 20 years of the coupled CO2 ramp simu","key":"YJMePEOxoS"},{"type":"abbreviation","title":"latitude","children":[{"type":"text","value":"lat","key":"LORcqmBNvf"}],"key":"oLxz4WTy5m"},{"type":"text","value":"ion, comparing against the average over the last 20 years of the control simu","key":"dw1SUJTHaW"},{"type":"abbreviation","title":"latitude","children":[{"type":"text","value":"lat","key":"JLhaJbqfHu"}],"key":"ckqo0ViTqp"},{"type":"text","value":"ion.","key":"tT9CChXVyn"}],"key":"u03cLSxwTU"}],"key":"W3AkECjCVd"},{"type":"block","kind":"notebook-code","children":[{"type":"code","lang":"python","executable":true,"value":"","key":"ImBj0ydnpF"},{"type":"output","id":"WM5JmdDHpKUkxfys_qU9h","data":[],"key":"CyxA0Geimu"}],"key":"ZqU4MPDw7t"},{"type":"block","kind":"notebook-content","children":[{"type":"heading","depth":2,"position":{"start":{"line":1,"column":1},"end":{"line":1,"column":1}},"children":[{"type":"text","value":"Part 6","position":{"start":{"line":1,"column":1},"end":{"line":1,"column":1}},"key":"w6npORceNS"}],"identifier":"part-6","label":"Part 6","html_id":"part-6","implicit":true,"key":"UwlrP0iVFj"},{"type":"paragraph","position":{"start":{"line":3,"column":1},"end":{"line":3,"column":1}},"children":[{"type":"text","value":"Repeat part 5, but this time instead of the change in ","key":"XQLdzi9ORF"},{"type":"abbreviation","title":"Absorbed Shortwave Radiation","children":[{"type":"text","value":"ASR","key":"aVCLq9Xm7z"}],"key":"Nxa6VVmyyj"},{"type":"text","value":", look at the just change in the ","key":"sYEnLhpJIK"},{"type":"strong","position":{"start":{"line":3,"column":1},"end":{"line":3,"column":1}},"children":[{"type":"text","value":"clear-sky","position":{"start":{"line":3,"column":1},"end":{"line":3,"column":1}},"key":"auanQNf4UT"}],"key":"i5DWPJkNT9"},{"type":"text","value":" component of ","key":"kRgxqZDSnS"},{"type":"abbreviation","title":"Absorbed Shortwave Radiation","children":[{"type":"text","value":"ASR","key":"XsensgBmcJ"}],"key":"jCJvUsFWXy"},{"type":"text","value":". You can find this in the output field called ","key":"HT2Poa52hD"},{"type":"inlineCode","value":"FSNTC","position":{"start":{"line":3,"column":1},"end":{"line":3,"column":1}},"key":"LqATG0hQUW"},{"type":"text","value":".","position":{"start":{"line":3,"column":1},"end":{"line":3,"column":1}},"key":"dpJ2LrAR7M"}],"key":"bmc5XSQhsh"},{"type":"paragraph","position":{"start":{"line":5,"column":1},"end":{"line":5,"column":1}},"children":[{"type":"emphasis","position":{"start":{"line":5,"column":1},"end":{"line":5,"column":1}},"children":[{"type":"text","value":"The ","position":{"start":{"line":5,"column":1},"end":{"line":5,"column":1}},"key":"rQCNXKd0Pn"},{"type":"inlineCode","value":"FSNTC","position":{"start":{"line":5,"column":1},"end":{"line":5,"column":1}},"key":"A9iufWux0j"},{"type":"text","value":" field shows shortwave absorption in the absence of clouds, so the ","position":{"start":{"line":5,"column":1},"end":{"line":5,"column":1}},"key":"xgngoD2UXO"},{"type":"strong","position":{"start":{"line":5,"column":1},"end":{"line":5,"column":1}},"children":[{"type":"text","value":"change","position":{"start":{"line":5,"column":1},"end":{"line":5,"column":1}},"key":"CB8xHEoziM"}],"key":"EsokqZO2hj"},{"type":"text","value":" in ","position":{"start":{"line":5,"column":1},"end":{"line":5,"column":1}},"key":"nh6XtModEX"},{"type":"inlineCode","value":"FSNTC","position":{"start":{"line":5,"column":1},"end":{"line":5,"column":1}},"key":"W9199ci5m5"},{"type":"text","value":" shows how absorption and reflection of shortwave are affected by processes other than clouds.","position":{"start":{"line":5,"column":1},"end":{"line":5,"column":1}},"key":"xRR21CwtYm"}],"key":"hrNJNLmjZo"}],"key":"VLlKrNjWhk"}],"key":"qFbr7S1BbY"},{"type":"block","kind":"notebook-code","children":[{"type":"code","lang":"python","executable":true,"value":"","key":"QESnjcYikB"},{"type":"output","id":"RPtLg1TkvY4WiH-NiBY-h","data":[],"key":"lXBzWNGo9i"}],"key":"NJqV5KNHkc"},{"type":"block","kind":"notebook-content","children":[{"type":"heading","depth":2,"position":{"start":{"line":1,"column":1},"end":{"line":1,"column":1}},"children":[{"type":"text","value":"Part 7","position":{"start":{"line":1,"column":1},"end":{"line":1,"column":1}},"key":"Z1wqNKUTBh"}],"identifier":"part-7","label":"Part 7","html_id":"part-7","implicit":true,"key":"YPvmkQ9uQL"},{"type":"paragraph","position":{"start":{"line":3,"column":1},"end":{"line":3,"column":1}},"children":[{"type":"text","value":"Discussion:","position":{"start":{"line":3,"column":1},"end":{"line":3,"column":1}},"key":"dCuVT3n16J"}],"key":"mVsRlzNGUi"},{"type":"list","ordered":false,"spread":false,"position":{"start":{"line":5,"column":1},"end":{"line":7,"column":1}},"children":[{"type":"listItem","spread":true,"position":{"start":{"line":5,"column":1},"end":{"line":5,"column":1}},"children":[{"type":"text","value":"Do your two maps (change in ","key":"mgvMY4mpcp"},{"type":"abbreviation","title":"Absorbed Shortwave Radiation","children":[{"type":"text","value":"ASR","key":"ST4EOpc3lp"}],"key":"oFW9BQ9T79"},{"type":"text","value":", change in clear-sky ","key":"Q1I82fde2X"},{"type":"abbreviation","title":"Absorbed Shortwave Radiation","children":[{"type":"text","value":"ASR","key":"PiPZpV96zl"}],"key":"JWCwKHO5m8"},{"type":"text","value":") look the same?","key":"YXs2dow0Et"}],"key":"wdrn0kHtVM"},{"type":"listItem","spread":true,"position":{"start":{"line":6,"column":1},"end":{"line":6,"column":1}},"children":[{"type":"text","value":"Offer some ideas about why the clear-sky map looks the way it does.","position":{"start":{"line":6,"column":1},"end":{"line":6,"column":1}},"key":"yW6O1lBP7O"}],"key":"hJHOf6Yonu"},{"type":"listItem","spread":true,"position":{"start":{"line":7,"column":1},"end":{"line":7,"column":1}},"children":[{"type":"text","value":"Comment on anything interesting, unusual or surprising you found in the maps.","position":{"start":{"line":7,"column":1},"end":{"line":7,"column":1}},"key":"ovmCQeO1oK"}],"key":"YavcQoqacf"}],"key":"APJhkPQFog"}],"key":"NlcYRbXAwZ"},{"type":"block","kind":"notebook-code","children":[{"type":"code","lang":"python","executable":true,"value":"","key":"DOeiCG1j3s"},{"type":"output","id":"G3T2eFkNMR2GAV4_4z7ve","data":[],"key":"j2FCpLWFtv"}],"key":"YK18WpLdhV"},{"type":"block","kind":"notebook-content","children":[{"type":"thematicBreak","position":{"start":{"line":1,"column":1},"end":{"line":1,"column":1}},"key":"aAVwrcSDmX"},{"type":"heading","depth":2,"position":{"start":{"line":3,"column":1},"end":{"line":3,"column":1}},"children":[{"type":"text","value":"Credits","position":{"start":{"line":3,"column":1},"end":{"line":3,"column":1}},"key":"NlxUpS1yER"}],"identifier":"credits","label":"Credits","html_id":"credits","implicit":true,"key":"NOQMeBFxqE"},{"type":"paragraph","position":{"start":{"line":5,"column":1},"end":{"line":5,"column":1}},"children":[{"type":"text","value":"This notebook is part of ","position":{"start":{"line":5,"column":1},"end":{"line":5,"column":1}},"key":"E7yA8bA9bd"},{"type":"link","url":"https://brian-rose.github.io/ClimateLaboratoryBook","position":{"start":{"line":5,"column":1},"end":{"line":5,"column":1}},"children":[{"type":"text","value":"The Climate Laboratory","position":{"start":{"line":5,"column":1},"end":{"line":5,"column":1}},"key":"jlqPaHCVCS"}],"urlSource":"https://brian-rose.github.io/ClimateLaboratoryBook","key":"bVQcMPky0Z"},{"type":"text","value":", an open-source textbook developed and maintained by ","position":{"start":{"line":5,"column":1},"end":{"line":5,"column":1}},"key":"BRqCBH50ty"},{"type":"link","url":"http://www.atmos.albany.edu/facstaff/brose/index.html","position":{"start":{"line":5,"column":1},"end":{"line":5,"column":1}},"children":[{"type":"text","value":"Brian E. J. Rose","position":{"start":{"line":5,"column":1},"end":{"line":5,"column":1}},"key":"xn7H4XFHL9"}],"urlSource":"http://www.atmos.albany.edu/facstaff/brose/index.html","key":"qvEk4Cabte"},{"type":"text","value":", University at Albany.","position":{"start":{"line":5,"column":1},"end":{"line":5,"column":1}},"key":"b4B6t06SEZ"}],"key":"zMBdYSmhHl"},{"type":"paragraph","position":{"start":{"line":7,"column":1},"end":{"line":8,"column":1}},"children":[{"type":"text","value":"It is licensed for free and open consumption under the\n","position":{"start":{"line":7,"column":1},"end":{"line":7,"column":1}},"key":"d5I99ynnJY"},{"type":"link","url":"https://creativecommons.org/licenses/by/4.0/","position":{"start":{"line":7,"column":1},"end":{"line":7,"column":1}},"children":[{"type":"text","value":"Creative Commons Attribution 4.0 International (CC BY 4.0)","position":{"start":{"line":7,"column":1},"end":{"line":7,"column":1}},"key":"xjo37nAGYL"}],"urlSource":"https://creativecommons.org/licenses/by/4.0/","key":"W4foFAUzQp"},{"type":"text","value":" license.","position":{"start":{"line":7,"column":1},"end":{"line":7,"column":1}},"key":"Xw6N5i2QOI"}],"key":"GSl6ZtOO44"},{"type":"paragraph","position":{"start":{"line":10,"column":1},"end":{"line":10,"column":1}},"children":[{"type":"text","value":"Development of these notes and the ","position":{"start":{"line":10,"column":1},"end":{"line":10,"column":1}},"key":"BPABC0deuc"},{"type":"link","url":"https://github.com/climlab/climlab","position":{"start":{"line":10,"column":1},"end":{"line":10,"column":1}},"children":[{"type":"text","value":"climlab software","position":{"start":{"line":10,"column":1},"end":{"line":10,"column":1}},"key":"wNj8gDBJYl"}],"urlSource":"https://github.com/climlab/climlab","error":true,"key":"kgrIdyMaUq"},{"type":"text","value":" is partially supported by the National Science Foundation under award AGS-1455071 to Brian Rose. Any opinions, findings, conclusions or recommendations expressed here are mine and do not necessarily reflect the views of the National Science Foundation.","position":{"start":{"line":10,"column":1},"end":{"line":10,"column":1}},"key":"rSQg5gXVUw"}],"key":"Dehikb25B1"},{"type":"thematicBreak","position":{"start":{"line":11,"column":1},"end":{"line":11,"column":1}},"key":"L9Fabu3bvJ"}],"key":"NW4UkZfp24"}],"key":"NsmnWoGG9J"},"references":{"cite":{"order":[],"data":{}}},"footer":{"navigation":{"prev":{"title":"Assignment: Feedbacks in the Radiative-Convective Model","url":"/courseware/assignment-rcm-feedback","group":"The Climate Laboratory"},"next":{"title":"Assignment: Insolation and orbital parameters","url":"/courseware/assignment-insolation-orbit","group":"The Climate Laboratory"}}},"domain":"http://localhost:3000"}