{"version":2,"kind":"Notebook","sha256":"fa06c9432748d453240614a85664445f0fbdeab189b53c09a57c33e36929b57c","slug":"courseware.rce","location":"/courseware/rce.ipynb","dependencies":[],"frontmatter":{"title":"Radiative-Convective Equilibrium","content_includes_title":false,"kernelspec":{"name":"python3","display_name":"Python 3 (ipykernel)","language":"python"},"authors":[{"id":"brian-rose","nameParsed":{"literal":"Brian E. J. Rose","given":"Brian E. J.","family":"Rose"},"name":"Brian E. J. Rose","orcid":"0000-0002-9961-3821","email":"brose@albany.edu","affiliations":["UAlbany"],"url":"https://brian-rose.github.io","github":"brian-rose","bluesky":"@brianejrose.bsky.social","linkedin":"https://www.linkedin.com/in/brian-rose-37bb55106/"}],"doi":"https://doi.org/10.5281/zenodo.4265097","open_access":true,"license":{"content":{"id":"CC-BY-4.0","url":"https://creativecommons.org/licenses/by/4.0/","name":"Creative Commons Attribution 4.0 International","free":true,"CC":true}},"github":"https://github.com/brian-rose/ClimateLaboratoryBook","affiliations":[{"id":"UAlbany","name":"University at Albany (SUNY)","department":"Atmospheric and Environmental Sciences","url":"https://www.albany.edu/daes"}],"abbreviations":{"OLR":"Outgoing Longwave Radiation","ASR":"Absorbed Shortwave Radiation","ECS":"Equilibrium Climate Sensitivity","TCR":"Transient Climate Response","EBM":"Energy Balance Model","GCM":"Global Circulation Model","OGCM":"Ocean Global Circulation Model","AGCM":"Atmospheric Global Circulation Model","AOGCM":"Atmosphere-Ocean Global Circulation Model","RCM":"Radiative-Convective Model","RCE":"Radiative-Convective Equilibrium","SCM":"Single-Column Model","ESM":"Earth System Model","CESM":"Community Earth System Model","IPCC":"Intergovernmental Panel on Climate Change","NCAR":"National Center for Atmospheric Research"},"numbering":{"title":{"offset":1}},"edit_url":"https://github.com/brian-rose/ClimateLaboratoryBook/blob/HEAD/courseware/rce.ipynb","exports":[{"format":"ipynb","filename":"rce.ipynb","url":"/ClimateLaboratoryBook/_preview/169/build/rce-da0168321828a8bb992c1f5a4d880fd2.ipynb"}]},"widgets":{},"mdast":{"type":"root","children":[{"type":"block","kind":"notebook-content","data":{"slideshow":{"slide_type":"slide"}},"children":[{"type":"paragraph","position":{"start":{"line":3,"column":1},"end":{"line":3,"column":1}},"children":[{"type":"text","value":"This notebook is part of ","position":{"start":{"line":3,"column":1},"end":{"line":3,"column":1}},"key":"qJmpkgxDXM"},{"type":"link","url":"https://brian-rose.github.io/ClimateLaboratoryBook","position":{"start":{"line":3,"column":1},"end":{"line":3,"column":1}},"children":[{"type":"text","value":"The Climate Laboratory","position":{"start":{"line":3,"column":1},"end":{"line":3,"column":1}},"key":"H1qJG2yNOg"}],"urlSource":"https://brian-rose.github.io/ClimateLaboratoryBook","key":"TRUtNftlke"},{"type":"text","value":" by ","position":{"start":{"line":3,"column":1},"end":{"line":3,"column":1}},"key":"XdZ3fIhKeV"},{"type":"link","url":"http://www.atmos.albany.edu/facstaff/brose/index.html","position":{"start":{"line":3,"column":1},"end":{"line":3,"column":1}},"children":[{"type":"text","value":"Brian E. J. Rose","position":{"start":{"line":3,"column":1},"end":{"line":3,"column":1}},"key":"DxBVahiIGI"}],"urlSource":"http://www.atmos.albany.edu/facstaff/brose/index.html","key":"nKvLTRKZru"},{"type":"text","value":", University at Albany.","position":{"start":{"line":3,"column":1},"end":{"line":3,"column":1}},"key":"IGS3N9EmZs"}],"key":"bg0CoDz1If"}],"key":"uI4NXwbYOq"},{"type":"block","kind":"notebook-content","children":[{"type":"thematicBreak","position":{"start":{"line":1,"column":1},"end":{"line":1,"column":1}},"key":"PRHGhSPzqN"},{"type":"heading","depth":2,"position":{"start":{"line":3,"column":1},"end":{"line":3,"column":1}},"children":[{"type":"text","value":"1. Recap of radiative equilibrium results","position":{"start":{"line":3,"column":1},"end":{"line":3,"column":1}},"key":"D5WFBhkEF9"}],"identifier":"id-1-recap-of-radiative-equilibrium-results","label":"1. Recap of radiative equilibrium results","html_id":"id-1-recap-of-radiative-equilibrium-results","implicit":true,"key":"zoHpiCb4U0"},{"type":"thematicBreak","position":{"start":{"line":4,"column":1},"end":{"line":4,"column":1}},"key":"y4hbaZwabn"},{"type":"paragraph","position":{"start":{"line":6,"column":1},"end":{"line":6,"column":1}},"children":[{"type":"text","value":"Here we summarize results we generated in the ","position":{"start":{"line":6,"column":1},"end":{"line":6,"column":1}},"key":"xHma5NgCoe"},{"type":"link","url":"https://brian-rose.github.io/ClimateLaboratoryBook/courseware/radeq.html","position":{"start":{"line":6,"column":1},"end":{"line":6,"column":1}},"children":[{"type":"text","value":"Lecture on radiative equilibrium","position":{"start":{"line":6,"column":1},"end":{"line":6,"column":1}},"key":"mXy3dh94ur"}],"urlSource":"https://brian-rose.github.io/ClimateLaboratoryBook/courseware/radeq.html","key":"GlEmoITcLR"},{"type":"text","value":".","position":{"start":{"line":6,"column":1},"end":{"line":6,"column":1}},"key":"N4EKVp4b9c"}],"key":"DJEeJXMbC2"},{"type":"paragraph","position":{"start":{"line":8,"column":1},"end":{"line":8,"column":1}},"children":[{"type":"emphasis","position":{"start":{"line":8,"column":1},"end":{"line":8,"column":1}},"children":[{"type":"text","value":"For Python details, click to expand the code","position":{"start":{"line":8,"column":1},"end":{"line":8,"column":1}},"key":"zUf8HeSvcP"}],"key":"Qm8u483tzr"}],"key":"JjCURz872A"}],"key":"aFJEDQJt7I"},{"type":"block","kind":"notebook-code","data":{"tags":["hide_input"]},"children":[{"type":"code","lang":"python","executable":true,"value":"%matplotlib inline\nimport numpy as np\nimport matplotlib.pyplot as plt\nimport xarray as xr\nfrom metpy.plots import SkewT\n#  This code is used just to create the skew-T plot of global, annual mean air temperature\nncep_url = \"http://www.esrl.noaa.gov/psd/thredds/dodsC/Datasets/ncep.reanalysis.derived/\"\ntime_coder = xr.coders.CFDatetimeCoder(use_cftime=True)\nncep_air = xr.open_dataset( ncep_url + \"pressure/air.mon.1981-2010.ltm.nc\", decode_times=time_coder)\n#  Take global, annual average \ncoslat = np.cos(np.deg2rad(ncep_air.lat))\nweight = coslat / coslat.mean(dim='lat')\nTglobal = (ncep_air.air * weight).mean(dim=('lat','lon','time'))\n#  Resuable function to plot the temperature data on a Skew-T chart\ndef make_skewT():\n    fig = plt.figure(figsize=(9, 9))\n    skew = SkewT(fig, rotation=30)\n    skew.plot(Tglobal.level, Tglobal, color='black', linestyle='-', linewidth=2, label='Observations')\n    skew.ax.set_ylim(1050, 10)\n    skew.ax.set_xlim(-90, 45)\n    # Add the relevant special lines\n    skew.plot_dry_adiabats(linewidth=0.5)\n    skew.plot_moist_adiabats(linewidth=0.5)\n    #skew.plot_mixing_lines()\n    skew.ax.legend()\n    skew.ax.set_xlabel('Temperature (degC)', fontsize=14)\n    skew.ax.set_ylabel('Pressure (hPa)', fontsize=14)\n    return skew\n#  and a function to add extra profiles to this chart\ndef add_profile(skew, model, linestyle='-', color=None):\n    line = skew.plot(model.lev, model.Tatm - climlab.constants.tempCtoK,\n             label=model.name, linewidth=2)[0]\n    skew.plot(1000, model.Ts - climlab.constants.tempCtoK, 'o', \n              markersize=8, color=line.get_color())\n    skew.ax.legend()\n\n# Get the water vapor data from CESM output\ncesm_data_path = \"http://thredds.atmos.albany.edu:8080/thredds/dodsC/CESMA/\"\natm_control = xr.open_dataset(cesm_data_path + \"cpl_1850_f19/concatenated/cpl_1850_f19.cam.h0.nc\")\n# Take global, annual average of the specific humidity\nweight_factor = atm_control.gw / atm_control.gw.mean(dim='lat')\nQglobal = (atm_control.Q * weight_factor).mean(dim=('lat','lon','time'))\n#  Create the single-column model domain\nimport climlab\n#  Make a model on same vertical domain as the GCM\nmystate = climlab.column_state(lev=Qglobal.lev, water_depth=2.5)\n#  Create the model itself -- radiation only!\nrad = climlab.radiation.RRTMG(name='Radiation (all gases)',  # give our model a name!\n                              state=mystate,   # give our model an initial condition!\n                              specific_humidity=Qglobal.values,  # tell the model how much water vapor there is\n                              albedo = 0.25,  # this the SURFACE shortwave albedo\n                              timestep = climlab.constants.seconds_per_day,  # set the timestep to one day (measured in seconds)\n                             )\n\n#  remove ozone\nrad_noO3 = climlab.process_like(rad)\nrad_noO3.absorber_vmr['O3'] *= 0.\nrad_noO3.name = 'no O3'\n#  remove water vapor\nrad_noH2O = climlab.process_like(rad)\nrad_noH2O.specific_humidity *= 0.\nrad_noH2O.name = 'no H2O'\n#  remove both\nrad_noO3_noH2O = climlab.process_like(rad_noO3)\nrad_noO3_noH2O.specific_humidity *= 0.\nrad_noO3_noH2O.name = 'no O3, no H2O'\n#  put all models together in a list\nrad_models = [rad, rad_noO3, rad_noH2O, rad_noO3_noH2O]\n\n#  Loop through the models and integrate each one out to equilibrium\nfor model in rad_models:\n    for n in range(100):\n        model.step_forward()\n    while (np.abs(model.ASR-model.OLR)>0.01):\n        model.step_forward()\n        \n# Plot all the results\nskew = make_skewT()\nfor model in rad_models:\n    add_profile(skew, model)\nskew.ax.set_title('Pure radiative equilibrium', fontsize=18);","visibility":"show","key":"BKATijylen"},{"type":"output","id":"5FgFZ0yqBZem4pg2g2lgb","data":[{"output_type":"display_data","metadata":{},"data":{"image/png":{"content_type":"image/png","hash":"3e44dbc7f4a15a00f12a5fe534862f24","path":"/ClimateLaboratoryBook/_preview/169/build/3e44dbc7f4a15a00f12a5fe534862f24.png"},"text/plain":{"content":"<Figure size 900x900 with 1 Axes>","content_type":"text/plain"}}}],"visibility":"show","key":"akE2w7ur4I"}],"visibility":"show","key":"vZBzjSh56P"},{"type":"block","kind":"notebook-content","children":[{"type":"paragraph","position":{"start":{"line":1,"column":1},"end":{"line":1,"column":1}},"children":[{"type":"text","value":"As we have already discussed, none of these profiles really looks anything like the observations in the troposphere. This strongly suggests that ","position":{"start":{"line":1,"column":1},"end":{"line":1,"column":1}},"key":"fsT7PqFhd2"},{"type":"strong","position":{"start":{"line":1,"column":1},"end":{"line":1,"column":1}},"children":[{"type":"text","value":"other physical processes","position":{"start":{"line":1,"column":1},"end":{"line":1,"column":1}},"key":"djVvo8Ri1V"}],"key":"f67XScOinJ"},{"type":"text","value":" (aside from radiation) are important in determining the observed temperature profile.","position":{"start":{"line":1,"column":1},"end":{"line":1,"column":1}},"key":"T0DAGrkwFd"}],"key":"UAnOdiWvRG"},{"type":"paragraph","position":{"start":{"line":3,"column":1},"end":{"line":3,"column":1}},"children":[{"type":"text","value":"Plotting on the skew-T diagram makes it clear that ","position":{"start":{"line":3,"column":1},"end":{"line":3,"column":1}},"key":"UEQUnpLgVB"},{"type":"strong","position":{"start":{"line":3,"column":1},"end":{"line":3,"column":1}},"children":[{"type":"text","value":"all the radiative equilibrium profiles are statically unstable near the surface","position":{"start":{"line":3,"column":1},"end":{"line":3,"column":1}},"key":"kFhJ0kzj7m"}],"key":"D9h1k5kSvH"},{"type":"text","value":".","position":{"start":{"line":3,"column":1},"end":{"line":3,"column":1}},"key":"xXSlYDaFul"}],"key":"qB6IjaskSX"},{"type":"paragraph","position":{"start":{"line":5,"column":1},"end":{"line":5,"column":1}},"children":[{"type":"text","value":"So we’re now going to ","position":{"start":{"line":5,"column":1},"end":{"line":5,"column":1}},"key":"vC5uEZRScX"},{"type":"strong","position":{"start":{"line":5,"column":1},"end":{"line":5,"column":1}},"children":[{"type":"text","value":"add a representation of the effects of convective mixing","position":{"start":{"line":5,"column":1},"end":{"line":5,"column":1}},"key":"QG5ukJvUQC"}],"key":"QboHKWerSu"},{"type":"text","value":" to the single-column model.","position":{"start":{"line":5,"column":1},"end":{"line":5,"column":1}},"key":"lmh4ezLUvA"}],"key":"SUDzHod3ks"}],"key":"yjdYdNho2J"},{"type":"block","kind":"notebook-content","children":[{"type":"thematicBreak","position":{"start":{"line":1,"column":1},"end":{"line":1,"column":1}},"key":"o1W3VtzhBV"},{"type":"heading","depth":2,"position":{"start":{"line":3,"column":1},"end":{"line":3,"column":1}},"children":[{"type":"text","value":"2. Building a radiative-convection model in climlab","position":{"start":{"line":3,"column":1},"end":{"line":3,"column":1}},"key":"V1zE6JVYcz"}],"identifier":"id-2-building-a-radiative-convection-model-in-climlab","label":"2. Building a radiative-convection model in climlab","html_id":"id-2-building-a-radiative-convection-model-in-climlab","implicit":true,"key":"c2LzXRZzRh"},{"type":"thematicBreak","position":{"start":{"line":4,"column":1},"end":{"line":4,"column":1}},"key":"K3vxrgHsZH"}],"key":"dgMv9zyYaf"},{"type":"block","kind":"notebook-content","children":[{"type":"paragraph","position":{"start":{"line":1,"column":1},"end":{"line":1,"column":1}},"children":[{"type":"text","value":"To make a ","position":{"start":{"line":1,"column":1},"end":{"line":1,"column":1}},"key":"ZNRrBAo4Hm"},{"type":"strong","position":{"start":{"line":1,"column":1},"end":{"line":1,"column":1}},"children":[{"type":"text","value":"Radiative-Convective model","position":{"start":{"line":1,"column":1},"end":{"line":1,"column":1}},"key":"ibItxTC7to"}],"key":"iZc3N0OBvR"},{"type":"text","value":", we just take a ","position":{"start":{"line":1,"column":1},"end":{"line":1,"column":1}},"key":"WRTzmH0zzx"},{"type":"strong","position":{"start":{"line":1,"column":1},"end":{"line":1,"column":1}},"children":[{"type":"text","value":"radiation","position":{"start":{"line":1,"column":1},"end":{"line":1,"column":1}},"key":"wIqB36IUho"}],"key":"RXhcxwfpq6"},{"type":"text","value":" model and couple it to a ","position":{"start":{"line":1,"column":1},"end":{"line":1,"column":1}},"key":"A03c1xLXvt"},{"type":"strong","position":{"start":{"line":1,"column":1},"end":{"line":1,"column":1}},"children":[{"type":"text","value":"convection","position":{"start":{"line":1,"column":1},"end":{"line":1,"column":1}},"key":"LUEBSY6LHO"}],"key":"mcQVovFOt9"},{"type":"text","value":" model!","position":{"start":{"line":1,"column":1},"end":{"line":1,"column":1}},"key":"GQeMkXMRg5"}],"key":"RqDqPytPVJ"},{"type":"paragraph","position":{"start":{"line":3,"column":1},"end":{"line":3,"column":1}},"children":[{"type":"text","value":"The “convection” model we’re going to use here is available as","position":{"start":{"line":3,"column":1},"end":{"line":3,"column":1}},"key":"rjeHopQdTT"}],"key":"VSUWTli23T"},{"type":"code","lang":"","value":"climlab.convection.ConvectiveAdjustment","position":{"start":{"line":5,"column":1},"end":{"line":7,"column":1}},"key":"K7QLxDxL5U"},{"type":"paragraph","position":{"start":{"line":9,"column":1},"end":{"line":9,"column":1}},"children":[{"type":"text","value":"It is a simple process that looks for ","position":{"start":{"line":9,"column":1},"end":{"line":9,"column":1}},"key":"oY78MpLExh"},{"type":"strong","position":{"start":{"line":9,"column":1},"end":{"line":9,"column":1}},"children":[{"type":"text","value":"lapse rates exceeding a critical threshold","position":{"start":{"line":9,"column":1},"end":{"line":9,"column":1}},"key":"rqrMsfkyK2"}],"key":"xMykqboaM2"},{"type":"text","value":" and performs an ","position":{"start":{"line":9,"column":1},"end":{"line":9,"column":1}},"key":"la81y1Q68e"},{"type":"strong","position":{"start":{"line":9,"column":1},"end":{"line":9,"column":1}},"children":[{"type":"text","value":"instantaneous adjustment","position":{"start":{"line":9,"column":1},"end":{"line":9,"column":1}},"key":"Xq9yn6ScY4"}],"key":"jAGb0RIcDK"},{"type":"text","value":" that mixes temperatures to the critical lapse rate while conserving energy.","position":{"start":{"line":9,"column":1},"end":{"line":9,"column":1}},"key":"IAYldRrTUx"}],"key":"rFquJ9jGLM"},{"type":"paragraph","position":{"start":{"line":11,"column":1},"end":{"line":11,"column":1}},"children":[{"type":"text","value":"This is a ","position":{"start":{"line":11,"column":1},"end":{"line":11,"column":1}},"key":"B1jZfYv4R1"},{"type":"strong","position":{"start":{"line":11,"column":1},"end":{"line":11,"column":1}},"children":[{"type":"text","value":"parameterization","position":{"start":{"line":11,"column":1},"end":{"line":11,"column":1}},"key":"yEtt34nMCJ"}],"key":"GTo7EHl2f7"},{"type":"text","value":" of the complex, rapid mixing processes that actually occur in an unstable air column!","position":{"start":{"line":11,"column":1},"end":{"line":11,"column":1}},"key":"uld9WIXUKX"}],"key":"zwQjU9SVgy"}],"key":"tjdJQpfLFL"},{"type":"block","kind":"notebook-content","children":[{"type":"paragraph","position":{"start":{"line":1,"column":1},"end":{"line":1,"column":1}},"children":[{"type":"text","value":"Here is some code to put this model together in ","position":{"start":{"line":1,"column":1},"end":{"line":1,"column":1}},"key":"eYIG1SGfKz"},{"type":"inlineCode","value":"climlab","position":{"start":{"line":1,"column":1},"end":{"line":1,"column":1}},"key":"dtraq2jNbX"},{"type":"text","value":":","position":{"start":{"line":1,"column":1},"end":{"line":1,"column":1}},"key":"OuTJfmXGkL"}],"key":"ycx6mpZsRK"}],"key":"MH9vYqPEZj"},{"type":"block","kind":"notebook-code","children":[{"type":"code","lang":"python","executable":true,"value":"#  Make a model on same vertical domain as the GCM\nmystate = climlab.column_state(lev=Qglobal.lev, water_depth=2.5)\n#  Build the radiation model -- just like we already did\nrad = climlab.radiation.RRTMG(name='Radiation (net)',\n                              state=mystate, \n                              specific_humidity=Qglobal.values,\n                              timestep = climlab.constants.seconds_per_day,\n                              albedo = 0.25,  # surface albedo, tuned to give reasonable ASR for reference cloud-free model\n                             )\n#  Now create the convection model\nconv = climlab.convection.ConvectiveAdjustment(name='Convection',\n                                               state=mystate,\n                                               adj_lapse_rate=6.5, # this is the key parameter! We'll discuss below\n                                               timestep=rad.timestep,  # same timestep!\n                                              )\n#  Here is where we build the model by coupling together the two components\nrcm = climlab.couple([rad, conv], name='Radiative-Convective Model')","key":"BYmyBhNyyr"},{"type":"output","id":"DQYfN02DpeCJqXwaNLyot","data":[],"key":"cmSrPDlNzr"}],"key":"opCq6hEG1p"},{"type":"block","kind":"notebook-code","children":[{"type":"code","lang":"python","executable":true,"value":"rcm","key":"NG4CRKayjl"},{"type":"output","id":"Qbqi-5vznH7J0P-ucV17-","data":[{"output_type":"execute_result","execution_count":3,"metadata":{},"data":{"text/plain":{"content":"<climlab.process.time_dependent_process.TimeDependentProcess at 0x17729b770>","content_type":"text/plain"}}}],"key":"WWMpJElBPX"}],"key":"uqcfSvUDUc"},{"type":"block","kind":"notebook-content","children":[{"type":"thematicBreak","position":{"start":{"line":1,"column":1},"end":{"line":1,"column":1}},"key":"tyd8tDEptd"},{"type":"heading","depth":2,"position":{"start":{"line":3,"column":1},"end":{"line":3,"column":1}},"children":[{"type":"text","value":"3. Adjustment toward radiative-convective equilibrium","position":{"start":{"line":3,"column":1},"end":{"line":3,"column":1}},"key":"N1pxAZgKEu"}],"identifier":"id-3-adjustment-toward-radiative-convective-equilibrium","label":"3. Adjustment toward radiative-convective equilibrium","html_id":"id-3-adjustment-toward-radiative-convective-equilibrium","implicit":true,"key":"CxPGU6ygoH"},{"type":"thematicBreak","position":{"start":{"line":4,"column":1},"end":{"line":4,"column":1}},"key":"XLZpcKHV9U"}],"key":"rG7bbk9pLJ"},{"type":"block","kind":"notebook-content","children":[{"type":"heading","depth":3,"position":{"start":{"line":1,"column":1},"end":{"line":1,"column":1}},"children":[{"type":"text","value":"Adjustment from isothermal initial conditions","position":{"start":{"line":1,"column":1},"end":{"line":1,"column":1}},"key":"i8R233VLXS"}],"identifier":"adjustment-from-isothermal-initial-conditions","label":"Adjustment from isothermal initial conditions","html_id":"adjustment-from-isothermal-initial-conditions","implicit":true,"key":"URIAm6Jsth"},{"type":"paragraph","position":{"start":{"line":3,"column":1},"end":{"line":3,"column":1}},"children":[{"type":"text","value":"To get some insight into the interaction between radiation and convection, it’s useful to look at the adjustment process from a non-equilibrium initial condition.","position":{"start":{"line":3,"column":1},"end":{"line":3,"column":1}},"key":"e6UaPBDqtq"}],"key":"fkIRwx4MQr"},{"type":"paragraph","position":{"start":{"line":5,"column":1},"end":{"line":5,"column":1}},"children":[{"type":"strong","position":{"start":{"line":5,"column":1},"end":{"line":5,"column":1}},"children":[{"type":"text","value":"Let’s make an animation!","position":{"start":{"line":5,"column":1},"end":{"line":5,"column":1}},"key":"ic4N6vgkFF"}],"key":"t8JyqMupXd"}],"key":"Os0PGVydoW"},{"type":"paragraph","position":{"start":{"line":7,"column":1},"end":{"line":7,"column":1}},"children":[{"type":"emphasis","position":{"start":{"line":7,"column":1},"end":{"line":7,"column":1}},"children":[{"type":"text","value":"The code below is complicated but it is mostly for generating the animation. Focus on the results, not the code here.","position":{"start":{"line":7,"column":1},"end":{"line":7,"column":1}},"key":"XDslyiQ9fD"}],"key":"HB3tgX7X6d"}],"key":"bX2g9kS7ml"}],"key":"QTc1gnd987"},{"type":"block","kind":"notebook-code","data":{"tags":["hide_input"]},"children":[{"type":"code","lang":"python","executable":true,"value":"#  Some imports needed to make and display animations\nfrom IPython.display import HTML\nfrom matplotlib import animation\n\ndef get_tendencies(model):\n    '''Pack all the subprocess tendencies into xarray.Datasets\n    and convert to units of K / day'''\n    tendencies_atm = xr.Dataset()\n    tendencies_sfc = xr.Dataset()\n    for name, proc, top_proc in climlab.utils.walk.walk_processes(model, topname='Total', topdown=False):\n        tendencies_atm[name] = proc.tendencies['Tatm'].to_xarray()\n        tendencies_sfc[name] = proc.tendencies['Ts'].to_xarray()\n    for tend in [tendencies_atm, tendencies_sfc]:\n        #  convert to K / day\n        tend *= climlab.constants.seconds_per_day\n    return tendencies_atm, tendencies_sfc\n\ndef initial_figure(model):\n    fig = plt.figure(figsize=(14,6))\n    lines = []\n    \n    skew = SkewT(fig, subplot=(1,2,1), rotation=30)\n    #  plot the observations\n    skew.plot(Tglobal.level, Tglobal, color='black', linestyle='-', linewidth=2, label='Observations')    \n    lines.append(skew.plot(model.lev, model.Tatm - climlab.constants.tempCtoK, \n              linestyle='-', linewidth=2, color='C0', label='RC model (all gases)')[0])\n    skew.ax.legend()\n    skew.ax.set_ylim(1050, 10)\n    skew.ax.set_xlim(-60, 75)\n    # Add the relevant special lines\n    skew.plot_dry_adiabats(linewidth=0.5)\n    skew.plot_moist_adiabats(linewidth=0.5)\n    skew.ax.set_xlabel('Temperature (°C)', fontsize=14)\n    skew.ax.set_ylabel('Pressure (hPa)', fontsize=14)\n    lines.append(skew.plot(1000, model.Ts - climlab.constants.tempCtoK, 'o', \n                  markersize=8, color='C0', )[0])\n\n    ax = fig.add_subplot(1,2,2, sharey=skew.ax)\n    ax.set_ylim(1050, 10)\n    ax.set_xlim(-8,8)\n    ax.grid()\n    ax.set_xlabel(r'Temperature tendency (°C day$^{-1}$)', fontsize=14)\n\n    color_cycle=['g','b','r','y','k']\n    #color_cycle=['y', 'r', 'b', 'g', 'k']\n    tendencies_atm, tendencies_sfc = get_tendencies(rcm)\n    for i, name in enumerate(tendencies_atm.data_vars):\n        lines.append(ax.plot(tendencies_atm[name], model.lev, label=name, color=color_cycle[i])[0])\n    for i, name in enumerate(tendencies_sfc.data_vars):\n        lines.append(ax.plot(tendencies_sfc[name], 1000, 'o', markersize=8, color=color_cycle[i])[0])\n    ax.legend(loc='center right');\n    lines.append(skew.ax.text(-100, 50, 'Day {}'.format(int(model.time['days_elapsed'])), fontsize=12)) \n    return fig, lines\n\ndef animate(day, model, lines):\n    lines[0].set_xdata(np.array(model.Tatm)-climlab.constants.tempCtoK)\n    lines[1].set_xdata(np.array(model.Ts)-climlab.constants.tempCtoK)\n    #lines[2].set_xdata(np.array(model.q)*1E3)\n    tendencies_atm, tendencies_sfc = get_tendencies(model)\n    for i, name in enumerate(tendencies_atm.data_vars):\n        lines[2+i].set_xdata(tendencies_atm[name])\n    for i, name in enumerate(tendencies_sfc.data_vars):\n        lines[2+5+i].set_xdata(tendencies_sfc[name])\n    lines[-1].set_text('Day {}'.format(int(model.time['days_elapsed'])))\n    # This is kind of a hack, but without it the initial frame doesn't appear\n    if day != 0:\n        model.step_forward()\n    return lines","visibility":"show","key":"vOklJHCOHY"},{"type":"output","id":"k5sSj45ArdIDRUxgK2Ult","data":[],"visibility":"show","key":"mPeSivho5L"}],"visibility":"show","key":"h9LKW9XgBA"},{"type":"block","kind":"notebook-content","children":[{"type":"paragraph","position":{"start":{"line":1,"column":1},"end":{"line":1,"column":1}},"children":[{"type":"text","value":"We are going to start from an ","position":{"start":{"line":1,"column":1},"end":{"line":1,"column":1}},"key":"bbiGcMWpFG"},{"type":"strong","position":{"start":{"line":1,"column":1},"end":{"line":1,"column":1}},"children":[{"type":"text","value":"isothermal","position":{"start":{"line":1,"column":1},"end":{"line":1,"column":1}},"key":"bu7rREBJ2K"}],"key":"qoONUXxB8l"},{"type":"text","value":" initial state, and let the model drift toward equilibrium.","position":{"start":{"line":1,"column":1},"end":{"line":1,"column":1}},"key":"q52WLx5uZg"}],"key":"pckHCzSDti"}],"key":"go5iAzj7gg"},{"type":"block","kind":"notebook-code","children":[{"type":"code","lang":"python","executable":true,"value":"#  Start from isothermal state\nrcm.state.Tatm[:] = rcm.state.Ts\n#  Call the diagnostics once for initial plotting\nrcm.compute_diagnostics()\n#  Plot initial data\nfig, lines = initial_figure(rcm)","key":"HzFHhA02vZ"},{"type":"output","id":"Dt4kiGEziLQ-67NHqfgL8","data":[{"output_type":"display_data","metadata":{},"data":{"image/png":{"content_type":"image/png","hash":"5a2a1428d4a6f6e7e10b99bdc796505e","path":"/ClimateLaboratoryBook/_preview/169/build/5a2a1428d4a6f6e7e10b99bdc796505e.png"},"text/plain":{"content":"<Figure size 1400x600 with 2 Axes>","content_type":"text/plain"}}}],"key":"md3paDtdav"}],"key":"Xtzc6lKpd0"},{"type":"block","kind":"notebook-content","children":[{"type":"paragraph","position":{"start":{"line":1,"column":1},"end":{"line":1,"column":1}},"children":[{"type":"text","value":"Notice several things here:","position":{"start":{"line":1,"column":1},"end":{"line":1,"column":1}},"key":"c09ABJmg6K"}],"key":"dGzx1dRO20"},{"type":"list","ordered":false,"spread":false,"position":{"start":{"line":3,"column":1},"end":{"line":7,"column":1}},"children":[{"type":"listItem","spread":true,"position":{"start":{"line":3,"column":1},"end":{"line":3,"column":1}},"children":[{"type":"text","value":"The initial profile is isothermal at 15ºC. This is an arbitrary choice we made.","position":{"start":{"line":3,"column":1},"end":{"line":3,"column":1}},"key":"rcXsUxHq6o"}],"key":"wqr9WAmsKh"},{"type":"listItem","spread":true,"position":{"start":{"line":4,"column":1},"end":{"line":4,"column":1}},"children":[{"type":"text","value":"The initial tendency from ","position":{"start":{"line":4,"column":1},"end":{"line":4,"column":1}},"key":"y2EBw83qM1"},{"type":"strong","position":{"start":{"line":4,"column":1},"end":{"line":4,"column":1}},"children":[{"type":"text","value":"convection","position":{"start":{"line":4,"column":1},"end":{"line":4,"column":1}},"key":"gOn6J7Ll2U"}],"key":"rFHdZKSY9D"},{"type":"text","value":" is zero everywhere. Why?","position":{"start":{"line":4,"column":1},"end":{"line":4,"column":1}},"key":"eKPDmVRpfI"}],"key":"cUKKeB57kq"},{"type":"listItem","spread":true,"position":{"start":{"line":5,"column":1},"end":{"line":5,"column":1}},"children":[{"type":"text","value":"Shortwave radiation tends to ","position":{"start":{"line":5,"column":1},"end":{"line":5,"column":1}},"key":"aqnBDT5trN"},{"type":"strong","position":{"start":{"line":5,"column":1},"end":{"line":5,"column":1}},"children":[{"type":"text","value":"warm everywhere","position":{"start":{"line":5,"column":1},"end":{"line":5,"column":1}},"key":"VrkMGQbJDA"}],"key":"IxeEQSPVha"},{"type":"text","value":". Why?","position":{"start":{"line":5,"column":1},"end":{"line":5,"column":1}},"key":"GMDW8sP8R0"}],"key":"Jg8bHMYI4h"},{"type":"listItem","spread":true,"position":{"start":{"line":6,"column":1},"end":{"line":6,"column":1}},"children":[{"type":"text","value":"Longwave radiation tends to ","position":{"start":{"line":6,"column":1},"end":{"line":6,"column":1}},"key":"DpnSO5zHPF"},{"type":"strong","position":{"start":{"line":6,"column":1},"end":{"line":6,"column":1}},"children":[{"type":"text","value":"cool everywhere","position":{"start":{"line":6,"column":1},"end":{"line":6,"column":1}},"key":"nFQHXhZNlF"}],"key":"x2hfzlc4Mh"},{"type":"text","value":". The cooling is very strong especially aloft. Why?","position":{"start":{"line":6,"column":1},"end":{"line":6,"column":1}},"key":"LbmPU9SIdm"}],"key":"T7qnJTL51k"},{"type":"listItem","spread":true,"position":{"start":{"line":7,"column":1},"end":{"line":7,"column":1}},"children":[{"type":"text","value":"The total tendency (black) is warming at the surface and cooling in the atmosphere. What should happen next? What are the implications for convective instability?","position":{"start":{"line":7,"column":1},"end":{"line":7,"column":1}},"key":"iFeNXDdcXJ"}],"key":"UL4m94HQRV"}],"key":"QVtFKE0qGP"}],"key":"sKKfcpk60l"},{"type":"block","kind":"notebook-content","children":[{"type":"paragraph","position":{"start":{"line":1,"column":1},"end":{"line":1,"column":1}},"children":[{"type":"text","value":"Now let’s look at how the model actually adjusts:","position":{"start":{"line":1,"column":1},"end":{"line":1,"column":1}},"key":"HaBJ01HqFu"}],"key":"DK5mjBclao"}],"key":"DgEstpMOhr"},{"type":"block","kind":"notebook-code","children":[{"type":"code","lang":"python","executable":true,"value":"#  This is where we make a loop over many timesteps and create an animation in the notebook\nani = animation.FuncAnimation(fig, animate, 150, fargs=(rcm, lines))\nHTML(ani.to_html5_video())","key":"kCobWRfxmY"},{"type":"output","id":"-ZgSqyLyvTMj8jCbG-lOD","data":[{"output_type":"execute_result","execution_count":6,"metadata":{},"data":{"text/html":{"content_type":"text/html","hash":"679a9500f18ef3d5de24d4b9d885af33","path":"/ClimateLaboratoryBook/_preview/169/build/679a9500f18ef3d5de24d4b9d885af33.html"},"text/plain":{"content":"<IPython.core.display.HTML object>","content_type":"text/plain"}}}],"key":"Uf4fPzoUNm"}],"key":"AABX7VZ3PG"},{"type":"block","kind":"notebook-content","children":[{"type":"paragraph","position":{"start":{"line":1,"column":1},"end":{"line":1,"column":1}},"children":[{"type":"text","value":"Discuss.","position":{"start":{"line":1,"column":1},"end":{"line":1,"column":1}},"key":"LqRseTkkjU"}],"key":"gOWxgmiNpo"}],"key":"fHqcR4ewbL"},{"type":"block","kind":"notebook-content","children":[{"type":"heading","depth":3,"position":{"start":{"line":1,"column":1},"end":{"line":1,"column":1}},"children":[{"type":"text","value":"What if instead we start out from pure Radiative equilibrium?","position":{"start":{"line":1,"column":1},"end":{"line":1,"column":1}},"key":"Zp4QLemJhi"}],"identifier":"what-if-instead-we-start-out-from-pure-radiative-equilibrium","label":"What if instead we start out from pure Radiative equilibrium?","html_id":"what-if-instead-we-start-out-from-pure-radiative-equilibrium","implicit":true,"key":"nz8eSosGrB"},{"type":"paragraph","position":{"start":{"line":3,"column":1},"end":{"line":3,"column":1}},"children":[{"type":"text","value":"This will represent the effect of a sudden “switching on” of convective processes.","position":{"start":{"line":3,"column":1},"end":{"line":3,"column":1}},"key":"zj8h9o6X6F"}],"key":"rnLoHOBi8D"}],"key":"dRv3F6TAci"},{"type":"block","kind":"notebook-code","children":[{"type":"code","lang":"python","executable":true,"value":"#  Here we take JUST THE RADIATION COMPONENT of the full model and run it out to (near) equilibrium\n#  This is just to get the initial condition for our animation\nfor n in range(1000):\n    rcm.subprocess['Radiation (net)'].step_forward()","key":"K1yCekG0EV"},{"type":"output","id":"dAAd6TlRZg71IvGK0fxcL","data":[],"key":"UDZTeUiRXC"}],"key":"WAifEUT6mQ"},{"type":"block","kind":"notebook-code","children":[{"type":"code","lang":"python","executable":true,"value":"#  Call the diagnostics once for initial plotting\nrcm.compute_diagnostics()\n#  Plot initial data\nfig, lines = initial_figure(rcm)","key":"b5jgqvzU9e"},{"type":"output","id":"QfyOIGpWGKkS9rOvXUtZp","data":[{"output_type":"display_data","metadata":{},"data":{"image/png":{"content_type":"image/png","hash":"3b55aae86b658599fe2ec8660928f3df","path":"/ClimateLaboratoryBook/_preview/169/build/3b55aae86b658599fe2ec8660928f3df.png"},"text/plain":{"content":"<Figure size 1400x600 with 2 Axes>","content_type":"text/plain"}}}],"key":"dy7A2AVp5i"}],"key":"yYMVqsAkvG"},{"type":"block","kind":"notebook-code","children":[{"type":"code","lang":"python","executable":true,"value":"#  This is where we make a loop over many timesteps and create an animation in the notebook\nani = animation.FuncAnimation(fig, animate, 100, fargs=(rcm, lines))\nHTML(ani.to_html5_video())","key":"zUmKLxaouq"},{"type":"output","id":"bvsx1aksjNU0kpK55qGm1","data":[{"output_type":"execute_result","execution_count":9,"metadata":{},"data":{"text/html":{"content_type":"text/html","hash":"bf070765b416a2eb82276bbe21864ace","path":"/ClimateLaboratoryBook/_preview/169/build/bf070765b416a2eb82276bbe21864ace.html"},"text/plain":{"content":"<IPython.core.display.HTML object>","content_type":"text/plain"}}}],"key":"xRoHy8rF1a"}],"key":"wUlc7SAkWA"},{"type":"block","kind":"notebook-content","children":[{"type":"paragraph","position":{"start":{"line":1,"column":1},"end":{"line":1,"column":1}},"children":[{"type":"text","value":"This animation is not as exciting because the ","position":{"start":{"line":1,"column":1},"end":{"line":1,"column":1}},"key":"RWBdh6Muwz"},{"type":"strong","position":{"start":{"line":1,"column":1},"end":{"line":1,"column":1}},"children":[{"type":"text","value":"instability is destroyed immediately","position":{"start":{"line":1,"column":1},"end":{"line":1,"column":1}},"key":"yJXLI4YiDe"}],"key":"jnEulLN0aZ"},{"type":"text","value":" in the first timestep!","position":{"start":{"line":1,"column":1},"end":{"line":1,"column":1}},"key":"EYGjhIDMwm"}],"key":"kMDG0i4duB"},{"type":"paragraph","position":{"start":{"line":3,"column":1},"end":{"line":3,"column":1}},"children":[{"type":"text","value":"That is because the ","position":{"start":{"line":3,"column":1},"end":{"line":3,"column":1}},"key":"MC8Lyd3HwA"},{"type":"inlineCode","value":"ConvectiveAdjustment","position":{"start":{"line":3,"column":1},"end":{"line":3,"column":1}},"key":"lAd4sZu5yU"},{"type":"text","value":" process operates instantaneously whenever there is any instability. It is a parameterization taking advantage of the fact that, in nature, ","position":{"start":{"line":3,"column":1},"end":{"line":3,"column":1}},"key":"lTw790AUGB"},{"type":"strong","position":{"start":{"line":3,"column":1},"end":{"line":3,"column":1}},"children":[{"type":"text","value":"convection processes are fast compared to radiative processes","position":{"start":{"line":3,"column":1},"end":{"line":3,"column":1}},"key":"aiaDiZaYl2"}],"key":"KzpNTLxz4P"},{"type":"text","value":".","position":{"start":{"line":3,"column":1},"end":{"line":3,"column":1}},"key":"zJNcwhYHGh"}],"key":"tto45UusBK"},{"type":"paragraph","position":{"start":{"line":5,"column":1},"end":{"line":5,"column":1}},"children":[{"type":"text","value":"But notice that the final state is pretty much the same as in the first animation.","position":{"start":{"line":5,"column":1},"end":{"line":5,"column":1}},"key":"wxRDBImAGr"}],"key":"ogrNflVN3Q"},{"type":"paragraph","position":{"start":{"line":7,"column":1},"end":{"line":7,"column":1}},"children":[{"type":"strong","position":{"start":{"line":7,"column":1},"end":{"line":7,"column":1}},"children":[{"type":"text","value":"The column tends toward the same equilibrium state regardless of where it starts.","position":{"start":{"line":7,"column":1},"end":{"line":7,"column":1}},"key":"a46p50fDbd"}],"key":"tKtp3PGMuI"}],"key":"Y5cTKokczJ"}],"key":"ROlzAzSz9t"},{"type":"block","kind":"notebook-content","children":[{"type":"thematicBreak","position":{"start":{"line":1,"column":1},"end":{"line":1,"column":1}},"key":"WbBti4dOzP"},{"type":"heading","depth":2,"position":{"start":{"line":3,"column":1},"end":{"line":3,"column":1}},"children":[{"type":"text","value":"4. Compare Radiative- and Radiative-Convective Equilibrium","position":{"start":{"line":3,"column":1},"end":{"line":3,"column":1}},"key":"M3PuAEu2Mo"}],"identifier":"id-4-compare-radiative-and-radiative-convective-equilibrium","label":"4. Compare Radiative- and Radiative-Convective Equilibrium","html_id":"id-4-compare-radiative-and-radiative-convective-equilibrium","implicit":true,"key":"zm3Axfbpjd"},{"type":"thematicBreak","position":{"start":{"line":4,"column":1},"end":{"line":4,"column":1}},"key":"dTCXNyrqBs"}],"key":"qNS1t4xtDN"},{"type":"block","kind":"notebook-content","children":[{"type":"paragraph","position":{"start":{"line":1,"column":1},"end":{"line":1,"column":1}},"children":[{"type":"text","value":"Let’s repeat our experiment with removing certain absorbing gases from the model, but use the Radiative-Convective model.","position":{"start":{"line":1,"column":1},"end":{"line":1,"column":1}},"key":"xCDlyiZLYb"}],"key":"owJRuoqmFu"}],"key":"EtFVcPHCfY"},{"type":"block","kind":"notebook-code","data":{"tags":["hide_input"]},"children":[{"type":"code","lang":"python","executable":true,"value":"#  Make a model on same vertical domain as the GCM\nmystate = climlab.column_state(lev=Qglobal.lev, water_depth=2.5)\n\nrad = climlab.radiation.RRTMG(name='all gases',\n                              state=mystate, \n                              specific_humidity=Qglobal.values,\n                              timestep = climlab.constants.seconds_per_day,\n                              albedo = 0.25,  # tuned to give reasonable ASR for reference cloud-free model\n                             )\n#  remove ozone\nrad_noO3 = climlab.process_like(rad)\nrad_noO3.absorber_vmr['O3'] *= 0.\nrad_noO3.name = 'no O3'\n#  remove water vapor\nrad_noH2O = climlab.process_like(rad)\nrad_noH2O.specific_humidity *= 0.\nrad_noH2O.name = 'no H2O'\n#  remove both\nrad_noO3_noH2O = climlab.process_like(rad_noO3)\nrad_noO3_noH2O.specific_humidity *= 0.\nrad_noO3_noH2O.name = 'no O3, no H2O'\n#  put all models together in a list\nrad_models = [rad, rad_noO3, rad_noH2O, rad_noO3_noH2O]\n\nrc_models = []\nfor r in rad_models:\n    newrad = climlab.process_like(r)\n    conv = climlab.convection.ConvectiveAdjustment(name='Convective Adjustment',\n                                               state=newrad.state,\n                                               adj_lapse_rate=6.5,  # the key parameter in the convection model!\n                                               timestep=newrad.timestep,)\n    rc = newrad + conv\n    rc.name = newrad.name\n    rc_models.append(rc)\n\nfor model in rad_models:\n    for n in range(100):\n        model.step_forward()\n    while (np.abs(model.ASR-model.OLR)>0.01):\n        model.step_forward()    \n    \nfor model in rc_models:\n    for n in range(100):\n        model.step_forward()\n    while (np.abs(model.ASR-model.OLR)>0.01):\n        model.step_forward()","visibility":"show","key":"tNmuVnBc7F"},{"type":"output","id":"JKU96skoq9_SOckOXhbvc","data":[],"visibility":"show","key":"GMLn56nfbD"}],"visibility":"show","key":"MQmA9cmnkK"},{"type":"block","kind":"notebook-code","data":{"tags":["hide_input"]},"children":[{"type":"code","lang":"python","executable":true,"value":"skew = make_skewT()\nfor model in rad_models:\n    add_profile(skew, model)\nskew.ax.set_title('Pure radiative equilibrium', fontsize=18);","visibility":"show","key":"f7RMUlykk0"},{"type":"output","id":"KA7FZqKOeSmnI40wcBOm3","data":[{"output_type":"display_data","metadata":{},"data":{"image/png":{"content_type":"image/png","hash":"2eeee5a8927c4a96f3b0eb0dd9c7d088","path":"/ClimateLaboratoryBook/_preview/169/build/2eeee5a8927c4a96f3b0eb0dd9c7d088.png"},"text/plain":{"content":"<Figure size 900x900 with 1 Axes>","content_type":"text/plain"}}}],"visibility":"show","key":"xyTWpaMHIK"}],"visibility":"show","key":"avUznHB9So"},{"type":"block","kind":"notebook-code","data":{"tags":["hide_input"]},"children":[{"type":"code","lang":"python","executable":true,"value":"skew2 = make_skewT()\nfor model in rc_models:\n    add_profile(skew2, model)\nskew2.ax.set_title('Radiative-convective equilibrium', fontsize=18);","visibility":"show","key":"lnnMHWv0L0"},{"type":"output","id":"ez_bbaJL66yh9ZAXCmgt3","data":[{"output_type":"display_data","metadata":{},"data":{"image/png":{"content_type":"image/png","hash":"8a1c05a0bb64e7fd502a5f74fddff88e","path":"/ClimateLaboratoryBook/_preview/169/build/8a1c05a0bb64e7fd502a5f74fddff88e.png"},"text/plain":{"content":"<Figure size 900x900 with 1 Axes>","content_type":"text/plain"}}}],"visibility":"show","key":"MyZxsYM9dd"}],"visibility":"show","key":"LZdeFBLVWe"},{"type":"block","kind":"notebook-content","children":[{"type":"paragraph","position":{"start":{"line":1,"column":1},"end":{"line":1,"column":1}},"children":[{"type":"text","value":"Lots to discuss here.","position":{"start":{"line":1,"column":1},"end":{"line":1,"column":1}},"key":"IxIfZHrNt9"}],"key":"Vzh2PhG3By"},{"type":"paragraph","position":{"start":{"line":3,"column":1},"end":{"line":3,"column":1}},"children":[{"type":"text","value":"The overall message is that equilibrium temperature profile results from a competition between radiation and convection. Essentially:","position":{"start":{"line":3,"column":1},"end":{"line":3,"column":1}},"key":"wSt8UxjqmV"}],"key":"AAeP1rV42J"},{"type":"list","ordered":false,"spread":false,"position":{"start":{"line":5,"column":1},"end":{"line":11,"column":1}},"children":[{"type":"listItem","spread":true,"position":{"start":{"line":5,"column":1},"end":{"line":7,"column":1}},"children":[{"type":"text","value":"Radiation is always trying to push temperatures toward radiative equilibrium, which means","position":{"start":{"line":5,"column":1},"end":{"line":5,"column":1}},"key":"Q9vE09nqkr"},{"type":"list","ordered":false,"spread":false,"position":{"start":{"line":6,"column":1},"end":{"line":7,"column":1}},"children":[{"type":"listItem","spread":true,"position":{"start":{"line":6,"column":1},"end":{"line":6,"column":1}},"children":[{"type":"text","value":"warm surface","position":{"start":{"line":6,"column":1},"end":{"line":6,"column":1}},"key":"neskeY51JE"}],"key":"b4KmQFissU"},{"type":"listItem","spread":true,"position":{"start":{"line":7,"column":1},"end":{"line":7,"column":1}},"children":[{"type":"text","value":"cold troposphere","position":{"start":{"line":7,"column":1},"end":{"line":7,"column":1}},"key":"clYyxhYARO"}],"key":"E3w2Tp7p3o"}],"key":"Fj71Qqnmy3"}],"key":"iPFqkS3Q2e"},{"type":"listItem","spread":true,"position":{"start":{"line":8,"column":1},"end":{"line":8,"column":1}},"children":[{"type":"text","value":"Convection cools the surface and warms the troposphere","position":{"start":{"line":8,"column":1},"end":{"line":8,"column":1}},"key":"atXlhRAszY"}],"key":"s6upAMNegC"},{"type":"listItem","spread":true,"position":{"start":{"line":9,"column":1},"end":{"line":9,"column":1}},"children":[{"type":"text","value":"The troposphere can be defined here as the layer over which convection is active.","position":{"start":{"line":9,"column":1},"end":{"line":9,"column":1}},"key":"uEN0Caq5FY"}],"key":"U0sfKHTrs2"},{"type":"listItem","spread":true,"position":{"start":{"line":10,"column":1},"end":{"line":10,"column":1}},"children":[{"type":"text","value":"This is true whether or not we have the radiative effects of water vapor.","position":{"start":{"line":10,"column":1},"end":{"line":10,"column":1}},"key":"eRsNbKBpRr"}],"key":"TCeWNgpkaf"},{"type":"listItem","spread":true,"position":{"start":{"line":11,"column":1},"end":{"line":11,"column":1}},"children":[{"type":"text","value":"When we remove the water vapor (and its warming greenhouse effect), the surface temperature becomes much colder and the troposphere is much shallower -- but it is still there.","position":{"start":{"line":11,"column":1},"end":{"line":11,"column":1}},"key":"sZke3UGyJa"}],"key":"p5mSx1GS8K"}],"key":"ndntSAwF0X"}],"key":"vStrDITa2I"},{"type":"block","kind":"notebook-content","children":[{"type":"thematicBreak","position":{"start":{"line":1,"column":1},"end":{"line":1,"column":1}},"key":"s3F52NJjjo"},{"type":"heading","depth":2,"position":{"start":{"line":3,"column":1},"end":{"line":3,"column":1}},"children":[{"type":"text","value":"5. The role of the critical lapse rate","position":{"start":{"line":3,"column":1},"end":{"line":3,"column":1}},"key":"LtJ2hv1Yi1"}],"identifier":"id-5-the-role-of-the-critical-lapse-rate","label":"5. The role of the critical lapse rate","html_id":"id-5-the-role-of-the-critical-lapse-rate","implicit":true,"key":"uabDyH3Rx9"},{"type":"thematicBreak","position":{"start":{"line":4,"column":1},"end":{"line":4,"column":1}},"key":"QFjqOgG70w"}],"key":"BNnPJmwV81"},{"type":"block","kind":"notebook-content","children":[{"type":"heading","depth":3,"position":{"start":{"line":1,"column":1},"end":{"line":1,"column":1}},"children":[{"type":"text","value":"What have we done above","position":{"start":{"line":1,"column":1},"end":{"line":1,"column":1}},"key":"JgFOkGrd7T"}],"identifier":"what-have-we-done-above","label":"What have we done above","html_id":"what-have-we-done-above","implicit":true,"key":"nYHoD7WrUs"},{"type":"paragraph","position":{"start":{"line":3,"column":1},"end":{"line":3,"column":1}},"children":[{"type":"text","value":"These calculations all used a critical lapse rate of 6.5 K / km, which is a reasonable approximation to observations.","position":{"start":{"line":3,"column":1},"end":{"line":3,"column":1}},"key":"ivPogm9O5G"}],"key":"CyAIC5AjkF"},{"type":"paragraph","position":{"start":{"line":5,"column":1},"end":{"line":5,"column":1}},"children":[{"type":"text","value":"We set this with the input argument","position":{"start":{"line":5,"column":1},"end":{"line":5,"column":1}},"key":"rhzrYZz8QU"}],"key":"IlaYET8Xpt"},{"type":"code","lang":"","value":"adj_lapse_rate","position":{"start":{"line":6,"column":1},"end":{"line":8,"column":1}},"key":"IUnJiyBKiE"},{"type":"paragraph","position":{"start":{"line":9,"column":1},"end":{"line":9,"column":1}},"children":[{"type":"text","value":"to the ","position":{"start":{"line":9,"column":1},"end":{"line":9,"column":1}},"key":"bsYWNxUInS"},{"type":"inlineCode","value":"ConvectiveAdjustment","position":{"start":{"line":9,"column":1},"end":{"line":9,"column":1}},"key":"X1W6xCigjl"},{"type":"text","value":" process.","position":{"start":{"line":9,"column":1},"end":{"line":9,"column":1}},"key":"RsNe5KvjEr"}],"key":"vVNMQMkawa"},{"type":"paragraph","position":{"start":{"line":11,"column":1},"end":{"line":11,"column":1}},"children":[{"type":"text","value":"The idea is that we are trying to represent the statistical effects of many episodes of moist convection.","position":{"start":{"line":11,"column":1},"end":{"line":11,"column":1}},"key":"ZFsdXRVAgH"}],"key":"Um0TjzuhUd"},{"type":"paragraph","position":{"start":{"line":13,"column":1},"end":{"line":13,"column":1}},"children":[{"type":"text","value":"An air column that is perfectly neutral to moist instability would follow the blue ","position":{"start":{"line":13,"column":1},"end":{"line":13,"column":1}},"key":"iZKztVdJbO"},{"type":"strong","position":{"start":{"line":13,"column":1},"end":{"line":13,"column":1}},"children":[{"type":"text","value":"moist adiabats","position":{"start":{"line":13,"column":1},"end":{"line":13,"column":1}},"key":"RSll7dYYbB"}],"key":"SI8P0nXuQF"},{"type":"text","value":" on the skew-T diagrams.","position":{"start":{"line":13,"column":1},"end":{"line":13,"column":1}},"key":"ZIhueMV1xB"}],"key":"nTFzdhMMD8"},{"type":"paragraph","position":{"start":{"line":15,"column":1},"end":{"line":15,"column":1}},"children":[{"type":"text","value":"We can force the model to behave this way by setting","position":{"start":{"line":15,"column":1},"end":{"line":15,"column":1}},"key":"jAmEjNKO8O"}],"key":"rXor0uqB1L"},{"type":"code","lang":"","value":"adj_lapse_rate = 'pseudoadiabat'","position":{"start":{"line":16,"column":1},"end":{"line":18,"column":1}},"key":"tYsw69nxXN"},{"type":"paragraph","position":{"start":{"line":20,"column":1},"end":{"line":20,"column":1}},"children":[{"type":"text","value":"However the real atmosphere, on average, does not exactly follow these adiabats for several reasons:","position":{"start":{"line":20,"column":1},"end":{"line":20,"column":1}},"key":"KWh35KgSEY"}],"key":"ihzSjllvfa"},{"type":"list","ordered":false,"spread":false,"position":{"start":{"line":22,"column":1},"end":{"line":25,"column":1}},"children":[{"type":"listItem","spread":true,"position":{"start":{"line":22,"column":1},"end":{"line":22,"column":1}},"children":[{"type":"text","value":"the slope of the moist adiabat depends strongly on temperature (as we can see on these diagrams)","position":{"start":{"line":22,"column":1},"end":{"line":22,"column":1}},"key":"S4QV5oFO8P"}],"key":"Y6sJk8ewPd"},{"type":"listItem","spread":true,"position":{"start":{"line":23,"column":1},"end":{"line":23,"column":1}},"children":[{"type":"text","value":"We are looking at temperatures averaged over the whole planet, including regions that are warm and moist, warm and dry, and cold.","position":{"start":{"line":23,"column":1},"end":{"line":23,"column":1}},"key":"Nn4fSwZKnJ"}],"key":"iKVFisuxZL"},{"type":"listItem","spread":true,"position":{"start":{"line":24,"column":1},"end":{"line":25,"column":1}},"children":[{"type":"text","value":"Heat fluxes by mid-latitude eddies play an important role in ","position":{"start":{"line":24,"column":1},"end":{"line":24,"column":1}},"key":"POMYVnxiTJ"},{"type":"strong","position":{"start":{"line":24,"column":1},"end":{"line":24,"column":1}},"children":[{"type":"text","value":"stabilizing","position":{"start":{"line":24,"column":1},"end":{"line":24,"column":1}},"key":"Da7MbHoyNP"}],"key":"Zekpry5fyr"},{"type":"text","value":" the extra-tropical atmosphere.","position":{"start":{"line":24,"column":1},"end":{"line":24,"column":1}},"key":"KM57lB6vQ8"}],"key":"rgmJA0WStL"}],"key":"LwbSPlrGYc"},{"type":"paragraph","position":{"start":{"line":26,"column":1},"end":{"line":26,"column":1}},"children":[{"type":"text","value":"So here we sweep all this complexity under the rug and just choose a single critical lapse rate for our convective adjustment model.","position":{"start":{"line":26,"column":1},"end":{"line":26,"column":1}},"key":"cSBDwp3ufP"}],"key":"aYgWw4si2G"},{"type":"paragraph","position":{"start":{"line":28,"column":1},"end":{"line":28,"column":1}},"children":[{"type":"text","value":"But this is a ","position":{"start":{"line":28,"column":1},"end":{"line":28,"column":1}},"key":"MWQtkg5o1F"},{"type":"strong","position":{"start":{"line":28,"column":1},"end":{"line":28,"column":1}},"children":[{"type":"text","value":"parameter","position":{"start":{"line":28,"column":1},"end":{"line":28,"column":1}},"key":"PffZvVdUsY"}],"key":"F0HhugyWKM"},{"type":"text","value":" that is uncertain and could be interesting to explore.","position":{"start":{"line":28,"column":1},"end":{"line":28,"column":1}},"key":"tKyTtaiK62"}],"key":"QjEGDgokT2"}],"key":"z4pHRkSEfZ"},{"type":"block","kind":"notebook-content","children":[{"type":"heading","depth":3,"position":{"start":{"line":1,"column":1},"end":{"line":1,"column":1}},"children":[{"type":"text","value":"Python exercise: change the critical lapse rate","position":{"start":{"line":1,"column":1},"end":{"line":1,"column":1}},"key":"ZkwmT8kxpl"}],"identifier":"python-exercise-change-the-critical-lapse-rate","label":"Python exercise: change the critical lapse rate","html_id":"python-exercise-change-the-critical-lapse-rate","implicit":true,"key":"A5wEBoEZW7"},{"type":"paragraph","position":{"start":{"line":3,"column":1},"end":{"line":3,"column":1}},"children":[{"type":"text","value":"Repeat the whole series of calculations for the different combinations of absorbing gases above, but with different critical lapse rates:","position":{"start":{"line":3,"column":1},"end":{"line":3,"column":1}},"key":"kNCoehSlCJ"}],"key":"CKuqBGQssh"},{"type":"list","ordered":false,"spread":false,"position":{"start":{"line":5,"column":1},"end":{"line":6,"column":1}},"children":[{"type":"listItem","spread":true,"position":{"start":{"line":5,"column":1},"end":{"line":5,"column":1}},"children":[{"type":"inlineCode","value":"adj_lapse_rate = 9.8","position":{"start":{"line":5,"column":1},"end":{"line":5,"column":1}},"key":"mQ1P4LjhLo"},{"type":"text","value":" (in K/km, the dry adiabatic lapse rate, suitable for an atmosphere where condensation does not impact the buoyancy of air parcels)","position":{"start":{"line":5,"column":1},"end":{"line":5,"column":1}},"key":"Reuocw6R0W"}],"key":"eWpxCFck9d"},{"type":"listItem","spread":true,"position":{"start":{"line":6,"column":1},"end":{"line":6,"column":1}},"children":[{"type":"inlineCode","value":"adj_lapse_rate = 'pseudoadiabat'","position":{"start":{"line":6,"column":1},"end":{"line":6,"column":1}},"key":"OFphyOh4i5"},{"type":"text","value":" (more suitable for the tropical atmosphere)","position":{"start":{"line":6,"column":1},"end":{"line":6,"column":1}},"key":"WXYRro1Yg4"}],"key":"coHTSwRoMg"}],"key":"Squ6BDI5iL"}],"key":"oKAnMRbRwp"},{"type":"block","kind":"notebook-code","children":[{"type":"code","lang":"python","executable":true,"value":"","key":"sOWDv4yUMV"},{"type":"output","id":"t7_FrDJzgfkkpxPD_eQCM","data":[],"key":"xJrRxDRE6x"}],"key":"vbtz1ijEBv"},{"type":"block","kind":"notebook-content","children":[{"type":"thematicBreak","position":{"start":{"line":1,"column":1},"end":{"line":1,"column":1}},"key":"pltU1Ihhkw"},{"type":"heading","depth":2,"position":{"start":{"line":3,"column":1},"end":{"line":3,"column":1}},"children":[{"type":"text","value":"6. Summary of radiative-convection equilibrium results","position":{"start":{"line":3,"column":1},"end":{"line":3,"column":1}},"key":"nd42EGf2vQ"}],"identifier":"id-6-summary-of-radiative-convection-equilibrium-results","label":"6. Summary of radiative-convection equilibrium results","html_id":"id-6-summary-of-radiative-convection-equilibrium-results","implicit":true,"key":"y6AunokNym"},{"type":"thematicBreak","position":{"start":{"line":4,"column":1},"end":{"line":4,"column":1}},"key":"xAa27Z0rJ1"},{"type":"list","ordered":false,"spread":false,"position":{"start":{"line":6,"column":1},"end":{"line":9,"column":1}},"children":[{"type":"listItem","spread":true,"position":{"start":{"line":6,"column":1},"end":{"line":6,"column":1}},"children":[{"type":"text","value":"We noted that pure radiative equilibrium is ","position":{"start":{"line":6,"column":1},"end":{"line":6,"column":1}},"key":"DyiZUSgZxR"},{"type":"strong","position":{"start":{"line":6,"column":1},"end":{"line":6,"column":1}},"children":[{"type":"text","value":"not","position":{"start":{"line":6,"column":1},"end":{"line":6,"column":1}},"key":"ENwfNkOAcG"}],"key":"ueuxSyiQ1K"},{"type":"text","value":" a good model for the observed temperature profile.","position":{"start":{"line":6,"column":1},"end":{"line":6,"column":1}},"key":"PKUYTiUPAe"}],"key":"Xs0XxEvBVo"},{"type":"listItem","spread":true,"position":{"start":{"line":7,"column":1},"end":{"line":7,"column":1}},"children":[{"type":"text","value":"An air column in radiative equilibrium has a ","position":{"start":{"line":7,"column":1},"end":{"line":7,"column":1}},"key":"vP9S1dkVfU"},{"type":"strong","position":{"start":{"line":7,"column":1},"end":{"line":7,"column":1}},"children":[{"type":"text","value":"warm surface","position":{"start":{"line":7,"column":1},"end":{"line":7,"column":1}},"key":"HBkdUqg4dB"}],"key":"HPhyUSxocz"},{"type":"text","value":" and ","position":{"start":{"line":7,"column":1},"end":{"line":7,"column":1}},"key":"IdJkPvnCO8"},{"type":"strong","position":{"start":{"line":7,"column":1},"end":{"line":7,"column":1}},"children":[{"type":"text","value":"cold troposphere","position":{"start":{"line":7,"column":1},"end":{"line":7,"column":1}},"key":"MRVzvgg2XJ"}],"key":"cIoD8haZQu"},{"type":"text","value":".","position":{"start":{"line":7,"column":1},"end":{"line":7,"column":1}},"key":"sfyw4aJoKe"}],"key":"arbnbTwrNx"},{"type":"listItem","spread":true,"position":{"start":{"line":8,"column":1},"end":{"line":9,"column":1}},"children":[{"type":"text","value":"In reality this would tend to become ","position":{"start":{"line":8,"column":1},"end":{"line":8,"column":1}},"key":"CaswvSQUnk"},{"type":"strong","position":{"start":{"line":8,"column":1},"end":{"line":8,"column":1}},"children":[{"type":"text","value":"unstable","position":{"start":{"line":8,"column":1},"end":{"line":8,"column":1}},"key":"tnuhrYV02B"}],"key":"lCYoMgMZMh"},{"type":"text","value":" and cause vertical mixing.","position":{"start":{"line":8,"column":1},"end":{"line":8,"column":1}},"key":"OyQRffqw3y"}],"key":"wajyNmilmD"}],"key":"yAurxoGFjE"},{"type":"paragraph","position":{"start":{"line":10,"column":1},"end":{"line":10,"column":1}},"children":[{"type":"text","value":"To account for this shortcoming of the radiation model, we coupled our single-column radiation model (using the ","position":{"start":{"line":10,"column":1},"end":{"line":10,"column":1}},"key":"XvUHMvDHXQ"},{"type":"inlineCode","value":"RRTMG","position":{"start":{"line":10,"column":1},"end":{"line":10,"column":1}},"key":"rBQVgh0FBO"},{"type":"text","value":" radiation model) to a simple ","position":{"start":{"line":10,"column":1},"end":{"line":10,"column":1}},"key":"phA4flnklS"},{"type":"strong","position":{"start":{"line":10,"column":1},"end":{"line":10,"column":1}},"children":[{"type":"text","value":"convection","position":{"start":{"line":10,"column":1},"end":{"line":10,"column":1}},"key":"MFC779513g"}],"key":"ZqryWzWHCR"},{"type":"text","value":" model.","position":{"start":{"line":10,"column":1},"end":{"line":10,"column":1}},"key":"hcmPG6Mrc5"}],"key":"GA8lWI5hnp"},{"type":"list","ordered":false,"spread":false,"position":{"start":{"line":12,"column":1},"end":{"line":17,"column":1}},"children":[{"type":"listItem","spread":true,"position":{"start":{"line":12,"column":1},"end":{"line":12,"column":1}},"children":[{"type":"text","value":"The ","position":{"start":{"line":12,"column":1},"end":{"line":12,"column":1}},"key":"RYIomV0sQt"},{"type":"inlineCode","value":"ConvectiveAdjustment","position":{"start":{"line":12,"column":1},"end":{"line":12,"column":1}},"key":"txy1yMkyR8"},{"type":"text","value":" model instantly mixes out any profiles where the ","position":{"start":{"line":12,"column":1},"end":{"line":12,"column":1}},"key":"VlF0RjeZ0I"},{"type":"strong","position":{"start":{"line":12,"column":1},"end":{"line":12,"column":1}},"children":[{"type":"text","value":"lapse rate","position":{"start":{"line":12,"column":1},"end":{"line":12,"column":1}},"key":"TiIU4LwzYY"}],"key":"M95w6SYDqX"},{"type":"text","value":" exceeds some critical threshold value.","position":{"start":{"line":12,"column":1},"end":{"line":12,"column":1}},"key":"PXcS6Nd1zg"}],"key":"pTmoK9XIGf"},{"type":"listItem","spread":true,"position":{"start":{"line":13,"column":1},"end":{"line":13,"column":1}},"children":[{"type":"text","value":"This critical lapse rate is the tunable parameter in our combined ","position":{"start":{"line":13,"column":1},"end":{"line":13,"column":1}},"key":"cIB6zfoPc5"},{"type":"strong","position":{"start":{"line":13,"column":1},"end":{"line":13,"column":1}},"children":[{"type":"text","value":"Radiative-Convective Model","position":{"start":{"line":13,"column":1},"end":{"line":13,"column":1}},"key":"TOqwtd10pm"}],"key":"COHcszXZcU"},{"type":"text","value":" or ","key":"E5RTV2jBiq"},{"type":"abbreviation","title":"Radiative-Convective Model","children":[{"type":"text","value":"RCM","key":"sJgY7qGeSs"}],"key":"ShDntywITa"},{"type":"text","value":".","key":"h6h55YEE3a"}],"key":"nKJVxe46EV"},{"type":"listItem","spread":true,"position":{"start":{"line":14,"column":1},"end":{"line":14,"column":1}},"children":[{"type":"text","value":"Using a value of 6.5 K / km and realistic gas profiles gives a reasonable (not perfect) fit to the observed air temperatures.","position":{"start":{"line":14,"column":1},"end":{"line":14,"column":1}},"key":"nfXH4gv6VG"}],"key":"GaQ7IL23Uo"},{"type":"listItem","spread":true,"position":{"start":{"line":15,"column":1},"end":{"line":15,"column":1}},"children":[{"type":"text","value":"The ","position":{"start":{"line":15,"column":1},"end":{"line":15,"column":1}},"key":"QYXMNpujNz"},{"type":"strong","position":{"start":{"line":15,"column":1},"end":{"line":15,"column":1}},"children":[{"type":"abbreviation","title":"Radiative-Convective Model","children":[{"type":"text","value":"RCM","key":"Us7i52deux"}],"key":"NtifPqwKOU"},{"type":"text","value":" represents the “tug-of-war”","key":"cqdsxaye7S"}],"key":"DqWHZ99w8M"},{"type":"text","value":" between ","position":{"start":{"line":15,"column":1},"end":{"line":15,"column":1}},"key":"HNBl7slAOo"},{"type":"strong","position":{"start":{"line":15,"column":1},"end":{"line":15,"column":1}},"children":[{"type":"text","value":"radiation","position":{"start":{"line":15,"column":1},"end":{"line":15,"column":1}},"key":"kdZxX6evmD"}],"key":"Dtpx2muMA5"},{"type":"text","value":" (trying to warm the surface and cool the troposphere) and ","position":{"start":{"line":15,"column":1},"end":{"line":15,"column":1}},"key":"OxIzx74B3M"},{"type":"strong","position":{"start":{"line":15,"column":1},"end":{"line":15,"column":1}},"children":[{"type":"text","value":"convection","position":{"start":{"line":15,"column":1},"end":{"line":15,"column":1}},"key":"LCqGqtUIxG"}],"key":"TfE4taUOmc"},{"type":"text","value":" (cool the surface and warm the troposphere).","position":{"start":{"line":15,"column":1},"end":{"line":15,"column":1}},"key":"axmntAIvPd"}],"key":"fsgLGAjY0A"},{"type":"listItem","spread":true,"position":{"start":{"line":16,"column":1},"end":{"line":17,"column":1}},"children":[{"type":"text","value":"The convectively mixed layer extends up to near the top of the troposphere.","position":{"start":{"line":16,"column":1},"end":{"line":16,"column":1}},"key":"Dsvnd98hvi"}],"key":"RQTYqBud0a"}],"key":"XS2fSxEJhn"},{"type":"paragraph","position":{"start":{"line":18,"column":1},"end":{"line":18,"column":1}},"children":[{"type":"text","value":"Our experiments with removing certain absorbing gases show something interesting: the height of the tropopause (boundary bewteen troposphere and stratosphere) changes when we remove absorbers. Warmer columns also appear to have higher tropopause.","position":{"start":{"line":18,"column":1},"end":{"line":18,"column":1}},"key":"assqIP7t1J"}],"key":"oOUO1FzWwV"},{"type":"paragraph","position":{"start":{"line":20,"column":1},"end":{"line":20,"column":1}},"children":[{"type":"text","value":"Now that we know how to build and use this ","key":"OVDhxlFHfK"},{"type":"abbreviation","title":"Radiative-Convective Model","children":[{"type":"text","value":"RCM","key":"KeXr5JFl2o"}],"key":"HL01Ku4TTJ"},{"type":"text","value":", we’ll be able to use to study some climate change processes in more detail.","key":"XeU4i7jLS3"}],"key":"jj0rkNJ6Jx"}],"key":"DqOGsvuyZ9"},{"type":"block","kind":"notebook-content","data":{"slideshow":{"slide_type":"skip"}},"children":[{"type":"thematicBreak","position":{"start":{"line":1,"column":1},"end":{"line":1,"column":1}},"key":"nZ4Movysr5"},{"type":"heading","depth":2,"position":{"start":{"line":3,"column":1},"end":{"line":3,"column":1}},"children":[{"type":"text","value":"Credits","position":{"start":{"line":3,"column":1},"end":{"line":3,"column":1}},"key":"ev4atn0G9P"}],"identifier":"credits","label":"Credits","html_id":"credits","implicit":true,"key":"bfCR51GenZ"},{"type":"paragraph","position":{"start":{"line":5,"column":1},"end":{"line":5,"column":1}},"children":[{"type":"text","value":"This notebook is part of ","position":{"start":{"line":5,"column":1},"end":{"line":5,"column":1}},"key":"f7nScPJlQI"},{"type":"link","url":"https://brian-rose.github.io/ClimateLaboratoryBook","position":{"start":{"line":5,"column":1},"end":{"line":5,"column":1}},"children":[{"type":"text","value":"The Climate Laboratory","position":{"start":{"line":5,"column":1},"end":{"line":5,"column":1}},"key":"H2Sg4fB4pN"}],"urlSource":"https://brian-rose.github.io/ClimateLaboratoryBook","key":"oCemHrE5fl"},{"type":"text","value":", an open-source textbook developed and maintained by ","position":{"start":{"line":5,"column":1},"end":{"line":5,"column":1}},"key":"WNseJbiedC"},{"type":"link","url":"http://www.atmos.albany.edu/facstaff/brose/index.html","position":{"start":{"line":5,"column":1},"end":{"line":5,"column":1}},"children":[{"type":"text","value":"Brian E. J. Rose","position":{"start":{"line":5,"column":1},"end":{"line":5,"column":1}},"key":"lCbIUmBBrE"}],"urlSource":"http://www.atmos.albany.edu/facstaff/brose/index.html","key":"uQQ2ZcjzcM"},{"type":"text","value":", University at Albany.","position":{"start":{"line":5,"column":1},"end":{"line":5,"column":1}},"key":"GBLPxsDDEh"}],"key":"iZyALVyRwA"},{"type":"paragraph","position":{"start":{"line":7,"column":1},"end":{"line":8,"column":1}},"children":[{"type":"text","value":"It is licensed for free and open consumption under the\n","position":{"start":{"line":7,"column":1},"end":{"line":7,"column":1}},"key":"PSWyhLDJcQ"},{"type":"link","url":"https://creativecommons.org/licenses/by/4.0/","position":{"start":{"line":7,"column":1},"end":{"line":7,"column":1}},"children":[{"type":"text","value":"Creative Commons Attribution 4.0 International (CC BY 4.0)","position":{"start":{"line":7,"column":1},"end":{"line":7,"column":1}},"key":"sGaxTGkY33"}],"urlSource":"https://creativecommons.org/licenses/by/4.0/","key":"L4F7SUxhBN"},{"type":"text","value":" license.","position":{"start":{"line":7,"column":1},"end":{"line":7,"column":1}},"key":"qzOpTdE5q5"}],"key":"Ky6fBqKhqQ"},{"type":"paragraph","position":{"start":{"line":10,"column":1},"end":{"line":10,"column":1}},"children":[{"type":"text","value":"Development of these notes and the ","position":{"start":{"line":10,"column":1},"end":{"line":10,"column":1}},"key":"Xc9UZmpgoy"},{"type":"link","url":"https://github.com/climlab/climlab","position":{"start":{"line":10,"column":1},"end":{"line":10,"column":1}},"children":[{"type":"text","value":"climlab software","position":{"start":{"line":10,"column":1},"end":{"line":10,"column":1}},"key":"Z8f0Y9r0oC"}],"urlSource":"https://github.com/climlab/climlab","error":true,"key":"PO5C031ZHl"},{"type":"text","value":" is partially supported by the National Science Foundation under award AGS-1455071 to Brian Rose. Any opinions, findings, conclusions or recommendations expressed here are mine and do not necessarily reflect the views of the National Science Foundation.","position":{"start":{"line":10,"column":1},"end":{"line":10,"column":1}},"key":"TebsKqsT52"}],"key":"S5FSzXxG5v"},{"type":"thematicBreak","position":{"start":{"line":11,"column":1},"end":{"line":11,"column":1}},"key":"Ik4aLMxlfR"}],"key":"YxRaRJuUFW"}],"key":"qYOIjYFRtW"},"references":{"cite":{"order":[],"data":{}}},"footer":{"navigation":{"prev":{"title":"Radiative Equilibrium","url":"/courseware/radeq","group":"The Climate Laboratory"},"next":{"title":"Climate sensitivity and feedback","url":"/courseware/sensitivity-feedback","group":"The Climate Laboratory"}}},"domain":"http://localhost:3000"}